Workbook

Sheet Dashboard
A1: DSA PATTERNS MASTER TRACKER — Product-Based Company Prep
A2: Update Status in 'Problem Tracker' — everything here recalculates automatically.
D3: Bucket | E3: Total | F3: Solved | G3: % Done
A4: Total Problems | B4: =COUNTA('Problem Tracker'!$G$2:$G$541) -> 540 | D4: Easy | E4: =COUNTIF('Problem Tracker'!$H:$H,"Easy") -> 104 | F4: =(COUNTIFS('Problem Tracker'!$M:$M,"Solved",'Problem Tracker'!$H:$H,"Easy")+COUNTIFS('Problem Tracker'!$M:$M,"Mastered",'Problem Tracker'!$H:$H,"Easy")) -> 1 | G4: =IF(E4=0,0,F4/E4) -> 0.0096153846
A5: Solved / Mastered | B5: =(COUNTIFS('Problem Tracker'!$M:$M,"Solved")+COUNTIFS('Problem Tracker'!$M:$M,"Mastered")) -> 1 | D5: Medium | E5: =COUNTIF('Problem Tracker'!$H:$H,"Medium") -> 340 | F5: =(COUNTIFS('Problem Tracker'!$M:$M,"Solved",'Problem Tracker'!$H:$H,"Medium")+COUNTIFS('Problem Tracker'!$M:$M,"Mastered",'Problem Tracker'!$H:$H,"Medium")) -> 0 | G5: =IF(E5=0,0,F5/E5) -> 0
A6: Overall Progress | B6: =IF(B4=0,0,B5/B4) -> 0.0018518519 | D6: Hard | E6: =COUNTIF('Problem Tracker'!$H:$H,"Hard") -> 96 | F6: =(COUNTIFS('Problem Tracker'!$M:$M,"Solved",'Problem Tracker'!$H:$H,"Hard")+COUNTIFS('Problem Tracker'!$M:$M,"Mastered",'Problem Tracker'!$H:$H,"Hard")) -> 0 | G6: =IF(E6=0,0,F6/E6) -> 0
A7: Due for Revision Today | B7: =COUNTIFS('Problem Tracker'!$P$2:$P$541,"<="&TODAY(),'Problem Tracker'!$M$2:$M$541,"<>Mastered") -> 0 | D7: ★ Blind 75 | E7: =COUNTIF('Problem Tracker'!$I:$I,"★ Blind 75") -> 75 | F7: =(COUNTIFS('Problem Tracker'!$M:$M,"Solved",'Problem Tracker'!$I:$I,"★ Blind 75")+COUNTIFS('Problem Tracker'!$M:$M,"Mastered",'Problem Tracker'!$I:$I,"★ Blind 75")) -> 1 | G7: =IF(E7=0,0,F7/E7) -> 0.013333333
D8: ◆ NeetCode 150 (extra) | E8: =COUNTIF('Problem Tracker'!$I:$I,"◆ NeetCode 150") -> 76 | F8: =(COUNTIFS('Problem Tracker'!$M:$M,"Solved",'Problem Tracker'!$I:$I,"◆ NeetCode 150")+COUNTIFS('Problem Tracker'!$M:$M,"Mastered",'Problem Tracker'!$I:$I,"◆ NeetCode 150")) -> 0 | G8: =IF(E8=0,0,F8/E8) -> 0
D9: ● Must-Know Classic | E9: =COUNTIF('Problem Tracker'!$I:$I,"● Must-Know Classic") -> 84 | F9: =(COUNTIFS('Problem Tracker'!$M:$M,"Solved",'Problem Tracker'!$I:$I,"● Must-Know Classic")+COUNTIFS('Problem Tracker'!$M:$M,"Mastered",'Problem Tracker'!$I:$I,"● Must-Know Classic")) -> 0 | G9: =IF(E9=0,0,F9/E9) -> 0
D10: P0 + P1 (core set) | E10: =COUNTIF('Problem Tracker'!$J:$J,"P0")+COUNTIF('Problem Tracker'!$J:$J,"P1") -> 235 | F10: =(COUNTIFS('Problem Tracker'!$M:$M,"Solved",'Problem Tracker'!$J:$J,"P0")+COUNTIFS('Problem Tracker'!$M:$M,"Mastered",'Problem Tracker'!$J:$J,"P0"))+(COUNTIFS('Problem Tracker'!$M:$M,"Solved",'Problem Tracker'!$J:$J,"P1")+COUNTIFS('Problem Tracker'!$M:$M,"Mastered",'Problem Tracker'!$J:$J,"P1")) -> 1 | G10: =IF(E10=0,0,F10/E10) -> 0.0042553191
A12: PROGRESS BY DATA STRUCTURE
A13: Data Structure | B13: Week | C13: Total | D13: Easy | E13: Medium | F13: Hard | G13: ★ Blind 75 | H13: Solved | I13: % Done
A14: Hash Map & Set | B14: W01 | C14: =COUNTIFS('Problem Tracker'!$C:$C,"Hash Map & Set") -> 13 | D14: =COUNTIFS('Problem Tracker'!$C:$C,"Hash Map & Set",'Problem Tracker'!$H:$H,"Easy") -> 6 | E14: =COUNTIFS('Problem Tracker'!$C:$C,"Hash Map & Set",'Problem Tracker'!$H:$H,"Medium") -> 7 | F14: =COUNTIFS('Problem Tracker'!$C:$C,"Hash Map & Set",'Problem Tracker'!$H:$H,"Hard") -> 0 | G14: =COUNTIFS('Problem Tracker'!$C:$C,"Hash Map & Set",'Problem Tracker'!$I:$I,"★ Blind 75") -> 3 | H14: =(COUNTIFS('Problem Tracker'!$M:$M,"Solved",'Problem Tracker'!$C:$C,"Hash Map & Set")+COUNTIFS('Problem Tracker'!$M:$M,"Mastered",'Problem Tracker'!$C:$C,"Hash Map & Set")) -> 1 | I14: =IF(C14=0,0,H14/C14) -> 0.076923077
A15: Array | B15: W02–03 | C15: =COUNTIFS('Problem Tracker'!$C:$C,"Array") -> 74 | D15: =COUNTIFS('Problem Tracker'!$C:$C,"Array",'Problem Tracker'!$H:$H,"Easy") -> 15 | E15: =COUNTIFS('Problem Tracker'!$C:$C,"Array",'Problem Tracker'!$H:$H,"Medium") -> 49 | F15: =COUNTIFS('Problem Tracker'!$C:$C,"Array",'Problem Tracker'!$H:$H,"Hard") -> 10 | G15: =COUNTIFS('Problem Tracker'!$C:$C,"Array",'Problem Tracker'!$I:$I,"★ Blind 75") -> 10 | H15: =(COUNTIFS('Problem Tracker'!$M:$M,"Solved",'Problem Tracker'!$C:$C,"Array")+COUNTIFS('Problem Tracker'!$M:$M,"Mastered",'Problem Tracker'!$C:$C,"Array")) -> 0 | I15: =IF(C15=0,0,H15/C15) -> 0
A16: String | B16: W03 | C16: =COUNTIFS('Problem Tracker'!$C:$C,"String") -> 34 | D16: =COUNTIFS('Problem Tracker'!$C:$C,"String",'Problem Tracker'!$H:$H,"Easy") -> 13 | E16: =COUNTIFS('Problem Tracker'!$C:$C,"String",'Problem Tracker'!$H:$H,"Medium") -> 15 | F16: =COUNTIFS('Problem Tracker'!$C:$C,"String",'Problem Tracker'!$H:$H,"Hard") -> 6 | G16: =COUNTIFS('Problem Tracker'!$C:$C,"String",'Problem Tracker'!$I:$I,"★ Blind 75") -> 5 | H16: =(COUNTIFS('Problem Tracker'!$M:$M,"Solved",'Problem Tracker'!$C:$C,"String")+COUNTIFS('Problem Tracker'!$M:$M,"Mastered",'Problem Tracker'!$C:$C,"String")) -> 0 | I16: =IF(C16=0,0,H16/C16) -> 0
A17: Matrix (2D Array) | B17: W03 | C17: =COUNTIFS('Problem Tracker'!$C:$C,"Matrix (2D Array)") -> 8 | D17: =COUNTIFS('Problem Tracker'!$C:$C,"Matrix (2D Array)",'Problem Tracker'!$H:$H,"Easy") -> 2 | E17: =COUNTIFS('Problem Tracker'!$C:$C,"Matrix (2D Array)",'Problem Tracker'!$H:$H,"Medium") -> 6 | F17: =COUNTIFS('Problem Tracker'!$C:$C,"Matrix (2D Array)",'Problem Tracker'!$H:$H,"Hard") -> 0 | G17: =COUNTIFS('Problem Tracker'!$C:$C,"Matrix (2D Array)",'Problem Tracker'!$I:$I,"★ Blind 75") -> 3 | H17: =(COUNTIFS('Problem Tracker'!$M:$M,"Solved",'Problem Tracker'!$C:$C,"Matrix (2D Array)")+COUNTIFS('Problem Tracker'!$M:$M,"Mastered",'Problem Tracker'!$C:$C,"Matrix (2D Array)")) -> 0 | I17: =IF(C17=0,0,H17/C17) -> 0
A18: Stack | B18: W04 | C18: =COUNTIFS('Problem Tracker'!$C:$C,"Stack") -> 29 | D18: =COUNTIFS('Problem Tracker'!$C:$C,"Stack",'Problem Tracker'!$H:$H,"Easy") -> 5 | E18: =COUNTIFS('Problem Tracker'!$C:$C,"Stack",'Problem Tracker'!$H:$H,"Medium") -> 19 | F18: =COUNTIFS('Problem Tracker'!$C:$C,"Stack",'Problem Tracker'!$H:$H,"Hard") -> 5 | G18: =COUNTIFS('Problem Tracker'!$C:$C,"Stack",'Problem Tracker'!$I:$I,"★ Blind 75") -> 1 | H18: =(COUNTIFS('Problem Tracker'!$M:$M,"Solved",'Problem Tracker'!$C:$C,"Stack")+COUNTIFS('Problem Tracker'!$M:$M,"Mastered",'Problem Tracker'!$C:$C,"Stack")) -> 0 | I18: =IF(C18=0,0,H18/C18) -> 0
A19: Queue / Deque | B19: W04 | C19: =COUNTIFS('Problem Tracker'!$C:$C,"Queue / Deque") -> 5 | D19: =COUNTIFS('Problem Tracker'!$C:$C,"Queue / Deque",'Problem Tracker'!$H:$H,"Easy") -> 1 | E19: =COUNTIFS('Problem Tracker'!$C:$C,"Queue / Deque",'Problem Tracker'!$H:$H,"Medium") -> 4 | F19: =COUNTIFS('Problem Tracker'!$C:$C,"Queue / Deque",'Problem Tracker'!$H:$H,"Hard") -> 0 | G19: =COUNTIFS('Problem Tracker'!$C:$C,"Queue / Deque",'Problem Tracker'!$I:$I,"★ Blind 75") -> 0 | H19: =(COUNTIFS('Problem Tracker'!$M:$M,"Solved",'Problem Tracker'!$C:$C,"Queue / Deque")+COUNTIFS('Problem Tracker'!$M:$M,"Mastered",'Problem Tracker'!$C:$C,"Queue / Deque")) -> 0 | I19: =IF(C19=0,0,H19/C19) -> 0
A20: Binary Search | B20: W05 | C20: =COUNTIFS('Problem Tracker'!$C:$C,"Binary Search") -> 28 | D20: =COUNTIFS('Problem Tracker'!$C:$C,"Binary Search",'Problem Tracker'!$H:$H,"Easy") -> 5 | E20: =COUNTIFS('Problem Tracker'!$C:$C,"Binary Search",'Problem Tracker'!$H:$H,"Medium") -> 18 | F20: =COUNTIFS('Problem Tracker'!$C:$C,"Binary Search",'Problem Tracker'!$H:$H,"Hard") -> 5 | G20: =COUNTIFS('Problem Tracker'!$C:$C,"Binary Search",'Problem Tracker'!$I:$I,"★ Blind 75") -> 2 | H20: =(COUNTIFS('Problem Tracker'!$M:$M,"Solved",'Problem Tracker'!$C:$C,"Binary Search")+COUNTIFS('Problem Tracker'!$M:$M,"Mastered",'Problem Tracker'!$C:$C,"Binary Search")) -> 0 | I20: =IF(C20=0,0,H20/C20) -> 0
A21: Linked List | B21: W06 | C21: =COUNTIFS('Problem Tracker'!$C:$C,"Linked List") -> 25 | D21: =COUNTIFS('Problem Tracker'!$C:$C,"Linked List",'Problem Tracker'!$H:$H,"Easy") -> 8 | E21: =COUNTIFS('Problem Tracker'!$C:$C,"Linked List",'Problem Tracker'!$H:$H,"Medium") -> 16 | F21: =COUNTIFS('Problem Tracker'!$C:$C,"Linked List",'Problem Tracker'!$H:$H,"Hard") -> 1 | G21: =COUNTIFS('Problem Tracker'!$C:$C,"Linked List",'Problem Tracker'!$I:$I,"★ Blind 75") -> 5 | H21: =(COUNTIFS('Problem Tracker'!$M:$M,"Solved",'Problem Tracker'!$C:$C,"Linked List")+COUNTIFS('Problem Tracker'!$M:$M,"Mastered",'Problem Tracker'!$C:$C,"Linked List")) -> 0 | I21: =IF(C21=0,0,H21/C21) -> 0
A22: Intervals | B22: W06 | C22: =COUNTIFS('Problem Tracker'!$C:$C,"Intervals") -> 14 | D22: =COUNTIFS('Problem Tracker'!$C:$C,"Intervals",'Problem Tracker'!$H:$H,"Easy") -> 2 | E22: =COUNTIFS('Problem Tracker'!$C:$C,"Intervals",'Problem Tracker'!$H:$H,"Medium") -> 7 | F22: =COUNTIFS('Problem Tracker'!$C:$C,"Intervals",'Problem Tracker'!$H:$H,"Hard") -> 5 | G22: =COUNTIFS('Problem Tracker'!$C:$C,"Intervals",'Problem Tracker'!$I:$I,"★ Blind 75") -> 5 | H22: =(COUNTIFS('Problem Tracker'!$M:$M,"Solved",'Problem Tracker'!$C:$C,"Intervals")+COUNTIFS('Problem Tracker'!$M:$M,"Mastered",'Problem Tracker'!$C:$C,"Intervals")) -> 0 | I22: =IF(C22=0,0,H22/C22) -> 0
A23: Trees | B23: W07–08 | C23: =COUNTIFS('Problem Tracker'!$C:$C,"Trees") -> 50 | D23: =COUNTIFS('Problem Tracker'!$C:$C,"Trees",'Problem Tracker'!$H:$H,"Easy") -> 19 | E23: =COUNTIFS('Problem Tracker'!$C:$C,"Trees",'Problem Tracker'!$H:$H,"Medium") -> 28 | F23: =COUNTIFS('Problem Tracker'!$C:$C,"Trees",'Problem Tracker'!$H:$H,"Hard") -> 3 | G23: =COUNTIFS('Problem Tracker'!$C:$C,"Trees",'Problem Tracker'!$I:$I,"★ Blind 75") -> 11 | H23: =(COUNTIFS('Problem Tracker'!$M:$M,"Solved",'Problem Tracker'!$C:$C,"Trees")+COUNTIFS('Problem Tracker'!$M:$M,"Mastered",'Problem Tracker'!$C:$C,"Trees")) -> 0 | I23: =IF(C23=0,0,H23/C23) -> 0
A24: Heap / Priority Queue | B24: W09 | C24: =COUNTIFS('Problem Tracker'!$C:$C,"Heap / Priority Queue") -> 19 | D24: =COUNTIFS('Problem Tracker'!$C:$C,"Heap / Priority Queue",'Problem Tracker'!$H:$H,"Easy") -> 2 | E24: =COUNTIFS('Problem Tracker'!$C:$C,"Heap / Priority Queue",'Problem Tracker'!$H:$H,"Medium") -> 10 | F24: =COUNTIFS('Problem Tracker'!$C:$C,"Heap / Priority Queue",'Problem Tracker'!$H:$H,"Hard") -> 7 | G24: =COUNTIFS('Problem Tracker'!$C:$C,"Heap / Priority Queue",'Problem Tracker'!$I:$I,"★ Blind 75") -> 3 | H24: =(COUNTIFS('Problem Tracker'!$M:$M,"Solved",'Problem Tracker'!$C:$C,"Heap / Priority Queue")+COUNTIFS('Problem Tracker'!$M:$M,"Mastered",'Problem Tracker'!$C:$C,"Heap / Priority Queue")) -> 0 | I24: =IF(C24=0,0,H24/C24) -> 0
A25: Recursion & Backtracking | B25: W10 | C25: =COUNTIFS('Problem Tracker'!$C:$C,"Recursion & Backtracking") -> 27 | D25: =COUNTIFS('Problem Tracker'!$C:$C,"Recursion & Backtracking",'Problem Tracker'!$H:$H,"Easy") -> 1 | E25: =COUNTIFS('Problem Tracker'!$C:$C,"Recursion & Backtracking",'Problem Tracker'!$H:$H,"Medium") -> 20 | F25: =COUNTIFS('Problem Tracker'!$C:$C,"Recursion & Backtracking",'Problem Tracker'!$H:$H,"Hard") -> 6 | G25: =COUNTIFS('Problem Tracker'!$C:$C,"Recursion & Backtracking",'Problem Tracker'!$I:$I,"★ Blind 75") -> 1 | H25: =(COUNTIFS('Problem Tracker'!$M:$M,"Solved",'Problem Tracker'!$C:$C,"Recursion & Backtracking")+COUNTIFS('Problem Tracker'!$M:$M,"Mastered",'Problem Tracker'!$C:$C,"Recursion & Backtracking")) -> 0 | I25: =IF(C25=0,0,H25/C25) -> 0
A26: Trie | B26: W10 | C26: =COUNTIFS('Problem Tracker'!$C:$C,"Trie") -> 10 | D26: =COUNTIFS('Problem Tracker'!$C:$C,"Trie",'Problem Tracker'!$H:$H,"Easy") -> 0 | E26: =COUNTIFS('Problem Tracker'!$C:$C,"Trie",'Problem Tracker'!$H:$H,"Medium") -> 7 | F26: =COUNTIFS('Problem Tracker'!$C:$C,"Trie",'Problem Tracker'!$H:$H,"Hard") -> 3 | G26: =COUNTIFS('Problem Tracker'!$C:$C,"Trie",'Problem Tracker'!$I:$I,"★ Blind 75") -> 3 | H26: =(COUNTIFS('Problem Tracker'!$M:$M,"Solved",'Problem Tracker'!$C:$C,"Trie")+COUNTIFS('Problem Tracker'!$M:$M,"Mastered",'Problem Tracker'!$C:$C,"Trie")) -> 0 | I26: =IF(C26=0,0,H26/C26) -> 0
A27: Graphs | B27: W11–12 | C27: =COUNTIFS('Problem Tracker'!$C:$C,"Graphs") -> 57 | D27: =COUNTIFS('Problem Tracker'!$C:$C,"Graphs",'Problem Tracker'!$H:$H,"Easy") -> 4 | E27: =COUNTIFS('Problem Tracker'!$C:$C,"Graphs",'Problem Tracker'!$H:$H,"Medium") -> 43 | F27: =COUNTIFS('Problem Tracker'!$C:$C,"Graphs",'Problem Tracker'!$H:$H,"Hard") -> 10 | G27: =COUNTIFS('Problem Tracker'!$C:$C,"Graphs",'Problem Tracker'!$I:$I,"★ Blind 75") -> 7 | H27: =(COUNTIFS('Problem Tracker'!$M:$M,"Solved",'Problem Tracker'!$C:$C,"Graphs")+COUNTIFS('Problem Tracker'!$M:$M,"Mastered",'Problem Tracker'!$C:$C,"Graphs")) -> 0 | I27: =IF(C27=0,0,H27/C27) -> 0
A28: Greedy | B28: W13 | C28: =COUNTIFS('Problem Tracker'!$C:$C,"Greedy") -> 15 | D28: =COUNTIFS('Problem Tracker'!$C:$C,"Greedy",'Problem Tracker'!$H:$H,"Easy") -> 3 | E28: =COUNTIFS('Problem Tracker'!$C:$C,"Greedy",'Problem Tracker'!$H:$H,"Medium") -> 10 | F28: =COUNTIFS('Problem Tracker'!$C:$C,"Greedy",'Problem Tracker'!$H:$H,"Hard") -> 2 | G28: =COUNTIFS('Problem Tracker'!$C:$C,"Greedy",'Problem Tracker'!$I:$I,"★ Blind 75") -> 1 | H28: =(COUNTIFS('Problem Tracker'!$M:$M,"Solved",'Problem Tracker'!$C:$C,"Greedy")+COUNTIFS('Problem Tracker'!$M:$M,"Mastered",'Problem Tracker'!$C:$C,"Greedy")) -> 0 | I28: =IF(C28=0,0,H28/C28) -> 0
A29: Bit Manipulation | B29: W13 | C29: =COUNTIFS('Problem Tracker'!$C:$C,"Bit Manipulation") -> 15 | D29: =COUNTIFS('Problem Tracker'!$C:$C,"Bit Manipulation",'Problem Tracker'!$H:$H,"Easy") -> 7 | E29: =COUNTIFS('Problem Tracker'!$C:$C,"Bit Manipulation",'Problem Tracker'!$H:$H,"Medium") -> 8 | F29: =COUNTIFS('Problem Tracker'!$C:$C,"Bit Manipulation",'Problem Tracker'!$H:$H,"Hard") -> 0 | G29: =COUNTIFS('Problem Tracker'!$C:$C,"Bit Manipulation",'Problem Tracker'!$I:$I,"★ Blind 75") -> 5 | H29: =(COUNTIFS('Problem Tracker'!$M:$M,"Solved",'Problem Tracker'!$C:$C,"Bit Manipulation")+COUNTIFS('Problem Tracker'!$M:$M,"Mastered",'Problem Tracker'!$C:$C,"Bit Manipulation")) -> 0 | I29: =IF(C29=0,0,H29/C29) -> 0
A30: Dynamic Programming | B30: W14–16 | C30: =COUNTIFS('Problem Tracker'!$C:$C,"Dynamic Programming") -> 71 | D30: =COUNTIFS('Problem Tracker'!$C:$C,"Dynamic Programming",'Problem Tracker'!$H:$H,"Easy") -> 3 | E30: =COUNTIFS('Problem Tracker'!$C:$C,"Dynamic Programming",'Problem Tracker'!$H:$H,"Medium") -> 47 | F30: =COUNTIFS('Problem Tracker'!$C:$C,"Dynamic Programming",'Problem Tracker'!$H:$H,"Hard") -> 21 | G30: =COUNTIFS('Problem Tracker'!$C:$C,"Dynamic Programming",'Problem Tracker'!$I:$I,"★ Blind 75") -> 10 | H30: =(COUNTIFS('Problem Tracker'!$M:$M,"Solved",'Problem Tracker'!$C:$C,"Dynamic Programming")+COUNTIFS('Problem Tracker'!$M:$M,"Mastered",'Problem Tracker'!$C:$C,"Dynamic Programming")) -> 0 | I30: =IF(C30=0,0,H30/C30) -> 0
A31: Sorting | B31: W16 | C31: =COUNTIFS('Problem Tracker'!$C:$C,"Sorting") -> 12 | D31: =COUNTIFS('Problem Tracker'!$C:$C,"Sorting",'Problem Tracker'!$H:$H,"Easy") -> 2 | E31: =COUNTIFS('Problem Tracker'!$C:$C,"Sorting",'Problem Tracker'!$H:$H,"Medium") -> 7 | F31: =COUNTIFS('Problem Tracker'!$C:$C,"Sorting",'Problem Tracker'!$H:$H,"Hard") -> 3 | G31: =COUNTIFS('Problem Tracker'!$C:$C,"Sorting",'Problem Tracker'!$I:$I,"★ Blind 75") -> 0 | H31: =(COUNTIFS('Problem Tracker'!$M:$M,"Solved",'Problem Tracker'!$C:$C,"Sorting")+COUNTIFS('Problem Tracker'!$M:$M,"Mastered",'Problem Tracker'!$C:$C,"Sorting")) -> 0 | I31: =IF(C31=0,0,H31/C31) -> 0
A32: Math & Geometry | B32: W16 | C32: =COUNTIFS('Problem Tracker'!$C:$C,"Math & Geometry") -> 13 | D32: =COUNTIFS('Problem Tracker'!$C:$C,"Math & Geometry",'Problem Tracker'!$H:$H,"Easy") -> 4 | E32: =COUNTIFS('Problem Tracker'!$C:$C,"Math & Geometry",'Problem Tracker'!$H:$H,"Medium") -> 8 | F32: =COUNTIFS('Problem Tracker'!$C:$C,"Math & Geometry",'Problem Tracker'!$H:$H,"Hard") -> 1 | G32: =COUNTIFS('Problem Tracker'!$C:$C,"Math & Geometry",'Problem Tracker'!$I:$I,"★ Blind 75") -> 0 | H32: =(COUNTIFS('Problem Tracker'!$M:$M,"Solved",'Problem Tracker'!$C:$C,"Math & Geometry")+COUNTIFS('Problem Tracker'!$M:$M,"Mastered",'Problem Tracker'!$C:$C,"Math & Geometry")) -> 0 | I32: =IF(C32=0,0,H32/C32) -> 0
A33: Design | B33: W17 | C33: =COUNTIFS('Problem Tracker'!$C:$C,"Design") -> 14 | D33: =COUNTIFS('Problem Tracker'!$C:$C,"Design",'Problem Tracker'!$H:$H,"Easy") -> 2 | E33: =COUNTIFS('Problem Tracker'!$C:$C,"Design",'Problem Tracker'!$H:$H,"Medium") -> 9 | F33: =COUNTIFS('Problem Tracker'!$C:$C,"Design",'Problem Tracker'!$H:$H,"Hard") -> 3 | G33: =COUNTIFS('Problem Tracker'!$C:$C,"Design",'Problem Tracker'!$I:$I,"★ Blind 75") -> 0 | H33: =(COUNTIFS('Problem Tracker'!$M:$M,"Solved",'Problem Tracker'!$C:$C,"Design")+COUNTIFS('Problem Tracker'!$M:$M,"Mastered",'Problem Tracker'!$C:$C,"Design")) -> 0 | I33: =IF(C33=0,0,H33/C33) -> 0
A34: Advanced Data Structures | B34: W17 | C34: =COUNTIFS('Problem Tracker'!$C:$C,"Advanced Data Structures") -> 7 | D34: =COUNTIFS('Problem Tracker'!$C:$C,"Advanced Data Structures",'Problem Tracker'!$H:$H,"Easy") -> 0 | E34: =COUNTIFS('Problem Tracker'!$C:$C,"Advanced Data Structures",'Problem Tracker'!$H:$H,"Medium") -> 2 | F34: =COUNTIFS('Problem Tracker'!$C:$C,"Advanced Data Structures",'Problem Tracker'!$H:$H,"Hard") -> 5 | G34: =COUNTIFS('Problem Tracker'!$C:$C,"Advanced Data Structures",'Problem Tracker'!$I:$I,"★ Blind 75") -> 0 | H34: =(COUNTIFS('Problem Tracker'!$M:$M,"Solved",'Problem Tracker'!$C:$C,"Advanced Data Structures")+COUNTIFS('Problem Tracker'!$M:$M,"Mastered",'Problem Tracker'!$C:$C,"Advanced Data Structures")) -> 0 | I34: =IF(C34=0,0,H34/C34) -> 0
A35: TOTAL | C35: =SUM(C14:C34) -> 540 | D35: =SUM(D14:D34) -> 104 | E35: =SUM(E14:E34) -> 340 | F35: =SUM(F14:F34) -> 96 | G35: =SUM(G14:G34) -> 75 | H35: =SUM(H14:H34) -> 1 | I35: =IF(C35=0,0,H35/C35) -> 0.0018518519
A37: 17-WEEK STUDY PLAN
A38: Week | B38: Focus | F38: Problems | G38: Solved | H38: % Done
A39: W01 | B39: Hash Map & Set: Hashing Fundamentals | F39: =COUNTIF('Problem Tracker'!$B:$B,A39) -> 13 | G39: =COUNTIFS('Problem Tracker'!$B:$B,A39,'Problem Tracker'!$M:$M,"Solved")+COUNTIFS('Problem Tracker'!$B:$B,A39,'Problem Tracker'!$M:$M,"Mastered") -> 1 | H39: =IF(F39=0,0,G39/F39) -> 0.076923077
A40: W02 | B40: Array: Two Pointers; Array: In-place Manipulation | F40: =COUNTIF('Problem Tracker'!$B:$B,A40) -> 27 | G40: =COUNTIFS('Problem Tracker'!$B:$B,A40,'Problem Tracker'!$M:$M,"Solved")+COUNTIFS('Problem Tracker'!$B:$B,A40,'Problem Tracker'!$M:$M,"Mastered") -> 0 | H40: =IF(F40=0,0,G40/F40) -> 0
A41: W03 | B41: Array: Sliding Window; Array: Prefix Sum; Array: Kadane's / Subarray; String: Palindrome; String: Anagram / Frequency; String: Pattern Matching; String: Parsing & Simulation; Matrix (2D Array): Matrix Manipulation | F41: =COUNTIF('Problem Tracker'!$B:$B,A41) -> 89 | G41: =COUNTIFS('Problem Tracker'!$B:$B,A41,'Problem Tracker'!$M:$M,"Solved")+COUNTIFS('Problem Tracker'!$B:$B,A41,'Problem Tracker'!$M:$M,"Mastered") -> 0 | H41: =IF(F41=0,0,G41/F41) -> 0
A42: W04 | B42: Stack: Classic Stack; Stack: Monotonic Stack; Stack: Stack Design; Queue / Deque: Queue Patterns | F42: =COUNTIF('Problem Tracker'!$B:$B,A42) -> 34 | G42: =COUNTIFS('Problem Tracker'!$B:$B,A42,'Problem Tracker'!$M:$M,"Solved")+COUNTIFS('Problem Tracker'!$B:$B,A42,'Problem Tracker'!$M:$M,"Mastered") -> 0 | H42: =IF(F42=0,0,G42/F42) -> 0
A43: W05 | B43: Binary Search: Binary Search on Index; Binary Search: Binary Search on Answer | F43: =COUNTIF('Problem Tracker'!$B:$B,A43) -> 28 | G43: =COUNTIFS('Problem Tracker'!$B:$B,A43,'Problem Tracker'!$M:$M,"Solved")+COUNTIFS('Problem Tracker'!$B:$B,A43,'Problem Tracker'!$M:$M,"Mastered") -> 0 | H43: =IF(F43=0,0,G43/F43) -> 0
A44: W06 | B44: Linked List: Fast & Slow Pointers; Linked List: In-place Reversal; Linked List: Pointer Manipulation; Intervals: Interval Patterns | F44: =COUNTIF('Problem Tracker'!$B:$B,A44) -> 39 | G44: =COUNTIFS('Problem Tracker'!$B:$B,A44,'Problem Tracker'!$M:$M,"Solved")+COUNTIFS('Problem Tracker'!$B:$B,A44,'Problem Tracker'!$M:$M,"Mastered") -> 0 | H44: =IF(F44=0,0,G44/F44) -> 0
A45: W07 | B45: Trees: DFS Traversal; Trees: BFS / Level Order | F45: =COUNTIF('Problem Tracker'!$B:$B,A45) -> 19 | G45: =COUNTIFS('Problem Tracker'!$B:$B,A45,'Problem Tracker'!$M:$M,"Solved")+COUNTIFS('Problem Tracker'!$B:$B,A45,'Problem Tracker'!$M:$M,"Mastered") -> 0 | H45: =IF(F45=0,0,G45/F45) -> 0
A46: W08 | B46: Trees: Recursive Return Values; Trees: Binary Search Tree; Trees: Construction & Serialization | F46: =COUNTIF('Problem Tracker'!$B:$B,A46) -> 31 | G46: =COUNTIFS('Problem Tracker'!$B:$B,A46,'Problem Tracker'!$M:$M,"Solved")+COUNTIFS('Problem Tracker'!$B:$B,A46,'Problem Tracker'!$M:$M,"Mastered") -> 0 | H46: =IF(F46=0,0,G46/F46) -> 0
A47: W09 | B47: Heap / Priority Queue: Heap Patterns | F47: =COUNTIF('Problem Tracker'!$B:$B,A47) -> 19 | G47: =COUNTIFS('Problem Tracker'!$B:$B,A47,'Problem Tracker'!$M:$M,"Solved")+COUNTIFS('Problem Tracker'!$B:$B,A47,'Problem Tracker'!$M:$M,"Mastered") -> 0 | H47: =IF(F47=0,0,G47/F47) -> 0
A48: W10 | B48: Recursion & Backtracking: Recursion Basics; Recursion & Backtracking: Backtracking; Trie: Trie Patterns | F48: =COUNTIF('Problem Tracker'!$B:$B,A48) -> 37 | G48: =COUNTIFS('Problem Tracker'!$B:$B,A48,'Problem Tracker'!$M:$M,"Solved")+COUNTIFS('Problem Tracker'!$B:$B,A48,'Problem Tracker'!$M:$M,"Mastered") -> 0 | H48: =IF(F48=0,0,G48/F48) -> 0
A49: W11 | B49: Graphs: Grid Graphs (DFS / BFS); Graphs: Graph Traversal; Graphs: Topological Sort | F49: =COUNTIF('Problem Tracker'!$B:$B,A49) -> 38 | G49: =COUNTIFS('Problem Tracker'!$B:$B,A49,'Problem Tracker'!$M:$M,"Solved")+COUNTIFS('Problem Tracker'!$B:$B,A49,'Problem Tracker'!$M:$M,"Mastered") -> 0 | H49: =IF(F49=0,0,G49/F49) -> 0
A50: W12 | B50: Graphs: Union-Find (DSU); Graphs: Shortest Path (Weighted); Graphs: Advanced Graph | F50: =COUNTIF('Problem Tracker'!$B:$B,A50) -> 19 | G50: =COUNTIFS('Problem Tracker'!$B:$B,A50,'Problem Tracker'!$M:$M,"Solved")+COUNTIFS('Problem Tracker'!$B:$B,A50,'Problem Tracker'!$M:$M,"Mastered") -> 0 | H50: =IF(F50=0,0,G50/F50) -> 0
... A55: W17 | B55: Design: System / Data-Structure Design; Advanced Data Structures: Range Query Structures | F55: =COUNTIF('Problem Tracker'!$B:$B,A55) -> 21 | G55: =COUNTIFS('Problem Tracker'!$B:$B,A55,'Problem Tracker'!$M:$M,"Solved")+COUNTIFS('Problem Tracker'!$B:$B,A55,'Problem Tracker'!$M:$M,"Mastered") -> 0 | H55: =IF(F55=0,0,G55/F55) -> 0

Sheet Pattern Map
A1: Data Structure | B1: Pattern | C1: Sub-Pattern | D1: Interview Weight | E1: How to Recognize (Trigger) | F1: Core Technique / Template | G1: Complexity | H1: Week | I1: Problems | J1: Easy | K1: Medium | L1: Hard | M1: Solved | N1: % Done
A2: ▌ HASH MAP & SET | I2: =COUNTIF('Problem Tracker'!$C:$C,"Hash Map & Set") -> 13 | M2: =COUNTIFS('Problem Tracker'!$C:$C,"Hash Map & Set",'Problem Tracker'!$M:$M,"Solved")+COUNTIFS('Problem Tracker'!$C:$C,"Hash Map & Set",'Problem Tracker'!$M:$M,"Mastered") -> 1 | N2: =IF(I2=0,0,M2/I2) -> 0.076923077
A3: Hash Map & Set | B3: Hashing Fundamentals | C3: Complement Lookup | D3: 🔥 Very High | E3: Find a pair/tuple summing to target in unsorted data | F3: Store value→index; for each x check target−x in map | G3: O(n) time, O(n) space | H3: W01 | I3: =COUNTIFS('Problem Tracker'!$C:$C,"Hash Map & Set",'Problem Tracker'!$D:$D,"Hashing Fundamentals",'Problem Tracker'!$E:$E,"Complement Lookup") -> 3 | J3: =COUNTIFS('Problem Tracker'!$C:$C,"Hash Map & Set",'Problem Tracker'!$D:$D,"Hashing Fundamentals",'Problem Tracker'!$E:$E,"Complement Lookup",'Problem Tracker'!$H:$H,"Easy") -> 1 | K3: =COUNTIFS('Problem Tracker'!$C:$C,"Hash Map & Set",'Problem Tracker'!$D:$D,"Hashing Fundamentals",'Problem Tracker'!$E:$E,"Complement Lookup",'Problem Tracker'!$H:$H,"Medium") -> 2 | L3: =COUNTIFS('Problem Tracker'!$C:$C,"Hash Map & Set",'Problem Tracker'!$D:$D,"Hashing Fundamentals",'Problem Tracker'!$E:$E,"Complement Lookup",'Problem Tracker'!$H:$H,"Hard") -> 0 | M3: =COUNTIFS('Problem Tracker'!$C:$C,"Hash Map & Set",'Problem Tracker'!$D:$D,"Hashing Fundamentals",'Problem Tracker'!$E:$E,"Complement Lookup",'Problem Tracker'!$M:$M,"Solved")+COUNTIFS('Problem Tracker'!$C:$C,"Hash Map & Set",'Problem Tracker'!$D:$D,"Hashing Fundamentals",'Problem Tracker'!$E:$E,"Complement Lookup",'Problem Tracker'!$M:$M,"Mastered") -> 1 | N3: =IF(I3=0,0,M3/I3) -> 0.33333333
A4: Hash Map & Set | B4: Hashing Fundamentals | C4: Frequency Counting | D4: 🔥 Very High | E4: Counts, duplicates, 'appears k times', compare multisets | F4: Counter / int[26] array; compare or scan counts | G4: O(n) | H4: W01 | I4: =COUNTIFS('Problem Tracker'!$C:$C,"Hash Map & Set",'Problem Tracker'!$D:$D,"Hashing Fundamentals",'Problem Tracker'!$E:$E,"Frequency Counting") -> 4 | J4: =COUNTIFS('Problem Tracker'!$C:$C,"Hash Map & Set",'Problem Tracker'!$D:$D,"Hashing Fundamentals",'Problem Tracker'!$E:$E,"Frequency Counting",'Problem Tracker'!$H:$H,"Easy") -> 3 | K4: =COUNTIFS('Problem Tracker'!$C:$C,"Hash Map & Set",'Problem Tracker'!$D:$D,"Hashing Fundamentals",'Problem Tracker'!$E:$E,"Frequency Counting",'Problem Tracker'!$H:$H,"Medium") -> 1 | L4: =COUNTIFS('Problem Tracker'!$C:$C,"Hash Map & Set",'Problem Tracker'!$D:$D,"Hashing Fundamentals",'Problem Tracker'!$E:$E,"Frequency Counting",'Problem Tracker'!$H:$H,"Hard") -> 0 | M4: =COUNTIFS('Problem Tracker'!$C:$C,"Hash Map & Set",'Problem Tracker'!$D:$D,"Hashing Fundamentals",'Problem Tracker'!$E:$E,"Frequency Counting",'Problem Tracker'!$M:$M,"Solved")+COUNTIFS('Problem Tracker'!$C:$C,"Hash Map & Set",'Problem Tracker'!$D:$D,"Hashing Fundamentals",'Problem Tracker'!$E:$E,"Frequency Counting",'Problem Tracker'!$M:$M,"Mastered") -> 0 | N4: =IF(I4=0,0,M4/I4) -> 0
A5: Hash Map & Set | B5: Hashing Fundamentals | C5: Grouping by Canonical Key | D5: High | E5: Group items that are 'equivalent' (anagrams, shifts, same content) | F5: Compute a canonical key (sorted string / count tuple) → list | G5: O(n·k) | H5: W01 | I5: =COUNTIFS('Problem Tracker'!$C:$C,"Hash Map & Set",'Problem Tracker'!$D:$D,"Hashing Fundamentals",'Problem Tracker'!$E:$E,"Grouping by Canonical Key") -> 3 | J5: =COUNTIFS('Problem Tracker'!$C:$C,"Hash Map & Set",'Problem Tracker'!$D:$D,"Hashing Fundamentals",'Problem Tracker'!$E:$E,"Grouping by Canonical Key",'Problem Tracker'!$H:$H,"Easy") -> 0 | K5: =COUNTIFS('Problem Tracker'!$C:$C,"Hash Map & Set",'Problem Tracker'!$D:$D,"Hashing Fundamentals",'Problem Tracker'!$E:$E,"Grouping by Canonical Key",'Problem Tracker'!$H:$H,"Medium") -> 3 | L5: =COUNTIFS('Problem Tracker'!$C:$C,"Hash Map & Set",'Problem Tracker'!$D:$D,"Hashing Fundamentals",'Problem Tracker'!$E:$E,"Grouping by Canonical Key",'Problem Tracker'!$H:$H,"Hard") -> 0 | M5: =COUNTIFS('Problem Tracker'!$C:$C,"Hash Map & Set",'Problem Tracker'!$D:$D,"Hashing Fundamentals",'Problem Tracker'!$E:$E,"Grouping by Canonical Key",'Problem Tracker'!$M:$M,"Solved")+COUNTIFS('Problem Tracker'!$C:$C,"Hash Map & Set",'Problem Tracker'!$D:$D,"Hashing Fundamentals",'Problem Tracker'!$E:$E,"Grouping by Canonical Key",'Problem Tracker'!$M:$M,"Mastered") -> 0 | N5: =IF(I5=0,0,M5/I5) -> 0
A6: Hash Map & Set | B6: Hashing Fundamentals | C6: Set Existence / Sequence Building | D6: 🔥 Very High | E6: Membership checks, consecutive runs, cycle detection on values | F6: HashSet; only start counting from sequence starts | G6: O(n) | H6: W01 | I6: =COUNTIFS('Problem Tracker'!$C:$C,"Hash Map & Set",'Problem Tracker'!$D:$D,"Hashing Fundamentals",'Problem Tracker'!$E:$E,"Set Existence / Sequence Building") -> 3 | J6: =COUNTIFS('Problem Tracker'!$C:$C,"Hash Map & Set",'Problem Tracker'!$D:$D,"Hashing Fundamentals",'Problem Tracker'!$E:$E,"Set Existence / Sequence Building",'Problem Tracker'!$H:$H,"Easy") -> 2 | K6: =COUNTIFS('Problem Tracker'!$C:$C,"Hash Map & Set",'Problem Tracker'!$D:$D,"Hashing Fundamentals",'Problem Tracker'!$E:$E,"Set Existence / Sequence Building",'Problem Tracker'!$H:$H,"Medium") -> 1 | L6: =COUNTIFS('Problem Tracker'!$C:$C,"Hash Map & Set",'Problem Tracker'!$D:$D,"Hashing Fundamentals",'Problem Tracker'!$E:$E,"Set Existence / Sequence Building",'Problem Tracker'!$H:$H,"Hard") -> 0 | M6: =COUNTIFS('Problem Tracker'!$C:$C,"Hash Map & Set",'Problem Tracker'!$D:$D,"Hashing Fundamentals",'Problem Tracker'!$E:$E,"Set Existence / Sequence Building",'Problem Tracker'!$M:$M,"Solved")+COUNTIFS('Problem Tracker'!$C:$C,"Hash Map & Set",'Problem Tracker'!$D:$D,"Hashing Fundamentals",'Problem Tracker'!$E:$E,"Set Existence / Sequence Building",'Problem Tracker'!$M:$M,"Mastered") -> 0 | N6: =IF(I6=0,0,M6/I6) -> 0
A7: ▌ ARRAY | I7: =COUNTIF('Problem Tracker'!$C:$C,"Array") -> 74 | M7: =COUNTIFS('Problem Tracker'!$C:$C,"Array",'Problem Tracker'!$M:$M,"Solved")+COUNTIFS('Problem Tracker'!$C:$C,"Array",'Problem Tracker'!$M:$M,"Mastered") -> 0 | N7: =IF(I7=0,0,M7/I7) -> 0
A8: Array | B8: Two Pointers | C8: Opposite Ends (Converging) | D8: 🔥 Very High | E8: Sorted array / palindrome / pair with target / maximize area | F8: l=0, r=n−1; move the pointer that can improve the answer | G8: O(n) | H8: W02 | I8: =COUNTIFS('Problem Tracker'!$C:$C,"Array",'Problem Tracker'!$D:$D,"Two Pointers",'Problem Tracker'!$E:$E,"Opposite Ends (Converging)") -> 6 | J8: =COUNTIFS('Problem Tracker'!$C:$C,"Array",'Problem Tracker'!$D:$D,"Two Pointers",'Problem Tracker'!$E:$E,"Opposite Ends (Converging)",'Problem Tracker'!$H:$H,"Easy") -> 2 | K8: =COUNTIFS('Problem Tracker'!$C:$C,"Array",'Problem Tracker'!$D:$D,"Two Pointers",'Problem Tracker'!$E:$E,"Opposite Ends (Converging)",'Problem Tracker'!$H:$H,"Medium") -> 3 | L8: =COUNTIFS('Problem Tracker'!$C:$C,"Array",'Problem Tracker'!$D:$D,"Two Pointers",'Problem Tracker'!$E:$E,"Opposite Ends (Converging)",'Problem Tracker'!$H:$H,"Hard") -> 1 | M8: =COUNTIFS('Problem Tracker'!$C:$C,"Array",'Problem Tracker'!$D:$D,"Two Pointers",'Problem Tracker'!$E:$E,"Opposite Ends (Converging)",'Problem Tracker'!$M:$M,"Solved")+COUNTIFS('Problem Tracker'!$C:$C,"Array",'Problem Tracker'!$D:$D,"Two Pointers",'Problem Tracker'!$E:$E,"Opposite Ends (Converging)",'Problem Tracker'!$M:$M,"Mastered") -> 0 | N8: =IF(I8=0,0,M8/I8) -> 0
A9: Array | B9: Two Pointers | C9: Same Direction (Read / Write) | D9: 🔥 Very High | E9: In-place remove/compact/merge; 'without extra space' | F9: Slow write pointer, fast read pointer | G9: O(n), O(1) space | H9: W02 | I9: =COUNTIFS('Problem Tracker'!$C:$C,"Array",'Problem Tracker'!$D:$D,"Two Pointers",'Problem Tracker'!$E:$E,"Same Direction (Read / Write)") -> 6 | J9: =COUNTIFS('Problem Tracker'!$C:$C,"Array",'Problem Tracker'!$D:$D,"Two Pointers",'Problem Tracker'!$E:$E,"Same Direction (Read / Write)",'Problem Tracker'!$H:$H,"Easy") -> 5 | K9: =COUNTIFS('Problem Tracker'!$C:$C,"Array",'Problem Tracker'!$D:$D,"Two Pointers",'Problem Tracker'!$E:$E,"Same Direction (Read / Write)",'Problem Tracker'!$H:$H,"Medium") -> 1 | L9: =COUNTIFS('Problem Tracker'!$C:$C,"Array",'Problem Tracker'!$D:$D,"Two Pointers",'Problem Tracker'!$E:$E,"Same Direction (Read / Write)",'Problem Tracker'!$H:$H,"Hard") -> 0 | M9: =COUNTIFS('Problem Tracker'!$C:$C,"Array",'Problem Tracker'!$D:$D,"Two Pointers",'Problem Tracker'!$E:$E,"Same Direction (Read / Write)",'Problem Tracker'!$M:$M,"Solved")+COUNTIFS('Problem Tracker'!$C:$C,"Array",'Problem Tracker'!$D:$D,"Two Pointers",'Problem Tracker'!$E:$E,"Same Direction (Read / Write)",'Problem Tracker'!$M:$M,"Mastered") -> 0 | N9: =IF(I9=0,0,M9/I9) -> 0
A10: Array | B10: Two Pointers | C10: k-Sum (3Sum / 4Sum) | D10: 🔥 Very High | E10: Find triplets/quads with target sum, avoid duplicates | F10: Sort; fix i, run two-pointer on rest; skip equal neighbours | G10: O(n^(k−1)) | H10: W02 | I10: =COUNTIFS('Problem Tracker'!$C:$C,"Array",'Problem Tracker'!$D:$D,"Two Pointers",'Problem Tracker'!$E:$E,"k-Sum (3Sum / 4Sum)") -> 4 | J10: =COUNTIFS('Problem Tracker'!$C:$C,"Array",'Problem Tracker'!$D:$D,"Two Pointers",'Problem Tracker'!$E:$E,"k-Sum (3Sum / 4Sum)",'Problem Tracker'!$H:$H,"Easy") -> 0 | K10: =COUNTIFS('Problem Tracker'!$C:$C,"Array",'Problem Tracker'!$D:$D,"Two Pointers",'Problem Tracker'!$E:$E,"k-Sum (3Sum / 4Sum)",'Problem Tracker'!$H:$H,"Medium") -> 4 | L10: =COUNTIFS('Problem Tracker'!$C:$C,"Array",'Problem Tracker'!$D:$D,"Two Pointers",'Problem Tracker'!$E:$E,"k-Sum (3Sum / 4Sum)",'Problem Tracker'!$H:$H,"Hard") -> 0 | M10: =COUNTIFS('Problem Tracker'!$C:$C,"Array",'Problem Tracker'!$D:$D,"Two Pointers",'Problem Tracker'!$E:$E,"k-Sum (3Sum / 4Sum)",'Problem Tracker'!$M:$M,"Solved")+COUNTIFS('Problem Tracker'!$C:$C,"Array",'Problem Tracker'!$D:$D,"Two Pointers",'Problem Tracker'!$E:$E,"k-Sum (3Sum / 4Sum)",'Problem Tracker'!$M:$M,"Mastered") -> 0 | N10: =IF(I10=0,0,M10/I10) -> 0
A11: Array | B11: Two Pointers | C11: Dutch National Flag / Partitioning | D11: High | E11: Sort 0/1/2 or partition around a pivot in one pass | F11: low / mid / high pointers; swap into regions | G11: O(n), O(1) | H11: W02 | I11: =COUNTIFS('Problem Tracker'!$C:$C,"Array",'Problem Tracker'!$D:$D,"Two Pointers",'Problem Tracker'!$E:$E,"Dutch National Flag / Partitioning") -> 3 | J11: =COUNTIFS('Problem Tracker'!$C:$C,"Array",'Problem Tracker'!$D:$D,"Two Pointers",'Problem Tracker'!$E:$E,"Dutch National Flag / Partitioning",'Problem Tracker'!$H:$H,"Easy") -> 1 | K11: =COUNTIFS('Problem Tracker'!$C:$C,"Array",'Problem Tracker'!$D:$D,"Two Pointers",'Problem Tracker'!$E:$E,"Dutch National Flag / Partitioning",'Problem Tracker'!$H:$H,"Medium") -> 2 | L11: =COUNTIFS('Problem Tracker'!$C:$C,"Array",'Problem Tracker'!$D:$D,"Two Pointers",'Problem Tracker'!$E:$E,"Dutch National Flag / Partitioning",'Problem Tracker'!$H:$H,"Hard") -> 0 | M11: =COUNTIFS('Problem Tracker'!$C:$C,"Array",'Problem Tracker'!$D:$D,"Two Pointers",'Problem Tracker'!$E:$E,"Dutch National Flag / Partitioning",'Problem Tracker'!$M:$M,"Solved")+COUNTIFS('Problem Tracker'!$C:$C,"Array",'Problem Tracker'!$D:$D,"Two Pointers",'Problem Tracker'!$E:$E,"Dutch National Flag / Partitioning",'Problem Tracker'!$M:$M,"Mastered") -> 0 | N11: =IF(I11=0,0,M11/I11) -> 0
A12: Array | B12: In-place Manipulation | C12: Rotation / Reversal Trick | D12: High | E12: Rotate by k, reverse segments, O(1) space | F12: Reverse whole, then reverse parts | G12: O(n) | H12: W02 | I12: =COUNTIFS('Problem Tracker'!$C:$C,"Array",'Problem Tracker'!$D:$D,"In-place Manipulation",'Problem Tracker'!$E:$E,"Rotation / Reversal Trick") -> 2 | J12: =COUNTIFS('Problem Tracker'!$C:$C,"Array",'Problem Tracker'!$D:$D,"In-place Manipulation",'Problem Tracker'!$E:$E,"Rotation / Reversal Trick",'Problem Tracker'!$H:$H,"Easy") -> 0 | K12: =COUNTIFS('Problem Tracker'!$C:$C,"Array",'Problem Tracker'!$D:$D,"In-place Manipulation",'Problem Tracker'!$E:$E,"Rotation / Reversal Trick",'Problem Tracker'!$H:$H,"Medium") -> 2 | L12: =COUNTIFS('Problem Tracker'!$C:$C,"Array",'Problem Tracker'!$D:$D,"In-place Manipulation",'Problem Tracker'!$E:$E,"Rotation / Reversal Trick",'Problem Tracker'!$H:$H,"Hard") -> 0 | M12: =COUNTIFS('Problem Tracker'!$C:$C,"Array",'Problem Tracker'!$D:$D,"In-place Manipulation",'Problem Tracker'!$E:$E,"Rotation / Reversal Trick",'Problem Tracker'!$M:$M,"Solved")+COUNTIFS('Problem Tracker'!$C:$C,"Array",'Problem Tracker'!$D:$D,"In-place Manipulation",'Problem Tracker'!$E:$E,"Rotation / Reversal Trick",'Problem Tracker'!$M:$M,"Mastered") -> 0 | N12: =IF(I12=0,0,M12/I12) -> 0
A13: Array | B13: In-place Manipulation | C13: Majority Vote (Boyer–Moore) | D13: High | E13: Element appearing > n/2 or > n/3 times, O(1) space | F13: Candidate + counter; verify in second pass | G13: O(n), O(1) | H13: W02 | I13: =COUNTIFS('Problem Tracker'!$C:$C,"Array",'Problem Tracker'!$D:$D,"In-place Manipulation",'Problem Tracker'!$E:$E,"Majority Vote (Boyer–Moore)") -> 2 | J13: =COUNTIFS('Problem Tracker'!$C:$C,"Array",'Problem Tracker'!$D:$D,"In-place Manipulation",'Problem Tracker'!$E:$E,"Majority Vote (Boyer–Moore)",'Problem Tracker'!$H:$H,"Easy") -> 1 | K13: =COUNTIFS('Problem Tracker'!$C:$C,"Array",'Problem Tracker'!$D:$D,"In-place Manipulation",'Problem Tracker'!$E:$E,"Majority Vote (Boyer–Moore)",'Problem Tracker'!$H:$H,"Medium") -> 1 | L13: =COUNTIFS('Problem Tracker'!$C:$C,"Array",'Problem Tracker'!$D:$D,"In-place Manipulation",'Problem Tracker'!$E:$E,"Majority Vote (Boyer–Moore)",'Problem Tracker'!$H:$H,"Hard") -> 0 | M13: =COUNTIFS('Problem Tracker'!$C:$C,"Array",'Problem Tracker'!$D:$D,"In-place Manipulation",'Problem Tracker'!$E:$E,"Majority Vote (Boyer–Moore)",'Problem Tracker'!$M:$M,"Solved")+COUNTIFS('Problem Tracker'!$C:$C,"Array",'Problem Tracker'!$D:$D,"In-place Manipulation",'Problem Tracker'!$E:$E,"Majority Vote (Boyer–Moore)",'Problem Tracker'!$M:$M,"Mastered") -> 0 | N13: =IF(I13=0,0,M13/I13) -> 0
A14: Array | B14: In-place Manipulation | C14: Cyclic Sort / Index Marking | D14: 🔥 Very High | E14: Numbers in range [1..n] or [0..n]; find missing/duplicate | F14: Place x at index x−1, or negate arr[x] to mark seen | G14: O(n), O(1) | H14: W02 | I14: =COUNTIFS('Problem Tracker'!$C:$C,"Array",'Problem Tracker'!$D:$D,"In-place Manipulation",'Problem Tracker'!$E:$E,"Cyclic Sort / Index Marking") -> 4 | J14: =COUNTIFS('Problem Tracker'!$C:$C,"Array",'Problem Tracker'!$D:$D,"In-place Manipulation",'Problem Tracker'!$E:$E,"Cyclic Sort / Index Marking",'Problem Tracker'!$H:$H,"Easy") -> 1 | K14: =COUNTIFS('Problem Tracker'!$C:$C,"Array",'Problem Tracker'!$D:$D,"In-place Manipulation",'Problem Tracker'!$E:$E,"Cyclic Sort / Index Marking",'Problem Tracker'!$H:$H,"Medium") -> 2 | L14: =COUNTIFS('Problem Tracker'!$C:$C,"Array",'Problem Tracker'!$D:$D,"In-place Manipulation",'Problem Tracker'!$E:$E,"Cyclic Sort / Index Marking",'Problem Tracker'!$H:$H,"Hard") -> 1 | M14: =COUNTIFS('Problem Tracker'!$C:$C,"Array",'Problem Tracker'!$D:$D,"In-place Manipulation",'Problem Tracker'!$E:$E,"Cyclic Sort / Index Marking",'Problem Tracker'!$M:$M,"Solved")+COUNTIFS('Problem Tracker'!$C:$C,"Array",'Problem Tracker'!$D:$D,"In-place Manipulation",'Problem Tracker'!$E:$E,"Cyclic Sort / Index Marking",'Problem Tracker'!$M:$M,"Mastered") -> 0 | N14: =IF(I14=0,0,M14/I14) -> 0
A15: Array | B15: Sliding Window | C15: Fixed Size | D15: 🔥 Very High | E15: 'Subarray/substring of size k', window length is given | F15: Add arr[r], remove arr[r−k]; update answer each step | G15: O(n) | H15: W03 | I15: =COUNTIFS('Problem Tracker'!$C:$C,"Array",'Problem Tracker'!$D:$D,"Sliding Window",'Problem Tracker'!$E:$E,"Fixed Size") -> 7 | J15: =COUNTIFS('Problem Tracker'!$C:$C,"Array",'Problem Tracker'!$D:$D,"Sliding Window",'Problem Tracker'!$E:$E,"Fixed Size",'Problem Tracker'!$H:$H,"Easy") -> 1 | K15: =COUNTIFS('Problem Tracker'!$C:$C,"Array",'Problem Tracker'!$D:$D,"Sliding Window",'Problem Tracker'!$E:$E,"Fixed Size",'Problem Tracker'!$H:$H,"Medium") -> 5 | L15: =COUNTIFS('Problem Tracker'!$C:$C,"Array",'Problem Tracker'!$D:$D,"Sliding Window",'Problem Tracker'!$E:$E,"Fixed Size",'Problem Tracker'!$H:$H,"Hard") -> 1 | M15: =COUNTIFS('Problem Tracker'!$C:$C,"Array",'Problem Tracker'!$D:$D,"Sliding Window",'Problem Tracker'!$E:$E,"Fixed Size",'Problem Tracker'!$M:$M,"Solved")+COUNTIFS('Problem Tracker'!$C:$C,"Array",'Problem Tracker'!$D:$D,"Sliding Window",'Problem Tracker'!$E:$E,"Fixed Size",'Problem Tracker'!$M:$M,"Mastered") -> 0 | N15: =IF(I15=0,0,M15/I15) -> 0
A16: Array | B16: Sliding Window | C16: Variable Size (Longest / Shortest Valid) | D16: 🔥 Very High | E16: 'Longest/shortest subarray such that…' with a monotone validity condition | F16: Expand r; while invalid shrink l; record best | G16: O(n) | H16: W03 | I16: =COUNTIFS('Problem Tracker'!$C:$C,"Array",'Problem Tracker'!$D:$D,"Sliding Window",'Problem Tracker'!$E:$E,"Variable Size (Longest / Shortest Valid)") -> 7 | J16: =COUNTIFS('Problem Tracker'!$C:$C,"Array",'Problem Tracker'!$D:$D,"Sliding Window",'Problem Tracker'!$E:$E,"Variable Size (Longest / Shortest Valid)",'Problem Tracker'!$H:$H,"Easy") -> 0 | K16: =COUNTIFS('Problem Tracker'!$C:$C,"Array",'Problem Tracker'!$D:$D,"Sliding Window",'Problem Tracker'!$E:$E,"Variable Size (Longest / Shortest Valid)",'Problem Tracker'!$H:$H,"Medium") -> 6 | L16: =COUNTIFS('Problem Tracker'!$C:$C,"Array",'Problem Tracker'!$D:$D,"Sliding Window",'Problem Tracker'!$E:$E,"Variable Size (Longest / Shortest Valid)",'Problem Tracker'!$H:$H,"Hard") -> 1 | M16: =COUNTIFS('Problem Tracker'!$C:$C,"Array",'Problem Tracker'!$D:$D,"Sliding Window",'Problem Tracker'!$E:$E,"Variable Size (Longest / Shortest Valid)",'Problem Tracker'!$M:$M,"Solved")+COUNTIFS('Problem Tracker'!$C:$C,"Array",'Problem Tracker'!$D:$D,"Sliding Window",'Problem Tracker'!$E:$E,"Variable Size (Longest / Shortest Valid)",'Problem Tracker'!$M:$M,"Mastered") -> 0 | N16: =IF(I16=0,0,M16/I16) -> 0
A17: Array | B17: Sliding Window | C17: Expand–Shrink Counting (At-Most-K Trick) | D17: High | E17: 'Count subarrays' with exactly K / at most K / product < K | F17: count(exactly K) = atMost(K) − atMost(K−1); add (r−l+1) per step | G17: O(n) | H17: W03 | I17: =COUNTIFS('Problem Tracker'!$C:$C,"Array",'Problem Tracker'!$D:$D,"Sliding Window",'Problem Tracker'!$E:$E,"Expand–Shrink Counting (At-Most-K Trick)") -> 7 | J17: =COUNTIFS('Problem Tracker'!$C:$C,"Array",'Problem Tracker'!$D:$D,"Sliding Window",'Problem Tracker'!$E:$E,"Expand–Shrink Counting (At-Most-K Trick)",'Problem Tracker'!$H:$H,"Easy") -> 0 | K17: =COUNTIFS('Problem Tracker'!$C:$C,"Array",'Problem Tracker'!$D:$D,"Sliding Window",'Problem Tracker'!$E:$E,"Expand–Shrink Counting (At-Most-K Trick)",'Problem Tracker'!$H:$H,"Medium") -> 5 | L17: =COUNTIFS('Problem Tracker'!$C:$C,"Array",'Problem Tracker'!$D:$D,"Sliding Window",'Problem Tracker'!$E:$E,"Expand–Shrink Counting (At-Most-K Trick)",'Problem Tracker'!$H:$H,"Hard") -> 2 | M17: =COUNTIFS('Problem Tracker'!$C:$C,"Array",'Problem Tracker'!$D:$D,"Sliding Window",'Problem Tracker'!$E:$E,"Expand–Shrink Counting (At-Most-K Trick)",'Problem Tracker'!$M:$M,"Solved")+COUNTIFS('Problem Tracker'!$C:$C,"Array",'Problem Tracker'!$D:$D,"Sliding Window",'Problem Tracker'!$E:$E,"Expand–Shrink Counting (At-Most-K Trick)",'Problem Tracker'!$M:$M,"Mastered") -> 0 | N17: =IF(I17=0,0,M17/I17) -> 0
A18: Array | B18: Sliding Window | C18: Monotonic Window (Deque) | D18: High | E18: Max/min of every window, or window with |max−min| ≤ limit | F18: Deque of indices kept increasing/decreasing; pop expired front | G18: O(n) | H18: W03 | I18: =COUNTIFS('Problem Tracker'!$C:$C,"Array",'Problem Tracker'!$D:$D,"Sliding Window",'Problem Tracker'!$E:$E,"Monotonic Window (Deque)") -> 5 | J18: =COUNTIFS('Problem Tracker'!$C:$C,"Array",'Problem Tracker'!$D:$D,"Sliding Window",'Problem Tracker'!$E:$E,"Monotonic Window (Deque)",'Problem Tracker'!$H:$H,"Easy") -> 0 | K18: =COUNTIFS('Problem Tracker'!$C:$C,"Array",'Problem Tracker'!$D:$D,"Sliding Window",'Problem Tracker'!$E:$E,"Monotonic Window (Deque)",'Problem Tracker'!$H:$H,"Medium") -> 2 | L18: =COUNTIFS('Problem Tracker'!$C:$C,"Array",'Problem Tracker'!$D:$D,"Sliding Window",'Problem Tracker'!$E:$E,"Monotonic Window (Deque)",'Problem Tracker'!$H:$H,"Hard") -> 3 | M18: =COUNTIFS('Problem Tracker'!$C:$C,"Array",'Problem Tracker'!$D:$D,"Sliding Window",'Problem Tracker'!$E:$E,"Monotonic Window (Deque)",'Problem Tracker'!$M:$M,"Solved")+COUNTIFS('Problem Tracker'!$C:$C,"Array",'Problem Tracker'!$D:$D,"Sliding Window",'Problem Tracker'!$E:$E,"Monotonic Window (Deque)",'Problem Tracker'!$M:$M,"Mastered") -> 0 | N18: =IF(I18=0,0,M18/I18) -> 0
A19: Array | B19: Prefix Sum | C19: 1D Prefix Sum | D19: 🔥 Very High | E19: Many range-sum queries, pivot/balance index | F19: pre[i+1] = pre[i] + a[i]; sum(l..r) = pre[r+1] − pre[l] | G19: O(n) build, O(1) query | H19: W03 | I19: =COUNTIFS('Problem Tracker'!$C:$C,"Array",'Problem Tracker'!$D:$D,"Prefix Sum",'Problem Tracker'!$E:$E,"1D Prefix Sum") -> 3 | J19: =COUNTIFS('Problem Tracker'!$C:$C,"Array",'Problem Tracker'!$D:$D,"Prefix Sum",'Problem Tracker'!$E:$E,"1D Prefix Sum",'Problem Tracker'!$H:$H,"Easy") -> 3 | K19: =COUNTIFS('Problem Tracker'!$C:$C,"Array",'Problem Tracker'!$D:$D,"Prefix Sum",'Problem Tracker'!$E:$E,"1D Prefix Sum",'Problem Tracker'!$H:$H,"Medium") -> 0 | L19: =COUNTIFS('Problem Tracker'!$C:$C,"Array",'Problem Tracker'!$D:$D,"Prefix Sum",'Problem Tracker'!$E:$E,"1D Prefix Sum",'Problem Tracker'!$H:$H,"Hard") -> 0 | M19: =COUNTIFS('Problem Tracker'!$C:$C,"Array",'Problem Tracker'!$D:$D,"Prefix Sum",'Problem Tracker'!$E:$E,"1D Prefix Sum",'Problem Tracker'!$M:$M,"Solved")+COUNTIFS('Problem Tracker'!$C:$C,"Array",'Problem Tracker'!$D:$D,"Prefix Sum",'Problem Tracker'!$E:$E,"1D Prefix Sum",'Problem Tracker'!$M:$M,"Mastered") -> 0 | N19: =IF(I19=0,0,M19/I19) -> 0
A20: Array | B20: Prefix Sum | C20: Prefix Sum + HashMap | D20: 🔥 Very High | E20: Count/longest subarray with sum = K, divisible by K, equal 0s & 1s (negatives allowed) | F20: Map prefix → count/first index; look up pre − K | G20: O(n) | H20: W03 | I20: =COUNTIFS('Problem Tracker'!$C:$C,"Array",'Problem Tracker'!$D:$D,"Prefix Sum",'Problem Tracker'!$E:$E,"Prefix Sum + HashMap") -> 5 | J20: =COUNTIFS('Problem Tracker'!$C:$C,"Array",'Problem Tracker'!$D:$D,"Prefix Sum",'Problem Tracker'!$E:$E,"Prefix Sum + HashMap",'Problem Tracker'!$H:$H,"Easy") -> 0 | K20: =COUNTIFS('Problem Tracker'!$C:$C,"Array",'Problem Tracker'!$D:$D,"Prefix Sum",'Problem Tracker'!$E:$E,"Prefix Sum + HashMap",'Problem Tracker'!$H:$H,"Medium") -> 4 | L20: =COUNTIFS('Problem Tracker'!$C:$C,"Array",'Problem Tracker'!$D:$D,"Prefix Sum",'Problem Tracker'!$E:$E,"Prefix Sum + HashMap",'Problem Tracker'!$H:$H,"Hard") -> 1 | M20: =COUNTIFS('Problem Tracker'!$C:$C,"Array",'Problem Tracker'!$D:$D,"Prefix Sum",'Problem Tracker'!$E:$E,"Prefix Sum + HashMap",'Problem Tracker'!$M:$M,"Solved")+COUNTIFS('Problem Tracker'!$C:$C,"Array",'Problem Tracker'!$D:$D,"Prefix Sum",'Problem Tracker'!$E:$E,"Prefix Sum + HashMap",'Problem Tracker'!$M:$M,"Mastered") -> 0 | N20: =IF(I20=0,0,M20/I20) -> 0
A21: Array | B21: Prefix Sum | C21: 2D Prefix Sum | D21: High | E21: Rectangle sum queries on a matrix | F21: P[i][j] = a + P[i−1][j] + P[i][j−1] − P[i−1][j−1] | G21: O(mn) build, O(1) query | H21: W03 | I21: =COUNTIFS('Problem Tracker'!$C:$C,"Array",'Problem Tracker'!$D:$D,"Prefix Sum",'Problem Tracker'!$E:$E,"2D Prefix Sum") -> 2 | J21: =COUNTIFS('Problem Tracker'!$C:$C,"Array",'Problem Tracker'!$D:$D,"Prefix Sum",'Problem Tracker'!$E:$E,"2D Prefix Sum",'Problem Tracker'!$H:$H,"Easy") -> 0 | K21: =COUNTIFS('Problem Tracker'!$C:$C,"Array",'Problem Tracker'!$D:$D,"Prefix Sum",'Problem Tracker'!$E:$E,"2D Prefix Sum",'Problem Tracker'!$H:$H,"Medium") -> 2 | L21: =COUNTIFS('Problem Tracker'!$C:$C,"Array",'Problem Tracker'!$D:$D,"Prefix Sum",'Problem Tracker'!$E:$E,"2D Prefix Sum",'Problem Tracker'!$H:$H,"Hard") -> 0 | M21: =COUNTIFS('Problem Tracker'!$C:$C,"Array",'Problem Tracker'!$D:$D,"Prefix Sum",'Problem Tracker'!$E:$E,"2D Prefix Sum",'Problem Tracker'!$M:$M,"Solved")+COUNTIFS('Problem Tracker'!$C:$C,"Array",'Problem Tracker'!$D:$D,"Prefix Sum",'Problem Tracker'!$E:$E,"2D Prefix Sum",'Problem Tracker'!$M:$M,"Mastered") -> 0 | N21: =IF(I21=0,0,M21/I21) -> 0
A22: Array | B22: Prefix Sum | C22: Difference Array | D22: High | E22: Many range-update operations, then read final array | F22: diff[l] += v; diff[r+1] −= v; prefix-sum at the end | G22: O(n + q) | H22: W03 | I22: =COUNTIFS('Problem Tracker'!$C:$C,"Array",'Problem Tracker'!$D:$D,"Prefix Sum",'Problem Tracker'!$E:$E,"Difference Array") -> 3 | J22: =COUNTIFS('Problem Tracker'!$C:$C,"Array",'Problem Tracker'!$D:$D,"Prefix Sum",'Problem Tracker'!$E:$E,"Difference Array",'Problem Tracker'!$H:$H,"Easy") -> 0 | K22: =COUNTIFS('Problem Tracker'!$C:$C,"Array",'Problem Tracker'!$D:$D,"Prefix Sum",'Problem Tracker'!$E:$E,"Difference Array",'Problem Tracker'!$H:$H,"Medium") -> 3 | L22: =COUNTIFS('Problem Tracker'!$C:$C,"Array",'Problem Tracker'!$D:$D,"Prefix Sum",'Problem Tracker'!$E:$E,"Difference Array",'Problem Tracker'!$H:$H,"Hard") -> 0 | M22: =COUNTIFS('Problem Tracker'!$C:$C,"Array",'Problem Tracker'!$D:$D,"Prefix Sum",'Problem Tracker'!$E:$E,"Difference Array",'Problem Tracker'!$M:$M,"Solved")+COUNTIFS('Problem Tracker'!$C:$C,"Array",'Problem Tracker'!$D:$D,"Prefix Sum",'Problem Tracker'!$E:$E,"Difference Array",'Problem Tracker'!$M:$M,"Mastered") -> 0 | N22: =IF(I22=0,0,M22/I22) -> 0
A23: Array | B23: Prefix Sum | C23: Prefix–Suffix Products / Splits | D23: 🔥 Very High | E23: Answer for i depends on everything left and right of i | F23: Build left pass and right pass arrays (or one running var) | G23: O(n) | H23: W03 | I23: =COUNTIFS('Problem Tracker'!$C:$C,"Array",'Problem Tracker'!$D:$D,"Prefix Sum",'Problem Tracker'!$E:$E,"Prefix–Suffix Products / Splits") -> 2 | J23: =COUNTIFS('Problem Tracker'!$C:$C,"Array",'Problem Tracker'!$D:$D,"Prefix Sum",'Problem Tracker'!$E:$E,"Prefix–Suffix Products / Splits",'Problem Tracker'!$H:$H,"Easy") -> 0 | K23: =COUNTIFS('Problem Tracker'!$C:$C,"Array",'Problem Tracker'!$D:$D,"Prefix Sum",'Problem Tracker'!$E:$E,"Prefix–Suffix Products / Splits",'Problem Tracker'!$H:$H,"Medium") -> 2 | L23: =COUNTIFS('Problem Tracker'!$C:$C,"Array",'Problem Tracker'!$D:$D,"Prefix Sum",'Problem Tracker'!$E:$E,"Prefix–Suffix Products / Splits",'Problem Tracker'!$H:$H,"Hard") -> 0 | M23: =COUNTIFS('Problem Tracker'!$C:$C,"Array",'Problem Tracker'!$D:$D,"Prefix Sum",'Problem Tracker'!$E:$E,"Prefix–Suffix Products / Splits",'Problem Tracker'!$M:$M,"Solved")+COUNTIFS('Problem Tracker'!$C:$C,"Array",'Problem Tracker'!$D:$D,"Prefix Sum",'Problem Tracker'!$E:$E,"Prefix–Suffix Products / Splits",'Problem Tracker'!$M:$M,"Mastered") -> 0 | N23: =IF(I23=0,0,M23/I23) -> 0
A24: Array | B24: Kadane's / Subarray | C24: Running Min / Max (Kadane Core) | D24: 🔥 Very High | E24: Max profit / max contiguous sum in one pass | F24: cur = max(x, cur + x); best = max(best, cur) | G24: O(n), O(1) | H24: W03 | I24: =COUNTIFS('Problem Tracker'!$C:$C,"Array",'Problem Tracker'!$D:$D,"Kadane's / Subarray",'Problem Tracker'!$E:$E,"Running Min / Max (Kadane Core)") -> 3 | J24: =COUNTIFS('Problem Tracker'!$C:$C,"Array",'Problem Tracker'!$D:$D,"Kadane's / Subarray",'Problem Tracker'!$E:$E,"Running Min / Max (Kadane Core)",'Problem Tracker'!$H:$H,"Easy") -> 1 | K24: =COUNTIFS('Problem Tracker'!$C:$C,"Array",'Problem Tracker'!$D:$D,"Kadane's / Subarray",'Problem Tracker'!$E:$E,"Running Min / Max (Kadane Core)",'Problem Tracker'!$H:$H,"Medium") -> 2 | L24: =COUNTIFS('Problem Tracker'!$C:$C,"Array",'Problem Tracker'!$D:$D,"Kadane's / Subarray",'Problem Tracker'!$E:$E,"Running Min / Max (Kadane Core)",'Problem Tracker'!$H:$H,"Hard") -> 0 | M24: =COUNTIFS('Problem Tracker'!$C:$C,"Array",'Problem Tracker'!$D:$D,"Kadane's / Subarray",'Problem Tracker'!$E:$E,"Running Min / Max (Kadane Core)",'Problem Tracker'!$M:$M,"Solved")+COUNTIFS('Problem Tracker'!$C:$C,"Array",'Problem Tracker'!$D:$D,"Kadane's / Subarray",'Problem Tracker'!$E:$E,"Running Min / Max (Kadane Core)",'Problem Tracker'!$M:$M,"Mastered") -> 0 | N24: =IF(I24=0,0,M24/I24) -> 0
A25: Array | B25: Kadane's / Subarray | C25: Kadane Variants (Product / Circular / Deletion) | D25: High | E25: Negatives flip sign, wrap-around, one skip allowed | F25: Track both max & min; total − minSubarray for circular | G25: O(n) | H25: W03 | I25: =COUNTIFS('Problem Tracker'!$C:$C,"Array",'Problem Tracker'!$D:$D,"Kadane's / Subarray",'Problem Tracker'!$E:$E,"Kadane Variants (Product / Circular / Deletion)") -> 3 | J25: =COUNTIFS('Problem Tracker'!$C:$C,"Array",'Problem Tracker'!$D:$D,"Kadane's / Subarray",'Problem Tracker'!$E:$E,"Kadane Variants (Product / Circular / Deletion)",'Problem Tracker'!$H:$H,"Easy") -> 0 | K25: =COUNTIFS('Problem Tracker'!$C:$C,"Array",'Problem Tracker'!$D:$D,"Kadane's / Subarray",'Problem Tracker'!$E:$E,"Kadane Variants (Product / Circular / Deletion)",'Problem Tracker'!$H:$H,"Medium") -> 3 | L25: =COUNTIFS('Problem Tracker'!$C:$C,"Array",'Problem Tracker'!$D:$D,"Kadane's / Subarray",'Problem Tracker'!$E:$E,"Kadane Variants (Product / Circular / Deletion)",'Problem Tracker'!$H:$H,"Hard") -> 0 | M25: =COUNTIFS('Problem Tracker'!$C:$C,"Array",'Problem Tracker'!$D:$D,"Kadane's / Subarray",'Problem Tracker'!$E:$E,"Kadane Variants (Product / Circular / Deletion)",'Problem Tracker'!$M:$M,"Solved")+COUNTIFS('Problem Tracker'!$C:$C,"Array",'Problem Tracker'!$D:$D,"Kadane's / Subarray",'Problem Tracker'!$E:$E,"Kadane Variants (Product / Circular / Deletion)",'Problem Tracker'!$M:$M,"Mastered") -> 0 | N25: =IF(I25=0,0,M25/I25) -> 0
A26: ▌ STRING | I26: =COUNTIF('Problem Tracker'!$C:$C,"String") -> 34 | M26: =COUNTIFS('Problem Tracker'!$C:$C,"String",'Problem Tracker'!$M:$M,"Solved")+COUNTIFS('Problem Tracker'!$C:$C,"String",'Problem Tracker'!$M:$M,"Mastered") -> 0 | N26: =IF(I26=0,0,M26/I26) -> 0
A27: String | B27: Palindrome | C27: Two-Pointer Check | D27: High | E27: Is it (almost) a palindrome? | F27: Compare ends; on mismatch try skipping one side | G27: O(n) | H27: W03 | I27: =COUNTIFS('Problem Tracker'!$C:$C,"String",'Problem Tracker'!$D:$D,"Palindrome",'Problem Tracker'!$E:$E,"Two-Pointer Check") -> 2 | J27: =COUNTIFS('Problem Tracker'!$C:$C,"String",'Problem Tracker'!$D:$D,"Palindrome",'Problem Tracker'!$E:$E,"Two-Pointer Check",'Problem Tracker'!$H:$H,"Easy") -> 2 | K27: =COUNTIFS('Problem Tracker'!$C:$C,"String",'Problem Tracker'!$D:$D,"Palindrome",'Problem Tracker'!$E:$E,"Two-Pointer Check",'Problem Tracker'!$H:$H,"Medium") -> 0 | L27: =COUNTIFS('Problem Tracker'!$C:$C,"String",'Problem Tracker'!$D:$D,"Palindrome",'Problem Tracker'!$E:$E,"Two-Pointer Check",'Problem Tracker'!$H:$H,"Hard") -> 0 | M27: =COUNTIFS('Problem Tracker'!$C:$C,"String",'Problem Tracker'!$D:$D,"Palindrome",'Problem Tracker'!$E:$E,"Two-Pointer Check",'Problem Tracker'!$M:$M,"Solved")+COUNTIFS('Problem Tracker'!$C:$C,"String",'Problem Tracker'!$D:$D,"Palindrome",'Problem Tracker'!$E:$E,"Two-Pointer Check",'Problem Tracker'!$M:$M,"Mastered") -> 0 | N27: =IF(I27=0,0,M27/I27) -> 0
A28: String | B28: Palindrome | C28: Expand Around Center | D28: 🔥 Very High | E28: Longest / count of palindromic substrings | F28: For each of 2n−1 centres expand while s[l]==s[r] | G28: O(n²) | H28: W03 | I28: =COUNTIFS('Problem Tracker'!$C:$C,"String",'Problem Tracker'!$D:$D,"Palindrome",'Problem Tracker'!$E:$E,"Expand Around Center") -> 2 | J28: =COUNTIFS('Problem Tracker'!$C:$C,"String",'Problem Tracker'!$D:$D,"Palindrome",'Problem Tracker'!$E:$E,"Expand Around Center",'Problem Tracker'!$H:$H,"Easy") -> 0 | K28: =COUNTIFS('Problem Tracker'!$C:$C,"String",'Problem Tracker'!$D:$D,"Palindrome",'Problem Tracker'!$E:$E,"Expand Around Center",'Problem Tracker'!$H:$H,"Medium") -> 2 | L28: =COUNTIFS('Problem Tracker'!$C:$C,"String",'Problem Tracker'!$D:$D,"Palindrome",'Problem Tracker'!$E:$E,"Expand Around Center",'Problem Tracker'!$H:$H,"Hard") -> 0 | M28: =COUNTIFS('Problem Tracker'!$C:$C,"String",'Problem Tracker'!$D:$D,"Palindrome",'Problem Tracker'!$E:$E,"Expand Around Center",'Problem Tracker'!$M:$M,"Solved")+COUNTIFS('Problem Tracker'!$C:$C,"String",'Problem Tracker'!$D:$D,"Palindrome",'Problem Tracker'!$E:$E,"Expand Around Center",'Problem Tracker'!$M:$M,"Mastered") -> 0 | N28: =IF(I28=0,0,M28/I28) -> 0
A29: String | B29: Palindrome | C29: Palindrome Construction | D29: Medium | E29: Build longest palindrome / make string palindrome by adding chars | F29: Character parity counts, or KMP on s + '#' + rev(s) | G29: O(n) | H29: W03 | I29: =COUNTIFS('Problem Tracker'!$C:$C,"String",'Problem Tracker'!$D:$D,"Palindrome",'Problem Tracker'!$E:$E,"Palindrome Construction") -> 3 | J29: =COUNTIFS('Problem Tracker'!$C:$C,"String",'Problem Tracker'!$D:$D,"Palindrome",'Problem Tracker'!$E:$E,"Palindrome Construction",'Problem Tracker'!$H:$H,"Easy") -> 1 | K29: =COUNTIFS('Problem Tracker'!$C:$C,"String",'Problem Tracker'!$D:$D,"Palindrome",'Problem Tracker'!$E:$E,"Palindrome Construction",'Problem Tracker'!$H:$H,"Medium") -> 0 | L29: =COUNTIFS('Problem Tracker'!$C:$C,"String",'Problem Tracker'!$D:$D,"Palindrome",'Problem Tracker'!$E:$E,"Palindrome Construction",'Problem Tracker'!$H:$H,"Hard") -> 2 | M29: =COUNTIFS('Problem Tracker'!$C:$C,"String",'Problem Tracker'!$D:$D,"Palindrome",'Problem Tracker'!$E:$E,"Palindrome Construction",'Problem Tracker'!$M:$M,"Solved")+COUNTIFS('Problem Tracker'!$C:$C,"String",'Problem Tracker'!$D:$D,"Palindrome",'Problem Tracker'!$E:$E,"Palindrome Construction",'Problem Tracker'!$M:$M,"Mastered") -> 0 | N29: =IF(I29=0,0,M29/I29) -> 0
A30: String | B30: Anagram / Frequency | C30: Character Count Comparison | D30: 🔥 Very High | E30: Anagram, ransom note, 'same characters', first unique | F30: int[26] counts; compare or decrement | G30: O(n) | H30: W03 | I30: =COUNTIFS('Problem Tracker'!$C:$C,"String",'Problem Tracker'!$D:$D,"Anagram / Frequency",'Problem Tracker'!$E:$E,"Character Count Comparison") -> 6 | J30: =COUNTIFS('Problem Tracker'!$C:$C,"String",'Problem Tracker'!$D:$D,"Anagram / Frequency",'Problem Tracker'!$E:$E,"Character Count Comparison",'Problem Tracker'!$H:$H,"Easy") -> 3 | K30: =COUNTIFS('Problem Tracker'!$C:$C,"String",'Problem Tracker'!$D:$D,"Anagram / Frequency",'Problem Tracker'!$E:$E,"Character Count Comparison",'Problem Tracker'!$H:$H,"Medium") -> 3 | L30: =COUNTIFS('Problem Tracker'!$C:$C,"String",'Problem Tracker'!$D:$D,"Anagram / Frequency",'Problem Tracker'!$E:$E,"Character Count Comparison",'Problem Tracker'!$H:$H,"Hard") -> 0 | M30: =COUNTIFS('Problem Tracker'!$C:$C,"String",'Problem Tracker'!$D:$D,"Anagram / Frequency",'Problem Tracker'!$E:$E,"Character Count Comparison",'Problem Tracker'!$M:$M,"Solved")+COUNTIFS('Problem Tracker'!$C:$C,"String",'Problem Tracker'!$D:$D,"Anagram / Frequency",'Problem Tracker'!$E:$E,"Character Count Comparison",'Problem Tracker'!$M:$M,"Mastered") -> 0 | N30: =IF(I30=0,0,M30/I30) -> 0
A31: String | B31: Anagram / Frequency | C31: Bijection / Mapping | D31: Medium | E31: Isomorphic strings, word pattern, one-to-one mapping | F31: Two maps (a→b and b→a) or compare first-seen indices | G31: O(n) | H31: W03 | I31: =COUNTIFS('Problem Tracker'!$C:$C,"String",'Problem Tracker'!$D:$D,"Anagram / Frequency",'Problem Tracker'!$E:$E,"Bijection / Mapping") -> 3 | J31: =COUNTIFS('Problem Tracker'!$C:$C,"String",'Problem Tracker'!$D:$D,"Anagram / Frequency",'Problem Tracker'!$E:$E,"Bijection / Mapping",'Problem Tracker'!$H:$H,"Easy") -> 2 | K31: =COUNTIFS('Problem Tracker'!$C:$C,"String",'Problem Tracker'!$D:$D,"Anagram / Frequency",'Problem Tracker'!$E:$E,"Bijection / Mapping",'Problem Tracker'!$H:$H,"Medium") -> 1 | L31: =COUNTIFS('Problem Tracker'!$C:$C,"String",'Problem Tracker'!$D:$D,"Anagram / Frequency",'Problem Tracker'!$E:$E,"Bijection / Mapping",'Problem Tracker'!$H:$H,"Hard") -> 0 | M31: =COUNTIFS('Problem Tracker'!$C:$C,"String",'Problem Tracker'!$D:$D,"Anagram / Frequency",'Problem Tracker'!$E:$E,"Bijection / Mapping",'Problem Tracker'!$M:$M,"Solved")+COUNTIFS('Problem Tracker'!$C:$C,"String",'Problem Tracker'!$D:$D,"Anagram / Frequency",'Problem Tracker'!$E:$E,"Bijection / Mapping",'Problem Tracker'!$M:$M,"Mastered") -> 0 | N31: =IF(I31=0,0,M31/I31) -> 0
A32: String | B32: Pattern Matching | C32: KMP (Prefix Function) | D32: High | E32: Find pattern in text in linear time; longest prefix = suffix | F32: Build LPS array; never move text pointer back | G32: O(n + m) | H32: W03 | I32: =COUNTIFS('Problem Tracker'!$C:$C,"String",'Problem Tracker'!$D:$D,"Pattern Matching",'Problem Tracker'!$E:$E,"KMP (Prefix Function)") -> 3 | J32: =COUNTIFS('Problem Tracker'!$C:$C,"String",'Problem Tracker'!$D:$D,"Pattern Matching",'Problem Tracker'!$E:$E,"KMP (Prefix Function)",'Problem Tracker'!$H:$H,"Easy") -> 2 | K32: =COUNTIFS('Problem Tracker'!$C:$C,"String",'Problem Tracker'!$D:$D,"Pattern Matching",'Problem Tracker'!$E:$E,"KMP (Prefix Function)",'Problem Tracker'!$H:$H,"Medium") -> 0 | L32: =COUNTIFS('Problem Tracker'!$C:$C,"String",'Problem Tracker'!$D:$D,"Pattern Matching",'Problem Tracker'!$E:$E,"KMP (Prefix Function)",'Problem Tracker'!$H:$H,"Hard") -> 1 | M32: =COUNTIFS('Problem Tracker'!$C:$C,"String",'Problem Tracker'!$D:$D,"Pattern Matching",'Problem Tracker'!$E:$E,"KMP (Prefix Function)",'Problem Tracker'!$M:$M,"Solved")+COUNTIFS('Problem Tracker'!$C:$C,"String",'Problem Tracker'!$D:$D,"Pattern Matching",'Problem Tracker'!$E:$E,"KMP (Prefix Function)",'Problem Tracker'!$M:$M,"Mastered") -> 0 | N32: =IF(I32=0,0,M32/I32) -> 0
A33: String | B33: Pattern Matching | C33: Rabin–Karp / Rolling Hash | D33: Medium | E33: Repeated / duplicate substrings of length L | F33: Polynomial rolling hash; binary search on L if needed | G33: O(n) avg | H33: W03 | I33: =COUNTIFS('Problem Tracker'!$C:$C,"String",'Problem Tracker'!$D:$D,"Pattern Matching",'Problem Tracker'!$E:$E,"Rabin–Karp / Rolling Hash") -> 3 | J33: =COUNTIFS('Problem Tracker'!$C:$C,"String",'Problem Tracker'!$D:$D,"Pattern Matching",'Problem Tracker'!$E:$E,"Rabin–Karp / Rolling Hash",'Problem Tracker'!$H:$H,"Easy") -> 0 | K33: =COUNTIFS('Problem Tracker'!$C:$C,"String",'Problem Tracker'!$D:$D,"Pattern Matching",'Problem Tracker'!$E:$E,"Rabin–Karp / Rolling Hash",'Problem Tracker'!$H:$H,"Medium") -> 2 | L33: =COUNTIFS('Problem Tracker'!$C:$C,"String",'Problem Tracker'!$D:$D,"Pattern Matching",'Problem Tracker'!$E:$E,"Rabin–Karp / Rolling Hash",'Problem Tracker'!$H:$H,"Hard") -> 1 | M33: =COUNTIFS('Problem Tracker'!$C:$C,"String",'Problem Tracker'!$D:$D,"Pattern Matching",'Problem Tracker'!$E:$E,"Rabin–Karp / Rolling Hash",'Problem Tracker'!$M:$M,"Solved")+COUNTIFS('Problem Tracker'!$C:$C,"String",'Problem Tracker'!$D:$D,"Pattern Matching",'Problem Tracker'!$E:$E,"Rabin–Karp / Rolling Hash",'Problem Tracker'!$M:$M,"Mastered") -> 0 | N33: =IF(I33=0,0,M33/I33) -> 0
A34: String | B34: Pattern Matching | C34: Z-Algorithm | D34: Medium | E34: Match of every suffix with prefix | F34: Z-array with [l, r] box | G34: O(n) | H34: W03 | I34: =COUNTIFS('Problem Tracker'!$C:$C,"String",'Problem Tracker'!$D:$D,"Pattern Matching",'Problem Tracker'!$E:$E,"Z-Algorithm") -> 1 | J34: =COUNTIFS('Problem Tracker'!$C:$C,"String",'Problem Tracker'!$D:$D,"Pattern Matching",'Problem Tracker'!$E:$E,"Z-Algorithm",'Problem Tracker'!$H:$H,"Easy") -> 0 | K34: =COUNTIFS('Problem Tracker'!$C:$C,"String",'Problem Tracker'!$D:$D,"Pattern Matching",'Problem Tracker'!$E:$E,"Z-Algorithm",'Problem Tracker'!$H:$H,"Medium") -> 0 | L34: =COUNTIFS('Problem Tracker'!$C:$C,"String",'Problem Tracker'!$D:$D,"Pattern Matching",'Problem Tracker'!$E:$E,"Z-Algorithm",'Problem Tracker'!$H:$H,"Hard") -> 1 | M34: =COUNTIFS('Problem Tracker'!$C:$C,"String",'Problem Tracker'!$D:$D,"Pattern Matching",'Problem Tracker'!$E:$E,"Z-Algorithm",'Problem Tracker'!$M:$M,"Solved")+COUNTIFS('Problem Tracker'!$C:$C,"String",'Problem Tracker'!$D:$D,"Pattern Matching",'Problem Tracker'!$E:$E,"Z-Algorithm",'Problem Tracker'!$M:$M,"Mastered") -> 0 | N34: =IF(I34=0,0,M34/I34) -> 0
A35: String | B35: Parsing & Simulation | C35: String Parsing / Conversion | D35: High | E35: Convert formats, atoi, roman numerals, reverse words | F35: Careful index walking, edge cases (sign, overflow, spaces) | G35: O(n) | H35: W03 | I35: =COUNTIFS('Problem Tracker'!$C:$C,"String",'Problem Tracker'!$D:$D,"Parsing & Simulation",'Problem Tracker'!$E:$E,"String Parsing / Conversion") -> 7 | J35: =COUNTIFS('Problem Tracker'!$C:$C,"String",'Problem Tracker'!$D:$D,"Parsing & Simulation",'Problem Tracker'!$E:$E,"String Parsing / Conversion",'Problem Tracker'!$H:$H,"Easy") -> 3 | K35: =COUNTIFS('Problem Tracker'!$C:$C,"String",'Problem Tracker'!$D:$D,"Parsing & Simulation",'Problem Tracker'!$E:$E,"String Parsing / Conversion",'Problem Tracker'!$H:$H,"Medium") -> 4 | L35: =COUNTIFS('Problem Tracker'!$C:$C,"String",'Problem Tracker'!$D:$D,"Parsing & Simulation",'Problem Tracker'!$E:$E,"String Parsing / Conversion",'Problem Tracker'!$H:$H,"Hard") -> 0 | M35: =COUNTIFS('Problem Tracker'!$C:$C,"String",'Problem Tracker'!$D:$D,"Parsing & Simulation",'Problem Tracker'!$E:$E,"String Parsing / Conversion",'Problem Tracker'!$M:$M,"Solved")+COUNTIFS('Problem Tracker'!$C:$C,"String",'Problem Tracker'!$D:$D,"Parsing & Simulation",'Problem Tracker'!$E:$E,"String Parsing / Conversion",'Problem Tracker'!$M:$M,"Mastered") -> 0 | N35: =IF(I35=0,0,M35/I35) -> 0
A36: String | B36: Parsing & Simulation | C36: String Building / Encoding | D36: High | E36: Compress, encode/decode, big-number arithmetic | F36: StringBuilder; length-prefix encoding; digit-by-digit math | G36: O(n·m) | H36: W03 | I36: =COUNTIFS('Problem Tracker'!$C:$C,"String",'Problem Tracker'!$D:$D,"Parsing & Simulation",'Problem Tracker'!$E:$E,"String Building / Encoding") -> 4 | J36: =COUNTIFS('Problem Tracker'!$C:$C,"String",'Problem Tracker'!$D:$D,"Parsing & Simulation",'Problem Tracker'!$E:$E,"String Building / Encoding",'Problem Tracker'!$H:$H,"Easy") -> 0 | K36: =COUNTIFS('Problem Tracker'!$C:$C,"String",'Problem Tracker'!$D:$D,"Parsing & Simulation",'Problem Tracker'!$E:$E,"String Building / Encoding",'Problem Tracker'!$H:$H,"Medium") -> 3 | L36: =COUNTIFS('Problem Tracker'!$C:$C,"String",'Problem Tracker'!$D:$D,"Parsing & Simulation",'Problem Tracker'!$E:$E,"String Building / Encoding",'Problem Tracker'!$H:$H,"Hard") -> 1 | M36: =COUNTIFS('Problem Tracker'!$C:$C,"String",'Problem Tracker'!$D:$D,"Parsing & Simulation",'Problem Tracker'!$E:$E,"String Building / Encoding",'Problem Tracker'!$M:$M,"Solved")+COUNTIFS('Problem Tracker'!$C:$C,"String",'Problem Tracker'!$D:$D,"Parsing & Simulation",'Problem Tracker'!$E:$E,"String Building / Encoding",'Problem Tracker'!$M:$M,"Mastered") -> 0 | N36: =IF(I36=0,0,M36/I36) -> 0
A37: ▌ MATRIX (2D ARRAY) | I37: =COUNTIF('Problem Tracker'!$C:$C,"Matrix (2D Array)") -> 8 | M37: =COUNTIFS('Problem Tracker'!$C:$C,"Matrix (2D Array)",'Problem Tracker'!$M:$M,"Solved")+COUNTIFS('Problem Tracker'!$C:$C,"Matrix (2D Array)",'Problem Tracker'!$M:$M,"Mastered") -> 0 | N37: =IF(I37=0,0,M37/I37) -> 0
A38: Matrix (2D Array) | B38: Matrix Manipulation | C38: Traversal Order (Spiral / Diagonal) | D38: 🔥 Very High | E38: Visit cells in a specific order | F38: Maintain top/bottom/left/right boundaries | G38: O(mn) | H38: W03 | I38: =COUNTIFS('Problem Tracker'!$C:$C,"Matrix (2D Array)",'Problem Tracker'!$D:$D,"Matrix Manipulation",'Problem Tracker'!$E:$E,"Traversal Order (Spiral / Diagonal)") -> 3 | J38: =COUNTIFS('Problem Tracker'!$C:$C,"Matrix (2D Array)",'Problem Tracker'!$D:$D,"Matrix Manipulation",'Problem Tracker'!$E:$E,"Traversal Order (Spiral / Diagonal)",'Problem Tracker'!$H:$H,"Easy") -> 0 | K38: =COUNTIFS('Problem Tracker'!$C:$C,"Matrix (2D Array)",'Problem Tracker'!$D:$D,"Matrix Manipulation",'Problem Tracker'!$E:$E,"Traversal Order (Spiral / Diagonal)",'Problem Tracker'!$H:$H,"Medium") -> 3 | L38: =COUNTIFS('Problem Tracker'!$C:$C,"Matrix (2D Array)",'Problem Tracker'!$D:$D,"Matrix Manipulation",'Problem Tracker'!$E:$E,"Traversal Order (Spiral / Diagonal)",'Problem Tracker'!$H:$H,"Hard") -> 0 | M38: =COUNTIFS('Problem Tracker'!$C:$C,"Matrix (2D Array)",'Problem Tracker'!$D:$D,"Matrix Manipulation",'Problem Tracker'!$E:$E,"Traversal Order (Spiral / Diagonal)",'Problem Tracker'!$M:$M,"Solved")+COUNTIFS('Problem Tracker'!$C:$C,"Matrix (2D Array)",'Problem Tracker'!$D:$D,"Matrix Manipulation",'Problem Tracker'!$E:$E,"Traversal Order (Spiral / Diagonal)",'Problem Tracker'!$M:$M,"Mastered") -> 0 | N38: =IF(I38=0,0,M38/I38) -> 0
A39: Matrix (2D Array) | B39: Matrix Manipulation | C39: In-place Transformation | D39: 🔥 Very High | E39: Rotate / zero-out / next state without extra matrix | F39: Transpose + reverse; use first row/col or bit states as markers | G39: O(mn), O(1) | H39: W03 | I39: =COUNTIFS('Problem Tracker'!$C:$C,"Matrix (2D Array)",'Problem Tracker'!$D:$D,"Matrix Manipulation",'Problem Tracker'!$E:$E,"In-place Transformation") -> 5 | J39: =COUNTIFS('Problem Tracker'!$C:$C,"Matrix (2D Array)",'Problem Tracker'!$D:$D,"Matrix Manipulation",'Problem Tracker'!$E:$E,"In-place Transformation",'Problem Tracker'!$H:$H,"Easy") -> 2 | K39: =COUNTIFS('Problem Tracker'!$C:$C,"Matrix (2D Array)",'Problem Tracker'!$D:$D,"Matrix Manipulation",'Problem Tracker'!$E:$E,"In-place Transformation",'Problem Tracker'!$H:$H,"Medium") -> 3 | L39: =COUNTIFS('Problem Tracker'!$C:$C,"Matrix (2D Array)",'Problem Tracker'!$D:$D,"Matrix Manipulation",'Problem Tracker'!$E:$E,"In-place Transformation",'Problem Tracker'!$H:$H,"Hard") -> 0 | M39: =COUNTIFS('Problem Tracker'!$C:$C,"Matrix (2D Array)",'Problem Tracker'!$D:$D,"Matrix Manipulation",'Problem Tracker'!$E:$E,"In-place Transformation",'Problem Tracker'!$M:$M,"Solved")+COUNTIFS('Problem Tracker'!$C:$C,"Matrix (2D Array)",'Problem Tracker'!$D:$D,"Matrix Manipulation",'Problem Tracker'!$E:$E,"In-place Transformation",'Problem Tracker'!$M:$M,"Mastered") -> 0 | N39: =IF(I39=0,0,M39/I39) -> 0
A40: ▌ STACK | I40: =COUNTIF('Problem Tracker'!$C:$C,"Stack") -> 29 | M40: =COUNTIFS('Problem Tracker'!$C:$C,"Stack",'Problem Tracker'!$M:$M,"Solved")+COUNTIFS('Problem Tracker'!$C:$C,"Stack",'Problem Tracker'!$M:$M,"Mastered") -> 0 | N40: =IF(I40=0,0,M40/I40) -> 0
A41: Stack | B41: Classic Stack | C41: Matching / Balanced Brackets | D41: 🔥 Very High | E41: Brackets, adjacent duplicates, 'remove to make valid' | F41: Push opens; pop on match; track indices if needed | G41: O(n) | H41: W04 | I41: =COUNTIFS('Problem Tracker'!$C:$C,"Stack",'Problem Tracker'!$D:$D,"Classic Stack",'Problem Tracker'!$E:$E,"Matching / Balanced Brackets") -> 6 | J41: =COUNTIFS('Problem Tracker'!$C:$C,"Stack",'Problem Tracker'!$D:$D,"Classic Stack",'Problem Tracker'!$E:$E,"Matching / Balanced Brackets",'Problem Tracker'!$H:$H,"Easy") -> 2 | K41: =COUNTIFS('Problem Tracker'!$C:$C,"Stack",'Problem Tracker'!$D:$D,"Classic Stack",'Problem Tracker'!$E:$E,"Matching / Balanced Brackets",'Problem Tracker'!$H:$H,"Medium") -> 3 | L41: =COUNTIFS('Problem Tracker'!$C:$C,"Stack",'Problem Tracker'!$D:$D,"Classic Stack",'Problem Tracker'!$E:$E,"Matching / Balanced Brackets",'Problem Tracker'!$H:$H,"Hard") -> 1 | M41: =COUNTIFS('Problem Tracker'!$C:$C,"Stack",'Problem Tracker'!$D:$D,"Classic Stack",'Problem Tracker'!$E:$E,"Matching / Balanced Brackets",'Problem Tracker'!$M:$M,"Solved")+COUNTIFS('Problem Tracker'!$C:$C,"Stack",'Problem Tracker'!$D:$D,"Classic Stack",'Problem Tracker'!$E:$E,"Matching / Balanced Brackets",'Problem Tracker'!$M:$M,"Mastered") -> 0 | N41: =IF(I41=0,0,M41/I41) -> 0
A42: Stack | B42: Classic Stack | C42: Stack Simulation | D42: High | E42: Collisions, process-until-stable, push/pop sequence validation | F42: Simulate with stack; resolve while top conflicts | G42: O(n) | H42: W04 | I42: =COUNTIFS('Problem Tracker'!$C:$C,"Stack",'Problem Tracker'!$D:$D,"Classic Stack",'Problem Tracker'!$E:$E,"Stack Simulation") -> 3 | J42: =COUNTIFS('Problem Tracker'!$C:$C,"Stack",'Problem Tracker'!$D:$D,"Classic Stack",'Problem Tracker'!$E:$E,"Stack Simulation",'Problem Tracker'!$H:$H,"Easy") -> 0 | K42: =COUNTIFS('Problem Tracker'!$C:$C,"Stack",'Problem Tracker'!$D:$D,"Classic Stack",'Problem Tracker'!$E:$E,"Stack Simulation",'Problem Tracker'!$H:$H,"Medium") -> 3 | L42: =COUNTIFS('Problem Tracker'!$C:$C,"Stack",'Problem Tracker'!$D:$D,"Classic Stack",'Problem Tracker'!$E:$E,"Stack Simulation",'Problem Tracker'!$H:$H,"Hard") -> 0 | M42: =COUNTIFS('Problem Tracker'!$C:$C,"Stack",'Problem Tracker'!$D:$D,"Classic Stack",'Problem Tracker'!$E:$E,"Stack Simulation",'Problem Tracker'!$M:$M,"Solved")+COUNTIFS('Problem Tracker'!$C:$C,"Stack",'Problem Tracker'!$D:$D,"Classic Stack",'Problem Tracker'!$E:$E,"Stack Simulation",'Problem Tracker'!$M:$M,"Mastered") -> 0 | N42: =IF(I42=0,0,M42/I42) -> 0
A43: Stack | B43: Classic Stack | C43: Expression Evaluation / Nested Decoding | D43: 🔥 Very High | E43: Calculator, RPN, nested k[str], paths with '..' | F43: Operand + operator stacks or recursion on '(' | G43: O(n) | H43: W04 | I43: =COUNTIFS('Problem Tracker'!$C:$C,"Stack",'Problem Tracker'!$D:$D,"Classic Stack",'Problem Tracker'!$E:$E,"Expression Evaluation / Nested Decoding") -> 5 | J43: =COUNTIFS('Problem Tracker'!$C:$C,"Stack",'Problem Tracker'!$D:$D,"Classic Stack",'Problem Tracker'!$E:$E,"Expression Evaluation / Nested Decoding",'Problem Tracker'!$H:$H,"Easy") -> 0 | K43: =COUNTIFS('Problem Tracker'!$C:$C,"Stack",'Problem Tracker'!$D:$D,"Classic Stack",'Problem Tracker'!$E:$E,"Expression Evaluation / Nested Decoding",'Problem Tracker'!$H:$H,"Medium") -> 4 | L43: =COUNTIFS('Problem Tracker'!$C:$C,"Stack",'Problem Tracker'!$D:$D,"Classic Stack",'Problem Tracker'!$E:$E,"Expression Evaluation / Nested Decoding",'Problem Tracker'!$H:$H,"Hard") -> 1 | M43: =COUNTIFS('Problem Tracker'!$C:$C,"Stack",'Problem Tracker'!$D:$D,"Classic Stack",'Problem Tracker'!$E:$E,"Expression Evaluation / Nested Decoding",'Problem Tracker'!$M:$M,"Solved")+COUNTIFS('Problem Tracker'!$C:$C,"Stack",'Problem Tracker'!$D:$D,"Classic Stack",'Problem Tracker'!$E:$E,"Expression Evaluation / Nested Decoding",'Problem Tracker'!$M:$M,"Mastered") -> 0 | N43: =IF(I43=0,0,M43/I43) -> 0
A44: Stack | B44: Monotonic Stack | C44: Next Greater / Smaller Element | D44: 🔥 Very High | E44: 'Next warmer day', 'next greater', span, fleets | F44: Keep stack monotone; when popped, answer for that index is found | G44: O(n) | H44: W04 | I44: =COUNTIFS('Problem Tracker'!$C:$C,"Stack",'Problem Tracker'!$D:$D,"Monotonic Stack",'Problem Tracker'!$E:$E,"Next Greater / Smaller Element") -> 5 | J44: =COUNTIFS('Problem Tracker'!$C:$C,"Stack",'Problem Tracker'!$D:$D,"Monotonic Stack",'Problem Tracker'!$E:$E,"Next Greater / Smaller Element",'Problem Tracker'!$H:$H,"Easy") -> 1 | K44: =COUNTIFS('Problem Tracker'!$C:$C,"Stack",'Problem Tracker'!$D:$D,"Monotonic Stack",'Problem Tracker'!$E:$E,"Next Greater / Smaller Element",'Problem Tracker'!$H:$H,"Medium") -> 4 | L44: =COUNTIFS('Problem Tracker'!$C:$C,"Stack",'Problem Tracker'!$D:$D,"Monotonic Stack",'Problem Tracker'!$E:$E,"Next Greater / Smaller Element",'Problem Tracker'!$H:$H,"Hard") -> 0 | M44: =COUNTIFS('Problem Tracker'!$C:$C,"Stack",'Problem Tracker'!$D:$D,"Monotonic Stack",'Problem Tracker'!$E:$E,"Next Greater / Smaller Element",'Problem Tracker'!$M:$M,"Solved")+COUNTIFS('Problem Tracker'!$C:$C,"Stack",'Problem Tracker'!$D:$D,"Monotonic Stack",'Problem Tracker'!$E:$E,"Next Greater / Smaller Element",'Problem Tracker'!$M:$M,"Mastered") -> 0 | N44: =IF(I44=0,0,M44/I44) -> 0
A45: Stack | B45: Monotonic Stack | C45: Histogram / Max Rectangle | D45: 🔥 Very High | E45: Largest rectangle bounded by heights | F45: Previous & next smaller via stack; area = h × width | G45: O(n) | H45: W04 | I45: =COUNTIFS('Problem Tracker'!$C:$C,"Stack",'Problem Tracker'!$D:$D,"Monotonic Stack",'Problem Tracker'!$E:$E,"Histogram / Max Rectangle") -> 2 | J45: =COUNTIFS('Problem Tracker'!$C:$C,"Stack",'Problem Tracker'!$D:$D,"Monotonic Stack",'Problem Tracker'!$E:$E,"Histogram / Max Rectangle",'Problem Tracker'!$H:$H,"Easy") -> 0 | K45: =COUNTIFS('Problem Tracker'!$C:$C,"Stack",'Problem Tracker'!$D:$D,"Monotonic Stack",'Problem Tracker'!$E:$E,"Histogram / Max Rectangle",'Problem Tracker'!$H:$H,"Medium") -> 0 | L45: =COUNTIFS('Problem Tracker'!$C:$C,"Stack",'Problem Tracker'!$D:$D,"Monotonic Stack",'Problem Tracker'!$E:$E,"Histogram / Max Rectangle",'Problem Tracker'!$H:$H,"Hard") -> 2 | M45: =COUNTIFS('Problem Tracker'!$C:$C,"Stack",'Problem Tracker'!$D:$D,"Monotonic Stack",'Problem Tracker'!$E:$E,"Histogram / Max Rectangle",'Problem Tracker'!$M:$M,"Solved")+COUNTIFS('Problem Tracker'!$C:$C,"Stack",'Problem Tracker'!$D:$D,"Monotonic Stack",'Problem Tracker'!$E:$E,"Histogram / Max Rectangle",'Problem Tracker'!$M:$M,"Mastered") -> 0 | N45: =IF(I45=0,0,M45/I45) -> 0
A46: Stack | B46: Monotonic Stack | C46: Contribution Technique | D46: Medium | E46: Sum of min/max over all subarrays | F46: Each element contributes × (left span) × (right span) | G46: O(n) | H46: W04 | I46: =COUNTIFS('Problem Tracker'!$C:$C,"Stack",'Problem Tracker'!$D:$D,"Monotonic Stack",'Problem Tracker'!$E:$E,"Contribution Technique") -> 2 | J46: =COUNTIFS('Problem Tracker'!$C:$C,"Stack",'Problem Tracker'!$D:$D,"Monotonic Stack",'Problem Tracker'!$E:$E,"Contribution Technique",'Problem Tracker'!$H:$H,"Easy") -> 0 | K46: =COUNTIFS('Problem Tracker'!$C:$C,"Stack",'Problem Tracker'!$D:$D,"Monotonic Stack",'Problem Tracker'!$E:$E,"Contribution Technique",'Problem Tracker'!$H:$H,"Medium") -> 2 | L46: =COUNTIFS('Problem Tracker'!$C:$C,"Stack",'Problem Tracker'!$D:$D,"Monotonic Stack",'Problem Tracker'!$E:$E,"Contribution Technique",'Problem Tracker'!$H:$H,"Hard") -> 0 | M46: =COUNTIFS('Problem Tracker'!$C:$C,"Stack",'Problem Tracker'!$D:$D,"Monotonic Stack",'Problem Tracker'!$E:$E,"Contribution Technique",'Problem Tracker'!$M:$M,"Solved")+COUNTIFS('Problem Tracker'!$C:$C,"Stack",'Problem Tracker'!$D:$D,"Monotonic Stack",'Problem Tracker'!$E:$E,"Contribution Technique",'Problem Tracker'!$M:$M,"Mastered") -> 0 | N46: =IF(I46=0,0,M46/I46) -> 0
A47: Stack | B47: Monotonic Stack | C47: Greedy Removal (Lexicographic) | D47: High | E47: Smallest number/string after removing digits/duplicates | F47: Pop larger previous chars while removals remain | G47: O(n) | H47: W04 | I47: =COUNTIFS('Problem Tracker'!$C:$C,"Stack",'Problem Tracker'!$D:$D,"Monotonic Stack",'Problem Tracker'!$E:$E,"Greedy Removal (Lexicographic)") -> 2 | J47: =COUNTIFS('Problem Tracker'!$C:$C,"Stack",'Problem Tracker'!$D:$D,"Monotonic Stack",'Problem Tracker'!$E:$E,"Greedy Removal (Lexicographic)",'Problem Tracker'!$H:$H,"Easy") -> 0 | K47: =COUNTIFS('Problem Tracker'!$C:$C,"Stack",'Problem Tracker'!$D:$D,"Monotonic Stack",'Problem Tracker'!$E:$E,"Greedy Removal (Lexicographic)",'Problem Tracker'!$H:$H,"Medium") -> 2 | L47: =COUNTIFS('Problem Tracker'!$C:$C,"Stack",'Problem Tracker'!$D:$D,"Monotonic Stack",'Problem Tracker'!$E:$E,"Greedy Removal (Lexicographic)",'Problem Tracker'!$H:$H,"Hard") -> 0 | M47: =COUNTIFS('Problem Tracker'!$C:$C,"Stack",'Problem Tracker'!$D:$D,"Monotonic Stack",'Problem Tracker'!$E:$E,"Greedy Removal (Lexicographic)",'Problem Tracker'!$M:$M,"Solved")+COUNTIFS('Problem Tracker'!$C:$C,"Stack",'Problem Tracker'!$D:$D,"Monotonic Stack",'Problem Tracker'!$E:$E,"Greedy Removal (Lexicographic)",'Problem Tracker'!$M:$M,"Mastered") -> 0 | N47: =IF(I47=0,0,M47/I47) -> 0
A48: Stack | B48: Stack Design | C48: Augmented Stacks | D48: 🔥 Very High | E48: Stack with O(1) min / frequency / built from queues | F48: Store (value, extra-info) pairs or two containers | G48: O(1) per op | H48: W04 | I48: =COUNTIFS('Problem Tracker'!$C:$C,"Stack",'Problem Tracker'!$D:$D,"Stack Design",'Problem Tracker'!$E:$E,"Augmented Stacks") -> 4 | J48: =COUNTIFS('Problem Tracker'!$C:$C,"Stack",'Problem Tracker'!$D:$D,"Stack Design",'Problem Tracker'!$E:$E,"Augmented Stacks",'Problem Tracker'!$H:$H,"Easy") -> 2 | K48: =COUNTIFS('Problem Tracker'!$C:$C,"Stack",'Problem Tracker'!$D:$D,"Stack Design",'Problem Tracker'!$E:$E,"Augmented Stacks",'Problem Tracker'!$H:$H,"Medium") -> 1 | L48: =COUNTIFS('Problem Tracker'!$C:$C,"Stack",'Problem Tracker'!$D:$D,"Stack Design",'Problem Tracker'!$E:$E,"Augmented Stacks",'Problem Tracker'!$H:$H,"Hard") -> 1 | M48: =COUNTIFS('Problem Tracker'!$C:$C,"Stack",'Problem Tracker'!$D:$D,"Stack Design",'Problem Tracker'!$E:$E,"Augmented Stacks",'Problem Tracker'!$M:$M,"Solved")+COUNTIFS('Problem Tracker'!$C:$C,"Stack",'Problem Tracker'!$D:$D,"Stack Design",'Problem Tracker'!$E:$E,"Augmented Stacks",'Problem Tracker'!$M:$M,"Mastered") -> 0 | N48: =IF(I48=0,0,M48/I48) -> 0
A49: ▌ QUEUE / DEQUE | I49: =COUNTIF('Problem Tracker'!$C:$C,"Queue / Deque") -> 5 | M49: =COUNTIFS('Problem Tracker'!$C:$C,"Queue / Deque",'Problem Tracker'!$M:$M,"Solved")+COUNTIFS('Problem Tracker'!$C:$C,"Queue / Deque",'Problem Tracker'!$M:$M,"Mastered") -> 0 | N49: =IF(I49=0,0,M49/I49) -> 0
A50: Queue / Deque | B50: Queue Patterns | C50: Queue Simulation | D50: Medium | E50: Rounds, turns, recent-window counting, card reveal order | F50: FIFO queue; re-enqueue survivors | G50: O(n) | H50: W04 | I50: =COUNTIFS('Problem Tracker'!$C:$C,"Queue / Deque",'Problem Tracker'!$D:$D,"Queue Patterns",'Problem Tracker'!$E:$E,"Queue Simulation") -> 3 | J50: =COUNTIFS('Problem Tracker'!$C:$C,"Queue / Deque",'Problem Tracker'!$D:$D,"Queue Patterns",'Problem Tracker'!$E:$E,"Queue Simulation",'Problem Tracker'!$H:$H,"Easy") -> 1 | K50: =COUNTIFS('Problem Tracker'!$C:$C,"Queue / Deque",'Problem Tracker'!$D:$D,"Queue Patterns",'Problem Tracker'!$E:$E,"Queue Simulation",'Problem Tracker'!$H:$H,"Medium") -> 2 | L50: =COUNTIFS('Problem Tracker'!$C:$C,"Queue / Deque",'Problem Tracker'!$D:$D,"Queue Patterns",'Problem Tracker'!$E:$E,"Queue Simulation",'Problem Tracker'!$H:$H,"Hard") -> 0 | M50: =COUNTIFS('Problem Tracker'!$C:$C,"Queue / Deque",'Problem Tracker'!$D:$D,"Queue Patterns",'Problem Tracker'!$E:$E,"Queue Simulation",'Problem Tracker'!$M:$M,"Solved")+COUNTIFS('Problem Tracker'!$C:$C,"Queue / Deque",'Problem Tracker'!$D:$D,"Queue Patterns",'Problem Tracker'!$E:$E,"Queue Simulation",'Problem Tracker'!$M:$M,"Mastered") -> 0 | N50: =IF(I50=0,0,M50/I50) -> 0
A51: Queue / Deque | B51: Queue Patterns | C51: Circular Queue / Deque Design | D51: High | E51: Fixed-capacity ring buffer | F51: Array + head index + size, modulo arithmetic | G51: O(1) per op | H51: W04 | I51: =COUNTIFS('Problem Tracker'!$C:$C,"Queue / Deque",'Problem Tracker'!$D:$D,"Queue Patterns",'Problem Tracker'!$E:$E,"Circular Queue / Deque Design") -> 2 | J51: =COUNTIFS('Problem Tracker'!$C:$C,"Queue / Deque",'Problem Tracker'!$D:$D,"Queue Patterns",'Problem Tracker'!$E:$E,"Circular Queue / Deque Design",'Problem Tracker'!$H:$H,"Easy") -> 0 | K51: =COUNTIFS('Problem Tracker'!$C:$C,"Queue / Deque",'Problem Tracker'!$D:$D,"Queue Patterns",'Problem Tracker'!$E:$E,"Circular Queue / Deque Design",'Problem Tracker'!$H:$H,"Medium") -> 2 | L51: =COUNTIFS('Problem Tracker'!$C:$C,"Queue / Deque",'Problem Tracker'!$D:$D,"Queue Patterns",'Problem Tracker'!$E:$E,"Circular Queue / Deque Design",'Problem Tracker'!$H:$H,"Hard") -> 0 | M51: =COUNTIFS('Problem Tracker'!$C:$C,"Queue / Deque",'Problem Tracker'!$D:$D,"Queue Patterns",'Problem Tracker'!$E:$E,"Circular Queue / Deque Design",'Problem Tracker'!$M:$M,"Solved")+COUNTIFS('Problem Tracker'!$C:$C,"Queue / Deque",'Problem Tracker'!$D:$D,"Queue Patterns",'Problem Tracker'!$E:$E,"Circular Queue / Deque Design",'Problem Tracker'!$M:$M,"Mastered") -> 0 | N51: =IF(I51=0,0,M51/I51) -> 0
A52: ▌ BINARY SEARCH | I52: =COUNTIF('Problem Tracker'!$C:$C,"Binary Search") -> 28 | M52: =COUNTIFS('Problem Tracker'!$C:$C,"Binary Search",'Problem Tracker'!$M:$M,"Solved")+COUNTIFS('Problem Tracker'!$C:$C,"Binary Search",'Problem Tracker'!$M:$M,"Mastered") -> 0 | N52: =IF(I52=0,0,M52/I52) -> 0
A53: Binary Search | B53: Binary Search on Index | C53: Classic / Lower–Upper Bound | D53: 🔥 Very High | E53: Sorted input; find target, first/last position, insert point | F53: lo ≤ hi or lo < hi with consistent mid update; boundary search | G53: O(log n) | H53: W05 | I53: =COUNTIFS('Problem Tracker'!$C:$C,"Binary Search",'Problem Tracker'!$D:$D,"Binary Search on Index",'Problem Tracker'!$E:$E,"Classic / Lower–Upper Bound") -> 7 | J53: =COUNTIFS('Problem Tracker'!$C:$C,"Binary Search",'Problem Tracker'!$D:$D,"Binary Search on Index",'Problem Tracker'!$E:$E,"Classic / Lower–Upper Bound",'Problem Tracker'!$H:$H,"Easy") -> 5 | K53: =COUNTIFS('Problem Tracker'!$C:$C,"Binary Search",'Problem Tracker'!$D:$D,"Binary Search on Index",'Problem Tracker'!$E:$E,"Classic / Lower–Upper Bound",'Problem Tracker'!$H:$H,"Medium") -> 2 | L53: =COUNTIFS('Problem Tracker'!$C:$C,"Binary Search",'Problem Tracker'!$D:$D,"Binary Search on Index",'Problem Tracker'!$E:$E,"Classic / Lower–Upper Bound",'Problem Tracker'!$H:$H,"Hard") -> 0 | M53: =COUNTIFS('Problem Tracker'!$C:$C,"Binary Search",'Problem Tracker'!$D:$D,"Binary Search on Index",'Problem Tracker'!$E:$E,"Classic / Lower–Upper Bound",'Problem Tracker'!$M:$M,"Solved")+COUNTIFS('Problem Tracker'!$C:$C,"Binary Search",'Problem Tracker'!$D:$D,"Binary Search on Index",'Problem Tracker'!$E:$E,"Classic / Lower–Upper Bound",'Problem Tracker'!$M:$M,"Mastered") -> 0 | N53: =IF(I53=0,0,M53/I53) -> 0
A54: Binary Search | B54: Binary Search on Index | C54: Rotated Sorted Array | D54: 🔥 Very High | E54: Sorted array rotated at unknown pivot | F54: Decide which half is sorted, then whether target lies in it | G54: O(log n) | H54: W05 | I54: =COUNTIFS('Problem Tracker'!$C:$C,"Binary Search",'Problem Tracker'!$D:$D,"Binary Search on Index",'Problem Tracker'!$E:$E,"Rotated Sorted Array") -> 4 | J54: =COUNTIFS('Problem Tracker'!$C:$C,"Binary Search",'Problem Tracker'!$D:$D,"Binary Search on Index",'Problem Tracker'!$E:$E,"Rotated Sorted Array",'Problem Tracker'!$H:$H,"Easy") -> 0 | K54: =COUNTIFS('Problem Tracker'!$C:$C,"Binary Search",'Problem Tracker'!$D:$D,"Binary Search on Index",'Problem Tracker'!$E:$E,"Rotated Sorted Array",'Problem Tracker'!$H:$H,"Medium") -> 3 | L54: =COUNTIFS('Problem Tracker'!$C:$C,"Binary Search",'Problem Tracker'!$D:$D,"Binary Search on Index",'Problem Tracker'!$E:$E,"Rotated Sorted Array",'Problem Tracker'!$H:$H,"Hard") -> 1 | M54: =COUNTIFS('Problem Tracker'!$C:$C,"Binary Search",'Problem Tracker'!$D:$D,"Binary Search on Index",'Problem Tracker'!$E:$E,"Rotated Sorted Array",'Problem Tracker'!$M:$M,"Solved")+COUNTIFS('Problem Tracker'!$C:$C,"Binary Search",'Problem Tracker'!$D:$D,"Binary Search on Index",'Problem Tracker'!$E:$E,"Rotated Sorted Array",'Problem Tracker'!$M:$M,"Mastered") -> 0 | N54: =IF(I54=0,0,M54/I54) -> 0
A55: Binary Search | B55: Binary Search on Index | C55: Peak / Bitonic | D55: High | E55: Mountain array, local peak, unsorted but has slope | F55: Compare mid with mid+1; move towards the higher side | G55: O(log n) | H55: W05 | I55: =COUNTIFS('Problem Tracker'!$C:$C,"Binary Search",'Problem Tracker'!$D:$D,"Binary Search on Index",'Problem Tracker'!$E:$E,"Peak / Bitonic") -> 4 | J55: =COUNTIFS('Problem Tracker'!$C:$C,"Binary Search",'Problem Tracker'!$D:$D,"Binary Search on Index",'Problem Tracker'!$E:$E,"Peak / Bitonic",'Problem Tracker'!$H:$H,"Easy") -> 0 | K55: =COUNTIFS('Problem Tracker'!$C:$C,"Binary Search",'Problem Tracker'!$D:$D,"Binary Search on Index",'Problem Tracker'!$E:$E,"Peak / Bitonic",'Problem Tracker'!$H:$H,"Medium") -> 3 | L55: =COUNTIFS('Problem Tracker'!$C:$C,"Binary Search",'Problem Tracker'!$D:$D,"Binary Search on Index",'Problem Tracker'!$E:$E,"Peak / Bitonic",'Problem Tracker'!$H:$H,"Hard") -> 1 | M55: =COUNTIFS('Problem Tracker'!$C:$C,"Binary Search",'Problem Tracker'!$D:$D,"Binary Search on Index",'Problem Tracker'!$E:$E,"Peak / Bitonic",'Problem Tracker'!$M:$M,"Solved")+COUNTIFS('Problem Tracker'!$C:$C,"Binary Search",'Problem Tracker'!$D:$D,"Binary Search on Index",'Problem Tracker'!$E:$E,"Peak / Bitonic",'Problem Tracker'!$M:$M,"Mastered") -> 0 | N55: =IF(I55=0,0,M55/I55) -> 0
A56: Binary Search | B56: Binary Search on Index | C56: 2D Matrix Search | D56: High | E56: Row/column sorted matrix | F56: Treat as 1D array, or staircase from top-right | G56: O(log mn) / O(m+n) | H56: W05 | I56: =COUNTIFS('Problem Tracker'!$C:$C,"Binary Search",'Problem Tracker'!$D:$D,"Binary Search on Index",'Problem Tracker'!$E:$E,"2D Matrix Search") -> 3 | J56: =COUNTIFS('Problem Tracker'!$C:$C,"Binary Search",'Problem Tracker'!$D:$D,"Binary Search on Index",'Problem Tracker'!$E:$E,"2D Matrix Search",'Problem Tracker'!$H:$H,"Easy") -> 0 | K56: =COUNTIFS('Problem Tracker'!$C:$C,"Binary Search",'Problem Tracker'!$D:$D,"Binary Search on Index",'Problem Tracker'!$E:$E,"2D Matrix Search",'Problem Tracker'!$H:$H,"Medium") -> 3 | L56: =COUNTIFS('Problem Tracker'!$C:$C,"Binary Search",'Problem Tracker'!$D:$D,"Binary Search on Index",'Problem Tracker'!$E:$E,"2D Matrix Search",'Problem Tracker'!$H:$H,"Hard") -> 0 | M56: =COUNTIFS('Problem Tracker'!$C:$C,"Binary Search",'Problem Tracker'!$D:$D,"Binary Search on Index",'Problem Tracker'!$E:$E,"2D Matrix Search",'Problem Tracker'!$M:$M,"Solved")+COUNTIFS('Problem Tracker'!$C:$C,"Binary Search",'Problem Tracker'!$D:$D,"Binary Search on Index",'Problem Tracker'!$E:$E,"2D Matrix Search",'Problem Tracker'!$M:$M,"Mastered") -> 0 | N56: =IF(I56=0,0,M56/I56) -> 0
A57: Binary Search | B57: Binary Search on Index | C57: Binary Search with Data Structures | D57: High | E57: Timestamp lookups, partition of two sorted arrays | F57: Search on stored sorted lists / on partition index | G57: O(log n) | H57: W05 | I57: =COUNTIFS('Problem Tracker'!$C:$C,"Binary Search",'Problem Tracker'!$D:$D,"Binary Search on Index",'Problem Tracker'!$E:$E,"Binary Search with Data Structures") -> 2 | J57: =COUNTIFS('Problem Tracker'!$C:$C,"Binary Search",'Problem Tracker'!$D:$D,"Binary Search on Index",'Problem Tracker'!$E:$E,"Binary Search with Data Structures",'Problem Tracker'!$H:$H,"Easy") -> 0 | K57: =COUNTIFS('Problem Tracker'!$C:$C,"Binary Search",'Problem Tracker'!$D:$D,"Binary Search on Index",'Problem Tracker'!$E:$E,"Binary Search with Data Structures",'Problem Tracker'!$H:$H,"Medium") -> 1 | L57: =COUNTIFS('Problem Tracker'!$C:$C,"Binary Search",'Problem Tracker'!$D:$D,"Binary Search on Index",'Problem Tracker'!$E:$E,"Binary Search with Data Structures",'Problem Tracker'!$H:$H,"Hard") -> 1 | M57: =COUNTIFS('Problem Tracker'!$C:$C,"Binary Search",'Problem Tracker'!$D:$D,"Binary Search on Index",'Problem Tracker'!$E:$E,"Binary Search with Data Structures",'Problem Tracker'!$M:$M,"Solved")+COUNTIFS('Problem Tracker'!$C:$C,"Binary Search",'Problem Tracker'!$D:$D,"Binary Search on Index",'Problem Tracker'!$E:$E,"Binary Search with Data Structures",'Problem Tracker'!$M:$M,"Mastered") -> 0 | N57: =IF(I57=0,0,M57/I57) -> 0
A58: Binary Search | B58: Binary Search on Answer | C58: Minimize the Maximum / Maximize the Minimum | D58: 🔥 Very High | E58: 'Minimum capacity/speed/days such that…' — answer space is monotone | F58: lo..hi over answers; feasible(mid) greedy check | G58: O(n log range) | H58: W05 | I58: =COUNTIFS('Problem Tracker'!$C:$C,"Binary Search",'Problem Tracker'!$D:$D,"Binary Search on Answer",'Problem Tracker'!$E:$E,"Minimize the Maximum / Maximize the Minimum") -> 8 | J58: =COUNTIFS('Problem Tracker'!$C:$C,"Binary Search",'Problem Tracker'!$D:$D,"Binary Search on Answer",'Problem Tracker'!$E:$E,"Minimize the Maximum / Maximize the Minimum",'Problem Tracker'!$H:$H,"Easy") -> 0 | K58: =COUNTIFS('Problem Tracker'!$C:$C,"Binary Search",'Problem Tracker'!$D:$D,"Binary Search on Answer",'Problem Tracker'!$E:$E,"Minimize the Maximum / Maximize the Minimum",'Problem Tracker'!$H:$H,"Medium") -> 6 | L58: =COUNTIFS('Problem Tracker'!$C:$C,"Binary Search",'Problem Tracker'!$D:$D,"Binary Search on Answer",'Problem Tracker'!$E:$E,"Minimize the Maximum / Maximize the Minimum",'Problem Tracker'!$H:$H,"Hard") -> 2 | M58: =COUNTIFS('Problem Tracker'!$C:$C,"Binary Search",'Problem Tracker'!$D:$D,"Binary Search on Answer",'Problem Tracker'!$E:$E,"Minimize the Maximum / Maximize the Minimum",'Problem Tracker'!$M:$M,"Solved")+COUNTIFS('Problem Tracker'!$C:$C,"Binary Search",'Problem Tracker'!$D:$D,"Binary Search on Answer",'Problem Tracker'!$E:$E,"Minimize the Maximum / Maximize the Minimum",'Problem Tracker'!$M:$M,"Mastered") -> 0 | N58: =IF(I58=0,0,M58/I58) -> 0
A59: ▌ LINKED LIST | I59: =COUNTIF('Problem Tracker'!$C:$C,"Linked List") -> 25 | M59: =COUNTIFS('Problem Tracker'!$C:$C,"Linked List",'Problem Tracker'!$M:$M,"Solved")+COUNTIFS('Problem Tracker'!$C:$C,"Linked List",'Problem Tracker'!$M:$M,"Mastered") -> 0 | N59: =IF(I59=0,0,M59/I59) -> 0
A60: Linked List | B60: Fast & Slow Pointers | C60: Cycle Detection (Floyd) | D60: 🔥 Very High | E60: Does a cycle exist / where does it start | F60: slow += 1, fast += 2; reset one to head to find entry | G60: O(n), O(1) | H60: W06 | I60: =COUNTIFS('Problem Tracker'!$C:$C,"Linked List",'Problem Tracker'!$D:$D,"Fast & Slow Pointers",'Problem Tracker'!$E:$E,"Cycle Detection (Floyd)") -> 2 | J60: =COUNTIFS('Problem Tracker'!$C:$C,"Linked List",'Problem Tracker'!$D:$D,"Fast & Slow Pointers",'Problem Tracker'!$E:$E,"Cycle Detection (Floyd)",'Problem Tracker'!$H:$H,"Easy") -> 1 | K60: =COUNTIFS('Problem Tracker'!$C:$C,"Linked List",'Problem Tracker'!$D:$D,"Fast & Slow Pointers",'Problem Tracker'!$E:$E,"Cycle Detection (Floyd)",'Problem Tracker'!$H:$H,"Medium") -> 1 | L60: =COUNTIFS('Problem Tracker'!$C:$C,"Linked List",'Problem Tracker'!$D:$D,"Fast & Slow Pointers",'Problem Tracker'!$E:$E,"Cycle Detection (Floyd)",'Problem Tracker'!$H:$H,"Hard") -> 0 | M60: =COUNTIFS('Problem Tracker'!$C:$C,"Linked List",'Problem Tracker'!$D:$D,"Fast & Slow Pointers",'Problem Tracker'!$E:$E,"Cycle Detection (Floyd)",'Problem Tracker'!$M:$M,"Solved")+COUNTIFS('Problem Tracker'!$C:$C,"Linked List",'Problem Tracker'!$D:$D,"Fast & Slow Pointers",'Problem Tracker'!$E:$E,"Cycle Detection (Floyd)",'Problem Tracker'!$M:$M,"Mastered") -> 0 | N60: =IF(I60=0,0,M60/I60) -> 0
A61: Linked List | B61: Fast & Slow Pointers | C61: Middle / Split | D61: 🔥 Very High | E61: Middle node, palindrome list, delete middle | F61: When fast reaches end, slow is at middle | G61: O(n), O(1) | H61: W06 | I61: =COUNTIFS('Problem Tracker'!$C:$C,"Linked List",'Problem Tracker'!$D:$D,"Fast & Slow Pointers",'Problem Tracker'!$E:$E,"Middle / Split") -> 3 | J61: =COUNTIFS('Problem Tracker'!$C:$C,"Linked List",'Problem Tracker'!$D:$D,"Fast & Slow Pointers",'Problem Tracker'!$E:$E,"Middle / Split",'Problem Tracker'!$H:$H,"Easy") -> 2 | K61: =COUNTIFS('Problem Tracker'!$C:$C,"Linked List",'Problem Tracker'!$D:$D,"Fast & Slow Pointers",'Problem Tracker'!$E:$E,"Middle / Split",'Problem Tracker'!$H:$H,"Medium") -> 1 | L61: =COUNTIFS('Problem Tracker'!$C:$C,"Linked List",'Problem Tracker'!$D:$D,"Fast & Slow Pointers",'Problem Tracker'!$E:$E,"Middle / Split",'Problem Tracker'!$H:$H,"Hard") -> 0 | M61: =COUNTIFS('Problem Tracker'!$C:$C,"Linked List",'Problem Tracker'!$D:$D,"Fast & Slow Pointers",'Problem Tracker'!$E:$E,"Middle / Split",'Problem Tracker'!$M:$M,"Solved")+COUNTIFS('Problem Tracker'!$C:$C,"Linked List",'Problem Tracker'!$D:$D,"Fast & Slow Pointers",'Problem Tracker'!$E:$E,"Middle / Split",'Problem Tracker'!$M:$M,"Mastered") -> 0 | N61: =IF(I61=0,0,M61/I61) -> 0
A62: Linked List | B62: In-place Reversal | C62: Full / Partial / K-Group Reversal | D62: 🔥 Very High | E62: Reverse whole list, a sub-range, pairs, or every k nodes | F62: prev / curr / next pointer dance; reconnect boundaries | G62: O(n), O(1) | H62: W06 | I62: =COUNTIFS('Problem Tracker'!$C:$C,"Linked List",'Problem Tracker'!$D:$D,"In-place Reversal",'Problem Tracker'!$E:$E,"Full / Partial / K-Group Reversal") -> 5 | J62: =COUNTIFS('Problem Tracker'!$C:$C,"Linked List",'Problem Tracker'!$D:$D,"In-place Reversal",'Problem Tracker'!$E:$E,"Full / Partial / K-Group Reversal",'Problem Tracker'!$H:$H,"Easy") -> 1 | K62: =COUNTIFS('Problem Tracker'!$C:$C,"Linked List",'Problem Tracker'!$D:$D,"In-place Reversal",'Problem Tracker'!$E:$E,"Full / Partial / K-Group Reversal",'Problem Tracker'!$H:$H,"Medium") -> 3 | L62: =COUNTIFS('Problem Tracker'!$C:$C,"Linked List",'Problem Tracker'!$D:$D,"In-place Reversal",'Problem Tracker'!$E:$E,"Full / Partial / K-Group Reversal",'Problem Tracker'!$H:$H,"Hard") -> 1 | M62: =COUNTIFS('Problem Tracker'!$C:$C,"Linked List",'Problem Tracker'!$D:$D,"In-place Reversal",'Problem Tracker'!$E:$E,"Full / Partial / K-Group Reversal",'Problem Tracker'!$M:$M,"Solved")+COUNTIFS('Problem Tracker'!$C:$C,"Linked List",'Problem Tracker'!$D:$D,"In-place Reversal",'Problem Tracker'!$E:$E,"Full / Partial / K-Group Reversal",'Problem Tracker'!$M:$M,"Mastered") -> 0 | N62: =IF(I62=0,0,M62/I62) -> 0
A63: Linked List | B63: Pointer Manipulation | C63: Dummy Node / Removal | D63: 🔥 Very High | E63: Delete nodes, head may change | F63: Dummy → head; two pointers n apart for 'nth from end' | G63: O(n) | H63: W06 | I63: =COUNTIFS('Problem Tracker'!$C:$C,"Linked List",'Problem Tracker'!$D:$D,"Pointer Manipulation",'Problem Tracker'!$E:$E,"Dummy Node / Removal") -> 4 | J63: =COUNTIFS('Problem Tracker'!$C:$C,"Linked List",'Problem Tracker'!$D:$D,"Pointer Manipulation",'Problem Tracker'!$E:$E,"Dummy Node / Removal",'Problem Tracker'!$H:$H,"Easy") -> 2 | K63: =COUNTIFS('Problem Tracker'!$C:$C,"Linked List",'Problem Tracker'!$D:$D,"Pointer Manipulation",'Problem Tracker'!$E:$E,"Dummy Node / Removal",'Problem Tracker'!$H:$H,"Medium") -> 2 | L63: =COUNTIFS('Problem Tracker'!$C:$C,"Linked List",'Problem Tracker'!$D:$D,"Pointer Manipulation",'Problem Tracker'!$E:$E,"Dummy Node / Removal",'Problem Tracker'!$H:$H,"Hard") -> 0 | M63: =COUNTIFS('Problem Tracker'!$C:$C,"Linked List",'Problem Tracker'!$D:$D,"Pointer Manipulation",'Problem Tracker'!$E:$E,"Dummy Node / Removal",'Problem Tracker'!$M:$M,"Solved")+COUNTIFS('Problem Tracker'!$C:$C,"Linked List",'Problem Tracker'!$D:$D,"Pointer Manipulation",'Problem Tracker'!$E:$E,"Dummy Node / Removal",'Problem Tracker'!$M:$M,"Mastered") -> 0 | N63: =IF(I63=0,0,M63/I63) -> 0
A64: Linked List | B64: Pointer Manipulation | C64: Merge & Rearrange | D64: 🔥 Very High | E64: Merge sorted lists, reorder, odd/even, partition, rotate | F64: Split → reverse → weave; or build two lists and join | G64: O(n) | H64: W06 | I64: =COUNTIFS('Problem Tracker'!$C:$C,"Linked List",'Problem Tracker'!$D:$D,"Pointer Manipulation",'Problem Tracker'!$E:$E,"Merge & Rearrange") -> 5 | J64: =COUNTIFS('Problem Tracker'!$C:$C,"Linked List",'Problem Tracker'!$D:$D,"Pointer Manipulation",'Problem Tracker'!$E:$E,"Merge & Rearrange",'Problem Tracker'!$H:$H,"Easy") -> 1 | K64: =COUNTIFS('Problem Tracker'!$C:$C,"Linked List",'Problem Tracker'!$D:$D,"Pointer Manipulation",'Problem Tracker'!$E:$E,"Merge & Rearrange",'Problem Tracker'!$H:$H,"Medium") -> 4 | L64: =COUNTIFS('Problem Tracker'!$C:$C,"Linked List",'Problem Tracker'!$D:$D,"Pointer Manipulation",'Problem Tracker'!$E:$E,"Merge & Rearrange",'Problem Tracker'!$H:$H,"Hard") -> 0 | M64: =COUNTIFS('Problem Tracker'!$C:$C,"Linked List",'Problem Tracker'!$D:$D,"Pointer Manipulation",'Problem Tracker'!$E:$E,"Merge & Rearrange",'Problem Tracker'!$M:$M,"Solved")+COUNTIFS('Problem Tracker'!$C:$C,"Linked List",'Problem Tracker'!$D:$D,"Pointer Manipulation",'Problem Tracker'!$E:$E,"Merge & Rearrange",'Problem Tracker'!$M:$M,"Mastered") -> 0 | N64: =IF(I64=0,0,M64/I64) -> 0
A65: Linked List | B65: Pointer Manipulation | C65: Intersection & Arithmetic | D65: High | E65: Shared tail node, add numbers stored as lists | F65: Switch heads trick; carry propagation (stack for forward order) | G65: O(n) | H65: W06 | I65: =COUNTIFS('Problem Tracker'!$C:$C,"Linked List",'Problem Tracker'!$D:$D,"Pointer Manipulation",'Problem Tracker'!$E:$E,"Intersection & Arithmetic") -> 3 | J65: =COUNTIFS('Problem Tracker'!$C:$C,"Linked List",'Problem Tracker'!$D:$D,"Pointer Manipulation",'Problem Tracker'!$E:$E,"Intersection & Arithmetic",'Problem Tracker'!$H:$H,"Easy") -> 1 | K65: =COUNTIFS('Problem Tracker'!$C:$C,"Linked List",'Problem Tracker'!$D:$D,"Pointer Manipulation",'Problem Tracker'!$E:$E,"Intersection & Arithmetic",'Problem Tracker'!$H:$H,"Medium") -> 2 | L65: =COUNTIFS('Problem Tracker'!$C:$C,"Linked List",'Problem Tracker'!$D:$D,"Pointer Manipulation",'Problem Tracker'!$E:$E,"Intersection & Arithmetic",'Problem Tracker'!$H:$H,"Hard") -> 0 | M65: =COUNTIFS('Problem Tracker'!$C:$C,"Linked List",'Problem Tracker'!$D:$D,"Pointer Manipulation",'Problem Tracker'!$E:$E,"Intersection & Arithmetic",'Problem Tracker'!$M:$M,"Solved")+COUNTIFS('Problem Tracker'!$C:$C,"Linked List",'Problem Tracker'!$D:$D,"Pointer Manipulation",'Problem Tracker'!$E:$E,"Intersection & Arithmetic",'Problem Tracker'!$M:$M,"Mastered") -> 0 | N65: =IF(I65=0,0,M65/I65) -> 0
A66: Linked List | B66: Pointer Manipulation | C66: Complex Pointers (Random / Multilevel) | D66: High | E66: Deep copy with extra pointers, flatten child lists | F66: HashMap old→new, or interleave copies in-place | G66: O(n) | H66: W06 | I66: =COUNTIFS('Problem Tracker'!$C:$C,"Linked List",'Problem Tracker'!$D:$D,"Pointer Manipulation",'Problem Tracker'!$E:$E,"Complex Pointers (Random / Multilevel)") -> 3 | J66: =COUNTIFS('Problem Tracker'!$C:$C,"Linked List",'Problem Tracker'!$D:$D,"Pointer Manipulation",'Problem Tracker'!$E:$E,"Complex Pointers (Random / Multilevel)",'Problem Tracker'!$H:$H,"Easy") -> 0 | K66: =COUNTIFS('Problem Tracker'!$C:$C,"Linked List",'Problem Tracker'!$D:$D,"Pointer Manipulation",'Problem Tracker'!$E:$E,"Complex Pointers (Random / Multilevel)",'Problem Tracker'!$H:$H,"Medium") -> 3 | L66: =COUNTIFS('Problem Tracker'!$C:$C,"Linked List",'Problem Tracker'!$D:$D,"Pointer Manipulation",'Problem Tracker'!$E:$E,"Complex Pointers (Random / Multilevel)",'Problem Tracker'!$H:$H,"Hard") -> 0 | M66: =COUNTIFS('Problem Tracker'!$C:$C,"Linked List",'Problem Tracker'!$D:$D,"Pointer Manipulation",'Problem Tracker'!$E:$E,"Complex Pointers (Random / Multilevel)",'Problem Tracker'!$M:$M,"Solved")+COUNTIFS('Problem Tracker'!$C:$C,"Linked List",'Problem Tracker'!$D:$D,"Pointer Manipulation",'Problem Tracker'!$E:$E,"Complex Pointers (Random / Multilevel)",'Problem Tracker'!$M:$M,"Mastered") -> 0 | N66: =IF(I66=0,0,M66/I66) -> 0
A67: ▌ INTERVALS | I67: =COUNTIF('Problem Tracker'!$C:$C,"Intervals") -> 14 | M67: =COUNTIFS('Problem Tracker'!$C:$C,"Intervals",'Problem Tracker'!$M:$M,"Solved")+COUNTIFS('Problem Tracker'!$C:$C,"Intervals",'Problem Tracker'!$M:$M,"Mastered") -> 0 | N67: =IF(I67=0,0,M67/I67) -> 0
A68: Intervals | B68: Interval Patterns | C68: Merge / Insert | D68: 🔥 Very High | E68: Overlapping ranges to combine | F68: Sort by start; merge if start ≤ last end | G68: O(n log n) | H68: W06 | I68: =COUNTIFS('Problem Tracker'!$C:$C,"Intervals",'Problem Tracker'!$D:$D,"Interval Patterns",'Problem Tracker'!$E:$E,"Merge / Insert") -> 3 | J68: =COUNTIFS('Problem Tracker'!$C:$C,"Intervals",'Problem Tracker'!$D:$D,"Interval Patterns",'Problem Tracker'!$E:$E,"Merge / Insert",'Problem Tracker'!$H:$H,"Easy") -> 1 | K68: =COUNTIFS('Problem Tracker'!$C:$C,"Intervals",'Problem Tracker'!$D:$D,"Interval Patterns",'Problem Tracker'!$E:$E,"Merge / Insert",'Problem Tracker'!$H:$H,"Medium") -> 2 | L68: =COUNTIFS('Problem Tracker'!$C:$C,"Intervals",'Problem Tracker'!$D:$D,"Interval Patterns",'Problem Tracker'!$E:$E,"Merge / Insert",'Problem Tracker'!$H:$H,"Hard") -> 0 | M68: =COUNTIFS('Problem Tracker'!$C:$C,"Intervals",'Problem Tracker'!$D:$D,"Interval Patterns",'Problem Tracker'!$E:$E,"Merge / Insert",'Problem Tracker'!$M:$M,"Solved")+COUNTIFS('Problem Tracker'!$C:$C,"Intervals",'Problem Tracker'!$D:$D,"Interval Patterns",'Problem Tracker'!$E:$E,"Merge / Insert",'Problem Tracker'!$M:$M,"Mastered") -> 0 | N68: =IF(I68=0,0,M68/I68) -> 0
A69: Intervals | B69: Interval Patterns | C69: Non-overlap Scheduling (Greedy by End) | D69: 🔥 Very High | E69: Max non-overlapping, min removals, min arrows | F69: Sort by end; take interval if start ≥ last end | G69: O(n log n) | H69: W06 | I69: =COUNTIFS('Problem Tracker'!$C:$C,"Intervals",'Problem Tracker'!$D:$D,"Interval Patterns",'Problem Tracker'!$E:$E,"Non-overlap Scheduling (Greedy by End)") -> 3 | J69: =COUNTIFS('Problem Tracker'!$C:$C,"Intervals",'Problem Tracker'!$D:$D,"Interval Patterns",'Problem Tracker'!$E:$E,"Non-overlap Scheduling (Greedy by End)",'Problem Tracker'!$H:$H,"Easy") -> 1 | K69: =COUNTIFS('Problem Tracker'!$C:$C,"Intervals",'Problem Tracker'!$D:$D,"Interval Patterns",'Problem Tracker'!$E:$E,"Non-overlap Scheduling (Greedy by End)",'Problem Tracker'!$H:$H,"Medium") -> 2 | L69: =COUNTIFS('Problem Tracker'!$C:$C,"Intervals",'Problem Tracker'!$D:$D,"Interval Patterns",'Problem Tracker'!$E:$E,"Non-overlap Scheduling (Greedy by End)",'Problem Tracker'!$H:$H,"Hard") -> 0 | M69: =COUNTIFS('Problem Tracker'!$C:$C,"Intervals",'Problem Tracker'!$D:$D,"Interval Patterns",'Problem Tracker'!$E:$E,"Non-overlap Scheduling (Greedy by End)",'Problem Tracker'!$M:$M,"Solved")+COUNTIFS('Problem Tracker'!$C:$C,"Intervals",'Problem Tracker'!$D:$D,"Interval Patterns",'Problem Tracker'!$E:$E,"Non-overlap Scheduling (Greedy by End)",'Problem Tracker'!$M:$M,"Mastered") -> 0 | N69: =IF(I69=0,0,M69/I69) -> 0
A70: Intervals | B70: Interval Patterns | C70: Sweep Line / Concurrent Count | D70: 🔥 Very High | E70: Min rooms, max overlap at any time, skyline | F70: Events (+1 start, −1 end) sorted; or min-heap of end times | G70: O(n log n) | H70: W06 | I70: =COUNTIFS('Problem Tracker'!$C:$C,"Intervals",'Problem Tracker'!$D:$D,"Interval Patterns",'Problem Tracker'!$E:$E,"Sweep Line / Concurrent Count") -> 5 | J70: =COUNTIFS('Problem Tracker'!$C:$C,"Intervals",'Problem Tracker'!$D:$D,"Interval Patterns",'Problem Tracker'!$E:$E,"Sweep Line / Concurrent Count",'Problem Tracker'!$H:$H,"Easy") -> 0 | K70: =COUNTIFS('Problem Tracker'!$C:$C,"Intervals",'Problem Tracker'!$D:$D,"Interval Patterns",'Problem Tracker'!$E:$E,"Sweep Line / Concurrent Count",'Problem Tracker'!$H:$H,"Medium") -> 1 | L70: =COUNTIFS('Problem Tracker'!$C:$C,"Intervals",'Problem Tracker'!$D:$D,"Interval Patterns",'Problem Tracker'!$E:$E,"Sweep Line / Concurrent Count",'Problem Tracker'!$H:$H,"Hard") -> 4 | M70: =COUNTIFS('Problem Tracker'!$C:$C,"Intervals",'Problem Tracker'!$D:$D,"Interval Patterns",'Problem Tracker'!$E:$E,"Sweep Line / Concurrent Count",'Problem Tracker'!$M:$M,"Solved")+COUNTIFS('Problem Tracker'!$C:$C,"Intervals",'Problem Tracker'!$D:$D,"Interval Patterns",'Problem Tracker'!$E:$E,"Sweep Line / Concurrent Count",'Problem Tracker'!$M:$M,"Mastered") -> 0 | N70: =IF(I70=0,0,M70/I70) -> 0
A71: Intervals | B71: Interval Patterns | C71: Intersection / Booking | D71: High | E71: Intersect two interval lists, check booking conflicts | F71: Two pointers on sorted lists; advance smaller end | G71: O(n + m) | H71: W06 | I71: =COUNTIFS('Problem Tracker'!$C:$C,"Intervals",'Problem Tracker'!$D:$D,"Interval Patterns",'Problem Tracker'!$E:$E,"Intersection / Booking") -> 3 | J71: =COUNTIFS('Problem Tracker'!$C:$C,"Intervals",'Problem Tracker'!$D:$D,"Interval Patterns",'Problem Tracker'!$E:$E,"Intersection / Booking",'Problem Tracker'!$H:$H,"Easy") -> 0 | K71: =COUNTIFS('Problem Tracker'!$C:$C,"Intervals",'Problem Tracker'!$D:$D,"Interval Patterns",'Problem Tracker'!$E:$E,"Intersection / Booking",'Problem Tracker'!$H:$H,"Medium") -> 2 | L71: =COUNTIFS('Problem Tracker'!$C:$C,"Intervals",'Problem Tracker'!$D:$D,"Interval Patterns",'Problem Tracker'!$E:$E,"Intersection / Booking",'Problem Tracker'!$H:$H,"Hard") -> 1 | M71: =COUNTIFS('Problem Tracker'!$C:$C,"Intervals",'Problem Tracker'!$D:$D,"Interval Patterns",'Problem Tracker'!$E:$E,"Intersection / Booking",'Problem Tracker'!$M:$M,"Solved")+COUNTIFS('Problem Tracker'!$C:$C,"Intervals",'Problem Tracker'!$D:$D,"Interval Patterns",'Problem Tracker'!$E:$E,"Intersection / Booking",'Problem Tracker'!$M:$M,"Mastered") -> 0 | N71: =IF(I71=0,0,M71/I71) -> 0
A72: ▌ TREES | I72: =COUNTIF('Problem Tracker'!$C:$C,"Trees") -> 50 | M72: =COUNTIFS('Problem Tracker'!$C:$C,"Trees",'Problem Tracker'!$M:$M,"Solved")+COUNTIFS('Problem Tracker'!$C:$C,"Trees",'Problem Tracker'!$M:$M,"Mastered") -> 0 | N72: =IF(I72=0,0,M72/I72) -> 0
A73: Trees | B73: DFS Traversal | C73: Pre / In / Post-order (Recursive & Iterative) | D73: 🔥 Very High | E73: Visit every node; iterative version asked often | F73: Recursion, or explicit stack (Morris for O(1) space) | G73: O(n) | H73: W07 | I73: =COUNTIFS('Problem Tracker'!$C:$C,"Trees",'Problem Tracker'!$D:$D,"DFS Traversal",'Problem Tracker'!$E:$E,"Pre / In / Post-order (Recursive & Iterative)") -> 3 | J73: =COUNTIFS('Problem Tracker'!$C:$C,"Trees",'Problem Tracker'!$D:$D,"DFS Traversal",'Problem Tracker'!$E:$E,"Pre / In / Post-order (Recursive & Iterative)",'Problem Tracker'!$H:$H,"Easy") -> 3 | K73: =COUNTIFS('Problem Tracker'!$C:$C,"Trees",'Problem Tracker'!$D:$D,"DFS Traversal",'Problem Tracker'!$E:$E,"Pre / In / Post-order (Recursive & Iterative)",'Problem Tracker'!$H:$H,"Medium") -> 0 | L73: =COUNTIFS('Problem Tracker'!$C:$C,"Trees",'Problem Tracker'!$D:$D,"DFS Traversal",'Problem Tracker'!$E:$E,"Pre / In / Post-order (Recursive & Iterative)",'Problem Tracker'!$H:$H,"Hard") -> 0 | M73: =COUNTIFS('Problem Tracker'!$C:$C,"Trees",'Problem Tracker'!$D:$D,"DFS Traversal",'Problem Tracker'!$E:$E,"Pre / In / Post-order (Recursive & Iterative)",'Problem Tracker'!$M:$M,"Solved")+COUNTIFS('Problem Tracker'!$C:$C,"Trees",'Problem Tracker'!$D:$D,"DFS Traversal",'Problem Tracker'!$E:$E,"Pre / In / Post-order (Recursive & Iterative)",'Problem Tracker'!$M:$M,"Mastered") -> 0 | N73: =IF(I73=0,0,M73/I73) -> 0
A74: Trees | B74: DFS Traversal | C74: Structural Comparison | D74: 🔥 Very High | E74: Same / mirror / subtree / invert / merge | F74: Recurse on pairs of nodes | G74: O(n) | H74: W07 | I74: =COUNTIFS('Problem Tracker'!$C:$C,"Trees",'Problem Tracker'!$D:$D,"DFS Traversal",'Problem Tracker'!$E:$E,"Structural Comparison") -> 6 | J74: =COUNTIFS('Problem Tracker'!$C:$C,"Trees",'Problem Tracker'!$D:$D,"DFS Traversal",'Problem Tracker'!$E:$E,"Structural Comparison",'Problem Tracker'!$H:$H,"Easy") -> 6 | K74: =COUNTIFS('Problem Tracker'!$C:$C,"Trees",'Problem Tracker'!$D:$D,"DFS Traversal",'Problem Tracker'!$E:$E,"Structural Comparison",'Problem Tracker'!$H:$H,"Medium") -> 0 | L74: =COUNTIFS('Problem Tracker'!$C:$C,"Trees",'Problem Tracker'!$D:$D,"DFS Traversal",'Problem Tracker'!$E:$E,"Structural Comparison",'Problem Tracker'!$H:$H,"Hard") -> 0 | M74: =COUNTIFS('Problem Tracker'!$C:$C,"Trees",'Problem Tracker'!$D:$D,"DFS Traversal",'Problem Tracker'!$E:$E,"Structural Comparison",'Problem Tracker'!$M:$M,"Solved")+COUNTIFS('Problem Tracker'!$C:$C,"Trees",'Problem Tracker'!$D:$D,"DFS Traversal",'Problem Tracker'!$E:$E,"Structural Comparison",'Problem Tracker'!$M:$M,"Mastered") -> 0 | N74: =IF(I74=0,0,M74/I74) -> 0
A75: Trees | B75: BFS / Level Order | C75: Level-by-Level Processing | D75: 🔥 Very High | E75: Anything 'per level': averages, zigzag, right view, width | F75: Queue; process size-of-level nodes per iteration | G75: O(n) | H75: W07 | I75: =COUNTIFS('Problem Tracker'!$C:$C,"Trees",'Problem Tracker'!$D:$D,"BFS / Level Order",'Problem Tracker'!$E:$E,"Level-by-Level Processing") -> 7 | J75: =COUNTIFS('Problem Tracker'!$C:$C,"Trees",'Problem Tracker'!$D:$D,"BFS / Level Order",'Problem Tracker'!$E:$E,"Level-by-Level Processing",'Problem Tracker'!$H:$H,"Easy") -> 1 | K75: =COUNTIFS('Problem Tracker'!$C:$C,"Trees",'Problem Tracker'!$D:$D,"BFS / Level Order",'Problem Tracker'!$E:$E,"Level-by-Level Processing",'Problem Tracker'!$H:$H,"Medium") -> 6 | L75: =COUNTIFS('Problem Tracker'!$C:$C,"Trees",'Problem Tracker'!$D:$D,"BFS / Level Order",'Problem Tracker'!$E:$E,"Level-by-Level Processing",'Problem Tracker'!$H:$H,"Hard") -> 0 | M75: =COUNTIFS('Problem Tracker'!$C:$C,"Trees",'Problem Tracker'!$D:$D,"BFS / Level Order",'Problem Tracker'!$E:$E,"Level-by-Level Processing",'Problem Tracker'!$M:$M,"Solved")+COUNTIFS('Problem Tracker'!$C:$C,"Trees",'Problem Tracker'!$D:$D,"BFS / Level Order",'Problem Tracker'!$E:$E,"Level-by-Level Processing",'Problem Tracker'!$M:$M,"Mastered") -> 0 | N75: =IF(I75=0,0,M75/I75) -> 0
A76: Trees | B76: BFS / Level Order | C76: Vertical Order / Distance from Node | D76: High | E76: Columns, nodes at distance K, infection spread | F76: Assign (row, col) coords; or convert to graph with parent map + BFS | G76: O(n log n) | H76: W07 | I76: =COUNTIFS('Problem Tracker'!$C:$C,"Trees",'Problem Tracker'!$D:$D,"BFS / Level Order",'Problem Tracker'!$E:$E,"Vertical Order / Distance from Node") -> 3 | J76: =COUNTIFS('Problem Tracker'!$C:$C,"Trees",'Problem Tracker'!$D:$D,"BFS / Level Order",'Problem Tracker'!$E:$E,"Vertical Order / Distance from Node",'Problem Tracker'!$H:$H,"Easy") -> 0 | K76: =COUNTIFS('Problem Tracker'!$C:$C,"Trees",'Problem Tracker'!$D:$D,"BFS / Level Order",'Problem Tracker'!$E:$E,"Vertical Order / Distance from Node",'Problem Tracker'!$H:$H,"Medium") -> 2 | L76: =COUNTIFS('Problem Tracker'!$C:$C,"Trees",'Problem Tracker'!$D:$D,"BFS / Level Order",'Problem Tracker'!$E:$E,"Vertical Order / Distance from Node",'Problem Tracker'!$H:$H,"Hard") -> 1 | M76: =COUNTIFS('Problem Tracker'!$C:$C,"Trees",'Problem Tracker'!$D:$D,"BFS / Level Order",'Problem Tracker'!$E:$E,"Vertical Order / Distance from Node",'Problem Tracker'!$M:$M,"Solved")+COUNTIFS('Problem Tracker'!$C:$C,"Trees",'Problem Tracker'!$D:$D,"BFS / Level Order",'Problem Tracker'!$E:$E,"Vertical Order / Distance from Node",'Problem Tracker'!$M:$M,"Mastered") -> 0 | N76: =IF(I76=0,0,M76/I76) -> 0
A77: Trees | B77: Recursive Return Values | C77: Bottom-up (Height / Diameter / Balance) | D77: 🔥 Very High | E77: Answer at node needs children's answers | F77: Return height up; update global answer at each node | G77: O(n) | H77: W08 | I77: =COUNTIFS('Problem Tracker'!$C:$C,"Trees",'Problem Tracker'!$D:$D,"Recursive Return Values",'Problem Tracker'!$E:$E,"Bottom-up (Height / Diameter / Balance)") -> 5 | J77: =COUNTIFS('Problem Tracker'!$C:$C,"Trees",'Problem Tracker'!$D:$D,"Recursive Return Values",'Problem Tracker'!$E:$E,"Bottom-up (Height / Diameter / Balance)",'Problem Tracker'!$H:$H,"Easy") -> 4 | K77: =COUNTIFS('Problem Tracker'!$C:$C,"Trees",'Problem Tracker'!$D:$D,"Recursive Return Values",'Problem Tracker'!$E:$E,"Bottom-up (Height / Diameter / Balance)",'Problem Tracker'!$H:$H,"Medium") -> 0 | L77: =COUNTIFS('Problem Tracker'!$C:$C,"Trees",'Problem Tracker'!$D:$D,"Recursive Return Values",'Problem Tracker'!$E:$E,"Bottom-up (Height / Diameter / Balance)",'Problem Tracker'!$H:$H,"Hard") -> 1 | M77: =COUNTIFS('Problem Tracker'!$C:$C,"Trees",'Problem Tracker'!$D:$D,"Recursive Return Values",'Problem Tracker'!$E:$E,"Bottom-up (Height / Diameter / Balance)",'Problem Tracker'!$M:$M,"Solved")+COUNTIFS('Problem Tracker'!$C:$C,"Trees",'Problem Tracker'!$D:$D,"Recursive Return Values",'Problem Tracker'!$E:$E,"Bottom-up (Height / Diameter / Balance)",'Problem Tracker'!$M:$M,"Mastered") -> 0 | N77: =IF(I77=0,0,M77/I77) -> 0
A78: Trees | B78: Recursive Return Values | C78: Top-down (Root-to-Leaf Paths) | D78: 🔥 Very High | E78: Path sums, carrying state from root downwards | F78: Pass running value/max as parameter; backtrack path list | G78: O(n) | H78: W08 | I78: =COUNTIFS('Problem Tracker'!$C:$C,"Trees",'Problem Tracker'!$D:$D,"Recursive Return Values",'Problem Tracker'!$E:$E,"Top-down (Root-to-Leaf Paths)") -> 7 | J78: =COUNTIFS('Problem Tracker'!$C:$C,"Trees",'Problem Tracker'!$D:$D,"Recursive Return Values",'Problem Tracker'!$E:$E,"Top-down (Root-to-Leaf Paths)",'Problem Tracker'!$H:$H,"Easy") -> 2 | K78: =COUNTIFS('Problem Tracker'!$C:$C,"Trees",'Problem Tracker'!$D:$D,"Recursive Return Values",'Problem Tracker'!$E:$E,"Top-down (Root-to-Leaf Paths)",'Problem Tracker'!$H:$H,"Medium") -> 5 | L78: =COUNTIFS('Problem Tracker'!$C:$C,"Trees",'Problem Tracker'!$D:$D,"Recursive Return Values",'Problem Tracker'!$E:$E,"Top-down (Root-to-Leaf Paths)",'Problem Tracker'!$H:$H,"Hard") -> 0 | M78: =COUNTIFS('Problem Tracker'!$C:$C,"Trees",'Problem Tracker'!$D:$D,"Recursive Return Values",'Problem Tracker'!$E:$E,"Top-down (Root-to-Leaf Paths)",'Problem Tracker'!$M:$M,"Solved")+COUNTIFS('Problem Tracker'!$C:$C,"Trees",'Problem Tracker'!$D:$D,"Recursive Return Values",'Problem Tracker'!$E:$E,"Top-down (Root-to-Leaf Paths)",'Problem Tracker'!$M:$M,"Mastered") -> 0 | N78: =IF(I78=0,0,M78/I78) -> 0
A79: Trees | B79: Recursive Return Values | C79: Lowest Common Ancestor | D79: 🔥 Very High | E79: Shared ancestor of two nodes | F79: Return node if found; if both sides non-null → current is LCA | G79: O(n) | H79: W08 | I79: =COUNTIFS('Problem Tracker'!$C:$C,"Trees",'Problem Tracker'!$D:$D,"Recursive Return Values",'Problem Tracker'!$E:$E,"Lowest Common Ancestor") -> 3 | J79: =COUNTIFS('Problem Tracker'!$C:$C,"Trees",'Problem Tracker'!$D:$D,"Recursive Return Values",'Problem Tracker'!$E:$E,"Lowest Common Ancestor",'Problem Tracker'!$H:$H,"Easy") -> 0 | K79: =COUNTIFS('Problem Tracker'!$C:$C,"Trees",'Problem Tracker'!$D:$D,"Recursive Return Values",'Problem Tracker'!$E:$E,"Lowest Common Ancestor",'Problem Tracker'!$H:$H,"Medium") -> 3 | L79: =COUNTIFS('Problem Tracker'!$C:$C,"Trees",'Problem Tracker'!$D:$D,"Recursive Return Values",'Problem Tracker'!$E:$E,"Lowest Common Ancestor",'Problem Tracker'!$H:$H,"Hard") -> 0 | M79: =COUNTIFS('Problem Tracker'!$C:$C,"Trees",'Problem Tracker'!$D:$D,"Recursive Return Values",'Problem Tracker'!$E:$E,"Lowest Common Ancestor",'Problem Tracker'!$M:$M,"Solved")+COUNTIFS('Problem Tracker'!$C:$C,"Trees",'Problem Tracker'!$D:$D,"Recursive Return Values",'Problem Tracker'!$E:$E,"Lowest Common Ancestor",'Problem Tracker'!$M:$M,"Mastered") -> 0 | N79: =IF(I79=0,0,M79/I79) -> 0
A80: Trees | B80: Binary Search Tree | C80: BST Operations | D80: High | E80: Search / insert / delete using ordering property | F80: Go left if smaller, right if larger; handle 0/1/2 children on delete | G80: O(h) | H80: W08 | I80: =COUNTIFS('Problem Tracker'!$C:$C,"Trees",'Problem Tracker'!$D:$D,"Binary Search Tree",'Problem Tracker'!$E:$E,"BST Operations") -> 4 | J80: =COUNTIFS('Problem Tracker'!$C:$C,"Trees",'Problem Tracker'!$D:$D,"Binary Search Tree",'Problem Tracker'!$E:$E,"BST Operations",'Problem Tracker'!$H:$H,"Easy") -> 2 | K80: =COUNTIFS('Problem Tracker'!$C:$C,"Trees",'Problem Tracker'!$D:$D,"Binary Search Tree",'Problem Tracker'!$E:$E,"BST Operations",'Problem Tracker'!$H:$H,"Medium") -> 2 | L80: =COUNTIFS('Problem Tracker'!$C:$C,"Trees",'Problem Tracker'!$D:$D,"Binary Search Tree",'Problem Tracker'!$E:$E,"BST Operations",'Problem Tracker'!$H:$H,"Hard") -> 0 | M80: =COUNTIFS('Problem Tracker'!$C:$C,"Trees",'Problem Tracker'!$D:$D,"Binary Search Tree",'Problem Tracker'!$E:$E,"BST Operations",'Problem Tracker'!$M:$M,"Solved")+COUNTIFS('Problem Tracker'!$C:$C,"Trees",'Problem Tracker'!$D:$D,"Binary Search Tree",'Problem Tracker'!$E:$E,"BST Operations",'Problem Tracker'!$M:$M,"Mastered") -> 0 | N80: =IF(I80=0,0,M80/I80) -> 0
A81: Trees | B81: Binary Search Tree | C81: BST Validation & In-order Property | D81: 🔥 Very High | E81: Validate, kth smallest, iterator, recover swapped nodes | F81: In-order of BST is sorted; or pass (min, max) bounds | G81: O(n) / O(h) | H81: W08 | I81: =COUNTIFS('Problem Tracker'!$C:$C,"Trees",'Problem Tracker'!$D:$D,"Binary Search Tree",'Problem Tracker'!$E:$E,"BST Validation & In-order Property") -> 5 | J81: =COUNTIFS('Problem Tracker'!$C:$C,"Trees",'Problem Tracker'!$D:$D,"Binary Search Tree",'Problem Tracker'!$E:$E,"BST Validation & In-order Property",'Problem Tracker'!$H:$H,"Easy") -> 1 | K81: =COUNTIFS('Problem Tracker'!$C:$C,"Trees",'Problem Tracker'!$D:$D,"Binary Search Tree",'Problem Tracker'!$E:$E,"BST Validation & In-order Property",'Problem Tracker'!$H:$H,"Medium") -> 4 | L81: =COUNTIFS('Problem Tracker'!$C:$C,"Trees",'Problem Tracker'!$D:$D,"Binary Search Tree",'Problem Tracker'!$E:$E,"BST Validation & In-order Property",'Problem Tracker'!$H:$H,"Hard") -> 0 | M81: =COUNTIFS('Problem Tracker'!$C:$C,"Trees",'Problem Tracker'!$D:$D,"Binary Search Tree",'Problem Tracker'!$E:$E,"BST Validation & In-order Property",'Problem Tracker'!$M:$M,"Solved")+COUNTIFS('Problem Tracker'!$C:$C,"Trees",'Problem Tracker'!$D:$D,"Binary Search Tree",'Problem Tracker'!$E:$E,"BST Validation & In-order Property",'Problem Tracker'!$M:$M,"Mastered") -> 0 | N81: =IF(I81=0,0,M81/I81) -> 0
A82: Trees | B82: Construction & Serialization | C82: Build Tree from Traversals | D82: 🔥 Very High | E82: Given two traversals (or one for BST), rebuild tree | F82: Root from pre/post; split by inorder index (hashmap) | G82: O(n) | H82: W08 | I82: =COUNTIFS('Problem Tracker'!$C:$C,"Trees",'Problem Tracker'!$D:$D,"Construction & Serialization",'Problem Tracker'!$E:$E,"Build Tree from Traversals") -> 4 | J82: =COUNTIFS('Problem Tracker'!$C:$C,"Trees",'Problem Tracker'!$D:$D,"Construction & Serialization",'Problem Tracker'!$E:$E,"Build Tree from Traversals",'Problem Tracker'!$H:$H,"Easy") -> 0 | K82: =COUNTIFS('Problem Tracker'!$C:$C,"Trees",'Problem Tracker'!$D:$D,"Construction & Serialization",'Problem Tracker'!$E:$E,"Build Tree from Traversals",'Problem Tracker'!$H:$H,"Medium") -> 4 | L82: =COUNTIFS('Problem Tracker'!$C:$C,"Trees",'Problem Tracker'!$D:$D,"Construction & Serialization",'Problem Tracker'!$E:$E,"Build Tree from Traversals",'Problem Tracker'!$H:$H,"Hard") -> 0 | M82: =COUNTIFS('Problem Tracker'!$C:$C,"Trees",'Problem Tracker'!$D:$D,"Construction & Serialization",'Problem Tracker'!$E:$E,"Build Tree from Traversals",'Problem Tracker'!$M:$M,"Solved")+COUNTIFS('Problem Tracker'!$C:$C,"Trees",'Problem Tracker'!$D:$D,"Construction & Serialization",'Problem Tracker'!$E:$E,"Build Tree from Traversals",'Problem Tracker'!$M:$M,"Mastered") -> 0 | N82: =IF(I82=0,0,M82/I82) -> 0
A83: Trees | B83: Construction & Serialization | C83: Serialize / Flatten | D83: 🔥 Very High | E83: Convert tree ↔ string, flatten to list | F83: Preorder with null markers; reverse-postorder for flatten | G83: O(n) | H83: W08 | I83: =COUNTIFS('Problem Tracker'!$C:$C,"Trees",'Problem Tracker'!$D:$D,"Construction & Serialization",'Problem Tracker'!$E:$E,"Serialize / Flatten") -> 3 | J83: =COUNTIFS('Problem Tracker'!$C:$C,"Trees",'Problem Tracker'!$D:$D,"Construction & Serialization",'Problem Tracker'!$E:$E,"Serialize / Flatten",'Problem Tracker'!$H:$H,"Easy") -> 0 | K83: =COUNTIFS('Problem Tracker'!$C:$C,"Trees",'Problem Tracker'!$D:$D,"Construction & Serialization",'Problem Tracker'!$E:$E,"Serialize / Flatten",'Problem Tracker'!$H:$H,"Medium") -> 2 | L83: =COUNTIFS('Problem Tracker'!$C:$C,"Trees",'Problem Tracker'!$D:$D,"Construction & Serialization",'Problem Tracker'!$E:$E,"Serialize / Flatten",'Problem Tracker'!$H:$H,"Hard") -> 1 | M83: =COUNTIFS('Problem Tracker'!$C:$C,"Trees",'Problem Tracker'!$D:$D,"Construction & Serialization",'Problem Tracker'!$E:$E,"Serialize / Flatten",'Problem Tracker'!$M:$M,"Solved")+COUNTIFS('Problem Tracker'!$C:$C,"Trees",'Problem Tracker'!$D:$D,"Construction & Serialization",'Problem Tracker'!$E:$E,"Serialize / Flatten",'Problem Tracker'!$M:$M,"Mastered") -> 0 | N83: =IF(I83=0,0,M83/I83) -> 0
A84: ▌ HEAP / PRIORITY QUEUE | I84: =COUNTIF('Problem Tracker'!$C:$C,"Heap / Priority Queue") -> 19 | M84: =COUNTIFS('Problem Tracker'!$C:$C,"Heap / Priority Queue",'Problem Tracker'!$M:$M,"Solved")+COUNTIFS('Problem Tracker'!$C:$C,"Heap / Priority Queue",'Problem Tracker'!$M:$M,"Mastered") -> 0 | N84: =IF(I84=0,0,M84/I84) -> 0
A85: Heap / Priority Queue | B85: Heap Patterns | C85: Top-K Elements | D85: 🔥 Very High | E85: 'k largest / smallest / most frequent / closest' | F85: Min-heap of size k (or quickselect / bucket sort) | G85: O(n log k) | H85: W09 | I85: =COUNTIFS('Problem Tracker'!$C:$C,"Heap / Priority Queue",'Problem Tracker'!$D:$D,"Heap Patterns",'Problem Tracker'!$E:$E,"Top-K Elements") -> 6 | J85: =COUNTIFS('Problem Tracker'!$C:$C,"Heap / Priority Queue",'Problem Tracker'!$D:$D,"Heap Patterns",'Problem Tracker'!$E:$E,"Top-K Elements",'Problem Tracker'!$H:$H,"Easy") -> 2 | K85: =COUNTIFS('Problem Tracker'!$C:$C,"Heap / Priority Queue",'Problem Tracker'!$D:$D,"Heap Patterns",'Problem Tracker'!$E:$E,"Top-K Elements",'Problem Tracker'!$H:$H,"Medium") -> 4 | L85: =COUNTIFS('Problem Tracker'!$C:$C,"Heap / Priority Queue",'Problem Tracker'!$D:$D,"Heap Patterns",'Problem Tracker'!$E:$E,"Top-K Elements",'Problem Tracker'!$H:$H,"Hard") -> 0 | M85: =COUNTIFS('Problem Tracker'!$C:$C,"Heap / Priority Queue",'Problem Tracker'!$D:$D,"Heap Patterns",'Problem Tracker'!$E:$E,"Top-K Elements",'Problem Tracker'!$M:$M,"Solved")+COUNTIFS('Problem Tracker'!$C:$C,"Heap / Priority Queue",'Problem Tracker'!$D:$D,"Heap Patterns",'Problem Tracker'!$E:$E,"Top-K Elements",'Problem Tracker'!$M:$M,"Mastered") -> 0 | N85: =IF(I85=0,0,M85/I85) -> 0
A86: Heap / Priority Queue | B86: Heap Patterns | C86: K-way Merge | D86: 🔥 Very High | E86: Merge k sorted lists/arrays, smallest pairs across lists | F86: Heap holds one head from each list; pop & push next | G86: O(N log k) | H86: W09 | I86: =COUNTIFS('Problem Tracker'!$C:$C,"Heap / Priority Queue",'Problem Tracker'!$D:$D,"Heap Patterns",'Problem Tracker'!$E:$E,"K-way Merge") -> 3 | J86: =COUNTIFS('Problem Tracker'!$C:$C,"Heap / Priority Queue",'Problem Tracker'!$D:$D,"Heap Patterns",'Problem Tracker'!$E:$E,"K-way Merge",'Problem Tracker'!$H:$H,"Easy") -> 0 | K86: =COUNTIFS('Problem Tracker'!$C:$C,"Heap / Priority Queue",'Problem Tracker'!$D:$D,"Heap Patterns",'Problem Tracker'!$E:$E,"K-way Merge",'Problem Tracker'!$H:$H,"Medium") -> 1 | L86: =COUNTIFS('Problem Tracker'!$C:$C,"Heap / Priority Queue",'Problem Tracker'!$D:$D,"Heap Patterns",'Problem Tracker'!$E:$E,"K-way Merge",'Problem Tracker'!$H:$H,"Hard") -> 2 | M86: =COUNTIFS('Problem Tracker'!$C:$C,"Heap / Priority Queue",'Problem Tracker'!$D:$D,"Heap Patterns",'Problem Tracker'!$E:$E,"K-way Merge",'Problem Tracker'!$M:$M,"Solved")+COUNTIFS('Problem Tracker'!$C:$C,"Heap / Priority Queue",'Problem Tracker'!$D:$D,"Heap Patterns",'Problem Tracker'!$E:$E,"K-way Merge",'Problem Tracker'!$M:$M,"Mastered") -> 0 | N86: =IF(I86=0,0,M86/I86) -> 0
A87: Heap / Priority Queue | B87: Heap Patterns | C87: Two Heaps | D87: 🔥 Very High | E87: Running median, balance lower & upper halves | F87: Max-heap for low half, min-heap for high half; rebalance sizes | G87: O(log n) per op | H87: W09 | I87: =COUNTIFS('Problem Tracker'!$C:$C,"Heap / Priority Queue",'Problem Tracker'!$D:$D,"Heap Patterns",'Problem Tracker'!$E:$E,"Two Heaps") -> 3 | J87: =COUNTIFS('Problem Tracker'!$C:$C,"Heap / Priority Queue",'Problem Tracker'!$D:$D,"Heap Patterns",'Problem Tracker'!$E:$E,"Two Heaps",'Problem Tracker'!$H:$H,"Easy") -> 0 | K87: =COUNTIFS('Problem Tracker'!$C:$C,"Heap / Priority Queue",'Problem Tracker'!$D:$D,"Heap Patterns",'Problem Tracker'!$E:$E,"Two Heaps",'Problem Tracker'!$H:$H,"Medium") -> 0 | L87: =COUNTIFS('Problem Tracker'!$C:$C,"Heap / Priority Queue",'Problem Tracker'!$D:$D,"Heap Patterns",'Problem Tracker'!$E:$E,"Two Heaps",'Problem Tracker'!$H:$H,"Hard") -> 3 | M87: =COUNTIFS('Problem Tracker'!$C:$C,"Heap / Priority Queue",'Problem Tracker'!$D:$D,"Heap Patterns",'Problem Tracker'!$E:$E,"Two Heaps",'Problem Tracker'!$M:$M,"Solved")+COUNTIFS('Problem Tracker'!$C:$C,"Heap / Priority Queue",'Problem Tracker'!$D:$D,"Heap Patterns",'Problem Tracker'!$E:$E,"Two Heaps",'Problem Tracker'!$M:$M,"Mastered") -> 0 | N87: =IF(I87=0,0,M87/I87) -> 0
A88: Heap / Priority Queue | B88: Heap Patterns | C88: Greedy Scheduling with Heap | D88: High | E88: Pick best available option repeatedly (tasks, CPU, refuel) | F88: Sort by time; heap of available candidates | G88: O(n log n) | H88: W09 | I88: =COUNTIFS('Problem Tracker'!$C:$C,"Heap / Priority Queue",'Problem Tracker'!$D:$D,"Heap Patterns",'Problem Tracker'!$E:$E,"Greedy Scheduling with Heap") -> 7 | J88: =COUNTIFS('Problem Tracker'!$C:$C,"Heap / Priority Queue",'Problem Tracker'!$D:$D,"Heap Patterns",'Problem Tracker'!$E:$E,"Greedy Scheduling with Heap",'Problem Tracker'!$H:$H,"Easy") -> 0 | K88: =COUNTIFS('Problem Tracker'!$C:$C,"Heap / Priority Queue",'Problem Tracker'!$D:$D,"Heap Patterns",'Problem Tracker'!$E:$E,"Greedy Scheduling with Heap",'Problem Tracker'!$H:$H,"Medium") -> 5 | L88: =COUNTIFS('Problem Tracker'!$C:$C,"Heap / Priority Queue",'Problem Tracker'!$D:$D,"Heap Patterns",'Problem Tracker'!$E:$E,"Greedy Scheduling with Heap",'Problem Tracker'!$H:$H,"Hard") -> 2 | M88: =COUNTIFS('Problem Tracker'!$C:$C,"Heap / Priority Queue",'Problem Tracker'!$D:$D,"Heap Patterns",'Problem Tracker'!$E:$E,"Greedy Scheduling with Heap",'Problem Tracker'!$M:$M,"Solved")+COUNTIFS('Problem Tracker'!$C:$C,"Heap / Priority Queue",'Problem Tracker'!$D:$D,"Heap Patterns",'Problem Tracker'!$E:$E,"Greedy Scheduling with Heap",'Problem Tracker'!$M:$M,"Mastered") -> 0 | N88: =IF(I88=0,0,M88/I88) -> 0
A89: ▌ RECURSION & BACKTRACKING | I89: =COUNTIF('Problem Tracker'!$C:$C,"Recursion & Backtracking") -> 27 | M89: =COUNTIFS('Problem Tracker'!$C:$C,"Recursion & Backtracking",'Problem Tracker'!$M:$M,"Solved")+COUNTIFS('Problem Tracker'!$C:$C,"Recursion & Backtracking",'Problem Tracker'!$M:$M,"Mastered") -> 0 | N89: =IF(I89=0,0,M89/I89) -> 0
A90: Recursion & Backtracking | B90: Recursion Basics | C90: Divide & Recurse | D90: High | E90: Problem reduces to a smaller copy of itself | F90: Base case + recursive relation; fast power halves n | G90: Varies | H90: W10 | I90: =COUNTIFS('Problem Tracker'!$C:$C,"Recursion & Backtracking",'Problem Tracker'!$D:$D,"Recursion Basics",'Problem Tracker'!$E:$E,"Divide & Recurse") -> 5 | J90: =COUNTIFS('Problem Tracker'!$C:$C,"Recursion & Backtracking",'Problem Tracker'!$D:$D,"Recursion Basics",'Problem Tracker'!$E:$E,"Divide & Recurse",'Problem Tracker'!$H:$H,"Easy") -> 1 | K90: =COUNTIFS('Problem Tracker'!$C:$C,"Recursion & Backtracking",'Problem Tracker'!$D:$D,"Recursion Basics",'Problem Tracker'!$E:$E,"Divide & Recurse",'Problem Tracker'!$H:$H,"Medium") -> 4 | L90: =COUNTIFS('Problem Tracker'!$C:$C,"Recursion & Backtracking",'Problem Tracker'!$D:$D,"Recursion Basics",'Problem Tracker'!$E:$E,"Divide & Recurse",'Problem Tracker'!$H:$H,"Hard") -> 0 | M90: =COUNTIFS('Problem Tracker'!$C:$C,"Recursion & Backtracking",'Problem Tracker'!$D:$D,"Recursion Basics",'Problem Tracker'!$E:$E,"Divide & Recurse",'Problem Tracker'!$M:$M,"Solved")+COUNTIFS('Problem Tracker'!$C:$C,"Recursion & Backtracking",'Problem Tracker'!$D:$D,"Recursion Basics",'Problem Tracker'!$E:$E,"Divide & Recurse",'Problem Tracker'!$M:$M,"Mastered") -> 0 | N90: =IF(I90=0,0,M90/I90) -> 0
A91: Recursion & Backtracking | B91: Backtracking | C91: Subsets (Include / Exclude) | D91: 🔥 Very High | E91: 'All subsets', power set, case permutations | F91: At each index choose take / skip; sort + skip dups | G91: O(n·2ⁿ) | H91: W10 | I91: =COUNTIFS('Problem Tracker'!$C:$C,"Recursion & Backtracking",'Problem Tracker'!$D:$D,"Backtracking",'Problem Tracker'!$E:$E,"Subsets (Include / Exclude)") -> 3 | J91: =COUNTIFS('Problem Tracker'!$C:$C,"Recursion & Backtracking",'Problem Tracker'!$D:$D,"Backtracking",'Problem Tracker'!$E:$E,"Subsets (Include / Exclude)",'Problem Tracker'!$H:$H,"Easy") -> 0 | K91: =COUNTIFS('Problem Tracker'!$C:$C,"Recursion & Backtracking",'Problem Tracker'!$D:$D,"Backtracking",'Problem Tracker'!$E:$E,"Subsets (Include / Exclude)",'Problem Tracker'!$H:$H,"Medium") -> 3 | L91: =COUNTIFS('Problem Tracker'!$C:$C,"Recursion & Backtracking",'Problem Tracker'!$D:$D,"Backtracking",'Problem Tracker'!$E:$E,"Subsets (Include / Exclude)",'Problem Tracker'!$H:$H,"Hard") -> 0 | M91: =COUNTIFS('Problem Tracker'!$C:$C,"Recursion & Backtracking",'Problem Tracker'!$D:$D,"Backtracking",'Problem Tracker'!$E:$E,"Subsets (Include / Exclude)",'Problem Tracker'!$M:$M,"Solved")+COUNTIFS('Problem Tracker'!$C:$C,"Recursion & Backtracking",'Problem Tracker'!$D:$D,"Backtracking",'Problem Tracker'!$E:$E,"Subsets (Include / Exclude)",'Problem Tracker'!$M:$M,"Mastered") -> 0 | N91: =IF(I91=0,0,M91/I91) -> 0
A92: Recursion & Backtracking | B92: Backtracking | C92: Permutations | D92: 🔥 Very High | E92: All orderings | F92: used[] array or swap-in-place; skip duplicate choices at same depth | G92: O(n·n!) | H92: W10 | I92: =COUNTIFS('Problem Tracker'!$C:$C,"Recursion & Backtracking",'Problem Tracker'!$D:$D,"Backtracking",'Problem Tracker'!$E:$E,"Permutations") -> 3 | J92: =COUNTIFS('Problem Tracker'!$C:$C,"Recursion & Backtracking",'Problem Tracker'!$D:$D,"Backtracking",'Problem Tracker'!$E:$E,"Permutations",'Problem Tracker'!$H:$H,"Easy") -> 0 | K92: =COUNTIFS('Problem Tracker'!$C:$C,"Recursion & Backtracking",'Problem Tracker'!$D:$D,"Backtracking",'Problem Tracker'!$E:$E,"Permutations",'Problem Tracker'!$H:$H,"Medium") -> 2 | L92: =COUNTIFS('Problem Tracker'!$C:$C,"Recursion & Backtracking",'Problem Tracker'!$D:$D,"Backtracking",'Problem Tracker'!$E:$E,"Permutations",'Problem Tracker'!$H:$H,"Hard") -> 1 | M92: =COUNTIFS('Problem Tracker'!$C:$C,"Recursion & Backtracking",'Problem Tracker'!$D:$D,"Backtracking",'Problem Tracker'!$E:$E,"Permutations",'Problem Tracker'!$M:$M,"Solved")+COUNTIFS('Problem Tracker'!$C:$C,"Recursion & Backtracking",'Problem Tracker'!$D:$D,"Backtracking",'Problem Tracker'!$E:$E,"Permutations",'Problem Tracker'!$M:$M,"Mastered") -> 0 | N92: =IF(I92=0,0,M92/I92) -> 0
A93: Recursion & Backtracking | B93: Backtracking | C93: Combinations / Combination Sum | D93: 🔥 Very High | E93: Choose k items, or items summing to target (reuse or not) | F93: start index to avoid repeats; prune when sum > target | G93: O(2ⁿ) | H93: W10 | I93: =COUNTIFS('Problem Tracker'!$C:$C,"Recursion & Backtracking",'Problem Tracker'!$D:$D,"Backtracking",'Problem Tracker'!$E:$E,"Combinations / Combination Sum") -> 5 | J93: =COUNTIFS('Problem Tracker'!$C:$C,"Recursion & Backtracking",'Problem Tracker'!$D:$D,"Backtracking",'Problem Tracker'!$E:$E,"Combinations / Combination Sum",'Problem Tracker'!$H:$H,"Easy") -> 0 | K93: =COUNTIFS('Problem Tracker'!$C:$C,"Recursion & Backtracking",'Problem Tracker'!$D:$D,"Backtracking",'Problem Tracker'!$E:$E,"Combinations / Combination Sum",'Problem Tracker'!$H:$H,"Medium") -> 5 | L93: =COUNTIFS('Problem Tracker'!$C:$C,"Recursion & Backtracking",'Problem Tracker'!$D:$D,"Backtracking",'Problem Tracker'!$E:$E,"Combinations / Combination Sum",'Problem Tracker'!$H:$H,"Hard") -> 0 | M93: =COUNTIFS('Problem Tracker'!$C:$C,"Recursion & Backtracking",'Problem Tracker'!$D:$D,"Backtracking",'Problem Tracker'!$E:$E,"Combinations / Combination Sum",'Problem Tracker'!$M:$M,"Solved")+COUNTIFS('Problem Tracker'!$C:$C,"Recursion & Backtracking",'Problem Tracker'!$D:$D,"Backtracking",'Problem Tracker'!$E:$E,"Combinations / Combination Sum",'Problem Tracker'!$M:$M,"Mastered") -> 0 | N93: =IF(I93=0,0,M93/I93) -> 0
A94: Recursion & Backtracking | B94: Backtracking | C94: Partitioning | D94: High | E94: Split string/array into valid pieces (palindromes, IPs, equal sums) | F94: Try every cut point; recurse on remainder | G94: Exponential | H94: W10 | I94: =COUNTIFS('Problem Tracker'!$C:$C,"Recursion & Backtracking",'Problem Tracker'!$D:$D,"Backtracking",'Problem Tracker'!$E:$E,"Partitioning") -> 4 | J94: =COUNTIFS('Problem Tracker'!$C:$C,"Recursion & Backtracking",'Problem Tracker'!$D:$D,"Backtracking",'Problem Tracker'!$E:$E,"Partitioning",'Problem Tracker'!$H:$H,"Easy") -> 0 | K94: =COUNTIFS('Problem Tracker'!$C:$C,"Recursion & Backtracking",'Problem Tracker'!$D:$D,"Backtracking",'Problem Tracker'!$E:$E,"Partitioning",'Problem Tracker'!$H:$H,"Medium") -> 3 | L94: =COUNTIFS('Problem Tracker'!$C:$C,"Recursion & Backtracking",'Problem Tracker'!$D:$D,"Backtracking",'Problem Tracker'!$E:$E,"Partitioning",'Problem Tracker'!$H:$H,"Hard") -> 1 | M94: =COUNTIFS('Problem Tracker'!$C:$C,"Recursion & Backtracking",'Problem Tracker'!$D:$D,"Backtracking",'Problem Tracker'!$E:$E,"Partitioning",'Problem Tracker'!$M:$M,"Solved")+COUNTIFS('Problem Tracker'!$C:$C,"Recursion & Backtracking",'Problem Tracker'!$D:$D,"Backtracking",'Problem Tracker'!$E:$E,"Partitioning",'Problem Tracker'!$M:$M,"Mastered") -> 0 | N94: =IF(I94=0,0,M94/I94) -> 0
A95: Recursion & Backtracking | B95: Backtracking | C95: Generate Valid Structures | D95: 🔥 Very High | E95: Generate all well-formed strings/sequences | F95: Track counts (open/close) as constraints while building | G95: Catalan / 2ⁿ | H95: W10 | I95: =COUNTIFS('Problem Tracker'!$C:$C,"Recursion & Backtracking",'Problem Tracker'!$D:$D,"Backtracking",'Problem Tracker'!$E:$E,"Generate Valid Structures") -> 3 | J95: =COUNTIFS('Problem Tracker'!$C:$C,"Recursion & Backtracking",'Problem Tracker'!$D:$D,"Backtracking",'Problem Tracker'!$E:$E,"Generate Valid Structures",'Problem Tracker'!$H:$H,"Easy") -> 0 | K95: =COUNTIFS('Problem Tracker'!$C:$C,"Recursion & Backtracking",'Problem Tracker'!$D:$D,"Backtracking",'Problem Tracker'!$E:$E,"Generate Valid Structures",'Problem Tracker'!$H:$H,"Medium") -> 2 | L95: =COUNTIFS('Problem Tracker'!$C:$C,"Recursion & Backtracking",'Problem Tracker'!$D:$D,"Backtracking",'Problem Tracker'!$E:$E,"Generate Valid Structures",'Problem Tracker'!$H:$H,"Hard") -> 1 | M95: =COUNTIFS('Problem Tracker'!$C:$C,"Recursion & Backtracking",'Problem Tracker'!$D:$D,"Backtracking",'Problem Tracker'!$E:$E,"Generate Valid Structures",'Problem Tracker'!$M:$M,"Solved")+COUNTIFS('Problem Tracker'!$C:$C,"Recursion & Backtracking",'Problem Tracker'!$D:$D,"Backtracking",'Problem Tracker'!$E:$E,"Generate Valid Structures",'Problem Tracker'!$M:$M,"Mastered") -> 0 | N95: =IF(I95=0,0,M95/I95) -> 0
A96: Recursion & Backtracking | B96: Backtracking | C96: Constraint Satisfaction (Board / Grid) | D96: 🔥 Very High | E96: N-Queens, Sudoku, word in grid | F96: Place → recurse → undo; mark visited cells; use sets for columns/diagonals | G96: Exponential | H96: W10 | I96: =COUNTIFS('Problem Tracker'!$C:$C,"Recursion & Backtracking",'Problem Tracker'!$D:$D,"Backtracking",'Problem Tracker'!$E:$E,"Constraint Satisfaction (Board / Grid)") -> 4 | J96: =COUNTIFS('Problem Tracker'!$C:$C,"Recursion & Backtracking",'Problem Tracker'!$D:$D,"Backtracking",'Problem Tracker'!$E:$E,"Constraint Satisfaction (Board / Grid)",'Problem Tracker'!$H:$H,"Easy") -> 0 | K96: =COUNTIFS('Problem Tracker'!$C:$C,"Recursion & Backtracking",'Problem Tracker'!$D:$D,"Backtracking",'Problem Tracker'!$E:$E,"Constraint Satisfaction (Board / Grid)",'Problem Tracker'!$H:$H,"Medium") -> 1 | L96: =COUNTIFS('Problem Tracker'!$C:$C,"Recursion & Backtracking",'Problem Tracker'!$D:$D,"Backtracking",'Problem Tracker'!$E:$E,"Constraint Satisfaction (Board / Grid)",'Problem Tracker'!$H:$H,"Hard") -> 3 | M96: =COUNTIFS('Problem Tracker'!$C:$C,"Recursion & Backtracking",'Problem Tracker'!$D:$D,"Backtracking",'Problem Tracker'!$E:$E,"Constraint Satisfaction (Board / Grid)",'Problem Tracker'!$M:$M,"Solved")+COUNTIFS('Problem Tracker'!$C:$C,"Recursion & Backtracking",'Problem Tracker'!$D:$D,"Backtracking",'Problem Tracker'!$E:$E,"Constraint Satisfaction (Board / Grid)",'Problem Tracker'!$M:$M,"Mastered") -> 0 | N96: =IF(I96=0,0,M96/I96) -> 0
A97: ▌ TRIE | I97: =COUNTIF('Problem Tracker'!$C:$C,"Trie") -> 10 | M97: =COUNTIFS('Problem Tracker'!$C:$C,"Trie",'Problem Tracker'!$M:$M,"Solved")+COUNTIFS('Problem Tracker'!$C:$C,"Trie",'Problem Tracker'!$M:$M,"Mastered") -> 0 | N97: =IF(I97=0,0,M97/I97) -> 0
A98: Trie | B98: Trie Patterns | C98: Basic Trie (Insert / Search / Prefix) | D98: 🔥 Very High | E98: Prefix queries, autocomplete, dictionary roots | F98: Node{children[26], isEnd}; walk character by character | G98: O(L) per op | H98: W10 | I98: =COUNTIFS('Problem Tracker'!$C:$C,"Trie",'Problem Tracker'!$D:$D,"Trie Patterns",'Problem Tracker'!$E:$E,"Basic Trie (Insert / Search / Prefix)") -> 4 | J98: =COUNTIFS('Problem Tracker'!$C:$C,"Trie",'Problem Tracker'!$D:$D,"Trie Patterns",'Problem Tracker'!$E:$E,"Basic Trie (Insert / Search / Prefix)",'Problem Tracker'!$H:$H,"Easy") -> 0 | K98: =COUNTIFS('Problem Tracker'!$C:$C,"Trie",'Problem Tracker'!$D:$D,"Trie Patterns",'Problem Tracker'!$E:$E,"Basic Trie (Insert / Search / Prefix)",'Problem Tracker'!$H:$H,"Medium") -> 4 | L98: =COUNTIFS('Problem Tracker'!$C:$C,"Trie",'Problem Tracker'!$D:$D,"Trie Patterns",'Problem Tracker'!$E:$E,"Basic Trie (Insert / Search / Prefix)",'Problem Tracker'!$H:$H,"Hard") -> 0 | M98: =COUNTIFS('Problem Tracker'!$C:$C,"Trie",'Problem Tracker'!$D:$D,"Trie Patterns",'Problem Tracker'!$E:$E,"Basic Trie (Insert / Search / Prefix)",'Problem Tracker'!$M:$M,"Solved")+COUNTIFS('Problem Tracker'!$C:$C,"Trie",'Problem Tracker'!$D:$D,"Trie Patterns",'Problem Tracker'!$E:$E,"Basic Trie (Insert / Search / Prefix)",'Problem Tracker'!$M:$M,"Mastered") -> 0 | N98: =IF(I98=0,0,M98/I98) -> 0
A99: Trie | B99: Trie Patterns | C99: Wildcard / Fuzzy Search | D99: High | E99: '.' matches any char, one-edit matches | F99: DFS over children on wildcard | G99: O(26^k · L) | H99: W10 | I99: =COUNTIFS('Problem Tracker'!$C:$C,"Trie",'Problem Tracker'!$D:$D,"Trie Patterns",'Problem Tracker'!$E:$E,"Wildcard / Fuzzy Search") -> 2 | J99: =COUNTIFS('Problem Tracker'!$C:$C,"Trie",'Problem Tracker'!$D:$D,"Trie Patterns",'Problem Tracker'!$E:$E,"Wildcard / Fuzzy Search",'Problem Tracker'!$H:$H,"Easy") -> 0 | K99: =COUNTIFS('Problem Tracker'!$C:$C,"Trie",'Problem Tracker'!$D:$D,"Trie Patterns",'Problem Tracker'!$E:$E,"Wildcard / Fuzzy Search",'Problem Tracker'!$H:$H,"Medium") -> 2 | L99: =COUNTIFS('Problem Tracker'!$C:$C,"Trie",'Problem Tracker'!$D:$D,"Trie Patterns",'Problem Tracker'!$E:$E,"Wildcard / Fuzzy Search",'Problem Tracker'!$H:$H,"Hard") -> 0 | M99: =COUNTIFS('Problem Tracker'!$C:$C,"Trie",'Problem Tracker'!$D:$D,"Trie Patterns",'Problem Tracker'!$E:$E,"Wildcard / Fuzzy Search",'Problem Tracker'!$M:$M,"Solved")+COUNTIFS('Problem Tracker'!$C:$C,"Trie",'Problem Tracker'!$D:$D,"Trie Patterns",'Problem Tracker'!$E:$E,"Wildcard / Fuzzy Search",'Problem Tracker'!$M:$M,"Mastered") -> 0 | N99: =IF(I99=0,0,M99/I99) -> 0
A100: Trie | B100: Trie Patterns | C100: Trie + Backtracking | D100: 🔥 Very High | E100: Find many dictionary words in a grid / concatenations | F100: Build trie of words; DFS grid while trie path exists; prune | G100: O(m·n·4^L) | H100: W10 | I100: =COUNTIFS('Problem Tracker'!$C:$C,"Trie",'Problem Tracker'!$D:$D,"Trie Patterns",'Problem Tracker'!$E:$E,"Trie + Backtracking") -> 2 | J100: =COUNTIFS('Problem Tracker'!$C:$C,"Trie",'Problem Tracker'!$D:$D,"Trie Patterns",'Problem Tracker'!$E:$E,"Trie + Backtracking",'Problem Tracker'!$H:$H,"Easy") -> 0 | K100: =COUNTIFS('Problem Tracker'!$C:$C,"Trie",'Problem Tracker'!$D:$D,"Trie Patterns",'Problem Tracker'!$E:$E,"Trie + Backtracking",'Problem Tracker'!$H:$H,"Medium") -> 0 | L100: =COUNTIFS('Problem Tracker'!$C:$C,"Trie",'Problem Tracker'!$D:$D,"Trie Patterns",'Problem Tracker'!$E:$E,"Trie + Backtracking",'Problem Tracker'!$H:$H,"Hard") -> 2 | M100: =COUNTIFS('Problem Tracker'!$C:$C,"Trie",'Problem Tracker'!$D:$D,"Trie Patterns",'Problem Tracker'!$E:$E,"Trie + Backtracking",'Problem Tracker'!$M:$M,"Solved")+COUNTIFS('Problem Tracker'!$C:$C,"Trie",'Problem Tracker'!$D:$D,"Trie Patterns",'Problem Tracker'!$E:$E,"Trie + Backtracking",'Problem Tracker'!$M:$M,"Mastered") -> 0 | N100: =IF(I100=0,0,M100/I100) -> 0
...

Sheet Problem Tracker
A1: # | B1: Week | C1: Data Structure | D1: Pattern | E1: Sub-Pattern | F1: LC # | G1: Problem | H1: Difficulty | I1: Famous List | J1: Priority | K1: Premium | L1: LeetCode Link | M1: Status | N1: Date Solved | O1: Revisions | P1: Next Revision | Q1: Confidence (1-5) | R1: Notes
A2: 1 | B2: W01 | C2: Hash Map & Set | D2: Hashing Fundamentals | E2: Complement Lookup | F2: 1 | G2: Two Sum | H2: Easy | I2: ★ Blind 75 | J2: P0 | L2: https://leetcode.com/problems/two-sum/ | M2: Solved | N2: =DATE(2026,10,7) -> 46302 | O2: 1 | P2: =IF(N2="","",N2+CHOOSE(MIN(O2,3)+1,3,7,21,45)) -> 46309 | Q2: 4 | R2: Example row — map value→index; check complement before inserting
A3: 2 | B3: W01 | C3: Hash Map & Set | D3: Hashing Fundamentals | E3: Complement Lookup | F3: 1679 | G3: Max Number of K-Sum Pairs | H3: Medium | I3: Practice | J3: P2 | L3: https://leetcode.com/problems/max-number-of-k-sum-pairs/ | M3: Not Started | O3: 0 | P3: =IF(N3="","",N3+CHOOSE(MIN(O3,3)+1,3,7,21,45))
A4: 3 | B4: W01 | C4: Hash Map & Set | D4: Hashing Fundamentals | E4: Complement Lookup | F4: 454 | G4: 4Sum II | H4: Medium | I4: Practice | J4: P2 | L4: https://leetcode.com/problems/4sum-ii/ | M4: Not Started | O4: 0 | P4: =IF(N4="","",N4+CHOOSE(MIN(O4,3)+1,3,7,21,45))
A5: 4 | B5: W01 | C5: Hash Map & Set | D5: Hashing Fundamentals | E5: Frequency Counting | F5: 217 | G5: Contains Duplicate | H5: Easy | I5: ★ Blind 75 | J5: P0 | L5: https://leetcode.com/problems/contains-duplicate/ | M5: Not Started | O5: 0 | P5: =IF(N5="","",N5+CHOOSE(MIN(O5,3)+1,3,7,21,45))
A6: 5 | B6: W01 | C6: Hash Map & Set | D6: Hashing Fundamentals | E6: Frequency Counting | F6: 219 | G6: Contains Duplicate II | H6: Easy | I6: Practice | J6: P2 | L6: https://leetcode.com/problems/contains-duplicate-ii/ | M6: Not Started | O6: 0 | P6: =IF(N6="","",N6+CHOOSE(MIN(O6,3)+1,3,7,21,45))
A7: 6 | B7: W01 | C7: Hash Map & Set | D7: Hashing Fundamentals | E7: Frequency Counting | F7: 1207 | G7: Unique Number of Occurrences | H7: Easy | I7: Practice | J7: P2 | L7: https://leetcode.com/problems/unique-number-of-occurrences/ | M7: Not Started | O7: 0 | P7: =IF(N7="","",N7+CHOOSE(MIN(O7,3)+1,3,7,21,45))
A8: 7 | B8: W01 | C8: Hash Map & Set | D8: Hashing Fundamentals | E8: Frequency Counting | F8: 2352 | G8: Equal Row and Column Pairs | H8: Medium | I8: Practice | J8: P2 | L8: https://leetcode.com/problems/equal-row-and-column-pairs/ | M8: Not Started | O8: 0 | P8: =IF(N8="","",N8+CHOOSE(MIN(O8,3)+1,3,7,21,45))
A9: 8 | B9: W01 | C9: Hash Map & Set | D9: Hashing Fundamentals | E9: Grouping by Canonical Key | F9: 36 | G9: Valid Sudoku | H9: Medium | I9: ◆ NeetCode 150 | J9: P1 | L9: https://leetcode.com/problems/valid-sudoku/ | M9: Not Started | O9: 0 | P9: =IF(N9="","",N9+CHOOSE(MIN(O9,3)+1,3,7,21,45))
A10: 9 | B10: W01 | C10: Hash Map & Set | D10: Hashing Fundamentals | E10: Grouping by Canonical Key | F10: 249 | G10: Group Shifted Strings | H10: Medium | I10: Practice | J10: P2 | K10: 🔒 Yes | L10: https://leetcode.com/problems/group-shifted-strings/ | M10: Not Started | O10: 0 | P10: =IF(N10="","",N10+CHOOSE(MIN(O10,3)+1,3,7,21,45))
A11: 10 | B11: W01 | C11: Hash Map & Set | D11: Hashing Fundamentals | E11: Grouping by Canonical Key | F11: 609 | G11: Find Duplicate File in System | H11: Medium | I11: Practice | J11: P2 | L11: https://leetcode.com/problems/find-duplicate-file-in-system/ | M11: Not Started | O11: 0 | P11: =IF(N11="","",N11+CHOOSE(MIN(O11,3)+1,3,7,21,45))
A12: 11 | B12: W01 | C12: Hash Map & Set | D12: Hashing Fundamentals | E12: Set Existence / Sequence Building | F12: 349 | G12: Intersection of Two Arrays | H12: Easy | I12: Practice | J12: P2 | L12: https://leetcode.com/problems/intersection-of-two-arrays/ | M12: Not Started | O12: 0 | P12: =IF(N12="","",N12+CHOOSE(MIN(O12,3)+1,3,7,21,45))
A13: 12 | B13: W01 | C13: Hash Map & Set | D13: Hashing Fundamentals | E13: Set Existence / Sequence Building | F13: 202 | G13: Happy Number | H13: Easy | I13: ◆ NeetCode 150 | J13: P1 | L13: https://leetcode.com/problems/happy-number/ | M13: Not Started | O13: 0 | P13: =IF(N13="","",N13+CHOOSE(MIN(O13,3)+1,3,7,21,45))
A14: 13 | B14: W01 | C14: Hash Map & Set | D14: Hashing Fundamentals | E14: Set Existence / Sequence Building | F14: 128 | G14: Longest Consecutive Sequence | H14: Medium | I14: ★ Blind 75 | J14: P0 | L14: https://leetcode.com/problems/longest-consecutive-sequence/ | M14: Not Started | O14: 0 | P14: =IF(N14="","",N14+CHOOSE(MIN(O14,3)+1,3,7,21,45))
A15: 14 | B15: W02 | C15: Array | D15: Two Pointers | E15: Opposite Ends (Converging) | F15: 125 | G15: Valid Palindrome | H15: Easy | I15: ★ Blind 75 | J15: P0 | L15: https://leetcode.com/problems/valid-palindrome/ | M15: Not Started | O15: 0 | P15: =IF(N15="","",N15+CHOOSE(MIN(O15,3)+1,3,7,21,45))
A16: 15 | B16: W02 | C16: Array | D16: Two Pointers | E16: Opposite Ends (Converging) | F16: 977 | G16: Squares of a Sorted Array | H16: Easy | I16: Practice | J16: P2 | L16: https://leetcode.com/problems/squares-of-a-sorted-array/ | M16: Not Started | O16: 0 | P16: =IF(N16="","",N16+CHOOSE(MIN(O16,3)+1,3,7,21,45))
A17: 16 | B17: W02 | C17: Array | D17: Two Pointers | E17: Opposite Ends (Converging) | F17: 167 | G17: Two Sum II - Input Array Is Sorted | H17: Medium | I17: ◆ NeetCode 150 | J17: P1 | L17: https://leetcode.com/problems/two-sum-ii-input-array-is-sorted/ | M17: Not Started | O17: 0 | P17: =IF(N17="","",N17+CHOOSE(MIN(O17,3)+1,3,7,21,45))
A18: 17 | B18: W02 | C18: Array | D18: Two Pointers | E18: Opposite Ends (Converging) | F18: 11 | G18: Container With Most Water | H18: Medium | I18: ★ Blind 75 | J18: P0 | L18: https://leetcode.com/problems/container-with-most-water/ | M18: Not Started | O18: 0 | P18: =IF(N18="","",N18+CHOOSE(MIN(O18,3)+1,3,7,21,45))
A19: 18 | B19: W02 | C19: Array | D19: Two Pointers | E19: Opposite Ends (Converging) | F19: 881 | G19: Boats to Save People | H19: Medium | I19: Practice | J19: P2 | L19: https://leetcode.com/problems/boats-to-save-people/ | M19: Not Started | O19: 0 | P19: =IF(N19="","",N19+CHOOSE(MIN(O19,3)+1,3,7,21,45))
A20: 19 | B20: W02 | C20: Array | D20: Two Pointers | E20: Opposite Ends (Converging) | F20: 42 | G20: Trapping Rain Water | H20: Hard | I20: ◆ NeetCode 150 | J20: P1 | L20: https://leetcode.com/problems/trapping-rain-water/ | M20: Not Started | O20: 0 | P20: =IF(N20="","",N20+CHOOSE(MIN(O20,3)+1,3,7,21,45))
A21: 20 | B21: W02 | C21: Array | D21: Two Pointers | E21: Same Direction (Read / Write) | F21: 26 | G21: Remove Duplicates from Sorted Array | H21: Easy | I21: Practice | J21: P2 | L21: https://leetcode.com/problems/remove-duplicates-from-sorted-array/ | M21: Not Started | O21: 0 | P21: =IF(N21="","",N21+CHOOSE(MIN(O21,3)+1,3,7,21,45))
A22: 21 | B22: W02 | C22: Array | D22: Two Pointers | E22: Same Direction (Read / Write) | F22: 27 | G22: Remove Element | H22: Easy | I22: Practice | J22: P2 | L22: https://leetcode.com/problems/remove-element/ | M22: Not Started | O22: 0 | P22: =IF(N22="","",N22+CHOOSE(MIN(O22,3)+1,3,7,21,45))
... A59: 58 | B59: W03 | C59: Array | D59: Sliding Window | E59: Expand–Shrink Counting (At-Most-K Trick) | F59: 1358 | G59: Number of Substrings Containing All Three Characters | H59: Medium | I59: Practice | J59: P2 | L59: https://leetcode.com/problems/number-of-substrings-containing-all-three-characters/ | M59: Not Started | O59: 0 | P59: =IF(N59="","",N59+CHOOSE(MIN(O59,3)+1,3,7,21,45))
A60: 59 | B60: W03 | C60: Array | D60: Sliding Window | E60: Expand–Shrink Counting (At-Most-K Trick) | F60: 340 | G60: Longest Substring with At Most K Distinct Characters | H60: Medium | I60: Practice | J60: P2 | K60: 🔒 Yes | L60: https://leetcode.com/problems/longest-substring-with-at-most-k-distinct-characters/ | M60: Not Started | O60: 0 | P60: =IF(N60="","",N60+CHOOSE(MIN(O60,3)+1,3,7,21,45))
A61: 60 | B61: W03 | C61: Array | D61: Sliding Window | E61: Expand–Shrink Counting (At-Most-K Trick) | F61: 992 | G61: Subarrays with K Different Integers | H61: Hard | I61: ● Must-Know Classic | J61: P1 | L61: https://leetcode.com/problems/subarrays-with-k-different-integers/ | M61: Not Started | O61: 0 | P61: =IF(N61="","",N61+CHOOSE(MIN(O61,3)+1,3,7,21,45))
A62: 61 | B62: W03 | C62: Array | D62: Sliding Window | E62: Expand–Shrink Counting (At-Most-K Trick) | F62: 2302 | G62: Count Subarrays With Score Less Than K | H62: Hard | I62: Practice | J62: P2 | L62: https://leetcode.com/problems/count-subarrays-with-score-less-than-k/ | M62: Not Started | O62: 0 | P62: =IF(N62="","",N62+CHOOSE(MIN(O62,3)+1,3,7,21,45))
A63: 62 | B63: W03 | C63: Array | D63: Sliding Window | E63: Monotonic Window (Deque) | F63: 1438 | G63: Longest Continuous Subarray With Absolute Diff Less Than or Equal to Limit | H63: Medium | I63: Practice | J63: P2 | L63: https://leetcode.com/problems/longest-continuous-subarray-with-absolute-diff-less-than-or-equal-to-limit/ | M63: Not Started | O63: 0 | P63: =IF(N63="","",N63+CHOOSE(MIN(O63,3)+1,3,7,21,45))
A64: 63 | B64: W03 | C64: Array | D64: Sliding Window | E64: Monotonic Window (Deque) | F64: 1696 | G64: Jump Game VI | H64: Medium | I64: Practice | J64: P2 | L64: https://leetcode.com/problems/jump-game-vi/ | M64: Not Started | O64: 0 | P64: =IF(N64="","",N64+CHOOSE(MIN(O64,3)+1,3,7,21,45))
A65: 64 | B65: W03 | C65: Array | D65: Sliding Window | E65: Monotonic Window (Deque) | F65: 239 | G65: Sliding Window Maximum | H65: Hard | I65: ◆ NeetCode 150 | J65: P1 | L65: https://leetcode.com/problems/sliding-window-maximum/ | M65: Not Started | O65: 0 | P65: =IF(N65="","",N65+CHOOSE(MIN(O65,3)+1,3,7,21,45))
A66: 65 | B66: W03 | C66: Array | D66: Sliding Window | E66: Monotonic Window (Deque) | F66: 862 | G66: Shortest Subarray with Sum at Least K | H66: Hard | I66: Practice | J66: P2 | L66: https://leetcode.com/problems/shortest-subarray-with-sum-at-least-k/ | M66: Not Started | O66: 0 | P66: =IF(N66="","",N66+CHOOSE(MIN(O66,3)+1,3,7,21,45))
A67: 66 | B67: W03 | C67: Array | D67: Sliding Window | E67: Monotonic Window (Deque) | F67: 1499 | G67: Max Value of Equation | H67: Hard | I67: Practice | J67: P2 | L67: https://leetcode.com/problems/max-value-of-equation/ | M67: Not Started | O67: 0 | P67: =IF(N67="","",N67+CHOOSE(MIN(O67,3)+1,3,7,21,45))
A68: 67 | B68: W03 | C68: Array | D68: Prefix Sum | E68: 1D Prefix Sum | F68: 1480 | G68: Running Sum of 1d Array | H68: Easy | I68: Practice | J68: P2 | L68: https://leetcode.com/problems/running-sum-of-1d-array/ | M68: Not Started | O68: 0 | P68: =IF(N68="","",N68+CHOOSE(MIN(O68,3)+1,3,7,21,45))
A69: 68 | B69: W03 | C69: Array | D69: Prefix Sum | E69: 1D Prefix Sum | F69: 303 | G69: Range Sum Query - Immutable | H69: Easy | I69: Practice | J69: P2 | L69: https://leetcode.com/problems/range-sum-query-immutable/ | M69: Not Started | O69: 0 | P69: =IF(N69="","",N69+CHOOSE(MIN(O69,3)+1,3,7,21,45))
A70: 69 | B70: W03 | C70: Array | D70: Prefix Sum | E70: 1D Prefix Sum | F70: 724 | G70: Find Pivot Index | H70: Easy | I70: ● Must-Know Classic | J70: P1 | L70: https://leetcode.com/problems/find-pivot-index/ | M70: Not Started | O70: 0 | P70: =IF(N70="","",N70+CHOOSE(MIN(O70,3)+1,3,7,21,45))
A71: 70 | B71: W03 | C71: Array | D71: Prefix Sum | E71: Prefix Sum + HashMap | F71: 560 | G71: Subarray Sum Equals K | H71: Medium | I71: ● Must-Know Classic | J71: P1 | L71: https://leetcode.com/problems/subarray-sum-equals-k/ | M71: Not Started | O71: 0 | P71: =IF(N71="","",N71+CHOOSE(MIN(O71,3)+1,3,7,21,45))
A72: 71 | B72: W03 | C72: Array | D72: Prefix Sum | E72: Prefix Sum + HashMap | F72: 974 | G72: Subarray Sums Divisible by K | H72: Medium | I72: Practice | J72: P2 | L72: https://leetcode.com/problems/subarray-sums-divisible-by-k/ | M72: Not Started | O72: 0 | P72: =IF(N72="","",N72+CHOOSE(MIN(O72,3)+1,3,7,21,45))
... A119: 118 | B119: W03 | C119: String | D119: Parsing & Simulation | E119: String Building / Encoding | F119: 443 | G119: String Compression | H119: Medium | I119: Practice | J119: P2 | L119: https://leetcode.com/problems/string-compression/ | M119: Not Started | O119: 0 | P119: =IF(N119="","",N119+CHOOSE(MIN(O119,3)+1,3,7,21,45))
A120: 119 | B120: W03 | C120: String | D120: Parsing & Simulation | E120: String Building / Encoding | F120: 271 | G120: Encode and Decode Strings | H120: Medium | I120: ★ Blind 75 | J120: P0 | K120: 🔒 Yes | L120: https://leetcode.com/problems/encode-and-decode-strings/ | M120: Not Started | O120: 0 | P120: =IF(N120="","",N120+CHOOSE(MIN(O120,3)+1,3,7,21,45))
A121: 120 | B121: W03 | C121: String | D121: Parsing & Simulation | E121: String Building / Encoding | F121: 43 | G121: Multiply Strings | H121: Medium | I121: ◆ NeetCode 150 | J121: P1 | L121: https://leetcode.com/problems/multiply-strings/ | M121: Not Started | O121: 0 | P121: =IF(N121="","",N121+CHOOSE(MIN(O121,3)+1,3,7,21,45))
A122: 121 | B122: W03 | C122: String | D122: Parsing & Simulation | E122: String Building / Encoding | F122: 68 | G122: Text Justification | H122: Hard | I122: Practice | J122: P2 | L122: https://leetcode.com/problems/text-justification/ | M122: Not Started | O122: 0 | P122: =IF(N122="","",N122+CHOOSE(MIN(O122,3)+1,3,7,21,45))
A123: 122 | B123: W03 | C123: Matrix (2D Array) | D123: Matrix Manipulation | E123: Traversal Order (Spiral / Diagonal) | F123: 54 | G123: Spiral Matrix | H123: Medium | I123: ★ Blind 75 | J123: P0 | L123: https://leetcode.com/problems/spiral-matrix/ | M123: Not Started | O123: 0 | P123: =IF(N123="","",N123+CHOOSE(MIN(O123,3)+1,3,7,21,45))
A124: 123 | B124: W03 | C124: Matrix (2D Array) | D124: Matrix Manipulation | E124: Traversal Order (Spiral / Diagonal) | F124: 59 | G124: Spiral Matrix II | H124: Medium | I124: Practice | J124: P2 | L124: https://leetcode.com/problems/spiral-matrix-ii/ | M124: Not Started | O124: 0 | P124: =IF(N124="","",N124+CHOOSE(MIN(O124,3)+1,3,7,21,45))
A125: 124 | B125: W03 | C125: Matrix (2D Array) | D125: Matrix Manipulation | E125: Traversal Order (Spiral / Diagonal) | F125: 498 | G125: Diagonal Traverse | H125: Medium | I125: Practice | J125: P2 | L125: https://leetcode.com/problems/diagonal-traverse/ | M125: Not Started | O125: 0 | P125: =IF(N125="","",N125+CHOOSE(MIN(O125,3)+1,3,7,21,45))
A126: 125 | B126: W03 | C126: Matrix (2D Array) | D126: Matrix Manipulation | E126: In-place Transformation | F126: 867 | G126: Transpose Matrix | H126: Easy | I126: Practice | J126: P2 | L126: https://leetcode.com/problems/transpose-matrix/ | M126: Not Started | O126: 0 | P126: =IF(N126="","",N126+CHOOSE(MIN(O126,3)+1,3,7,21,45))
A127: 126 | B127: W03 | C127: Matrix (2D Array) | D127: Matrix Manipulation | E127: In-place Transformation | F127: 766 | G127: Toeplitz Matrix | H127: Easy | I127: Practice | J127: P2 | L127: https://leetcode.com/problems/toeplitz-matrix/ | M127: Not Started | O127: 0 | P127: =IF(N127="","",N127+CHOOSE(MIN(O127,3)+1,3,7,21,45))
A128: 127 | B128: W03 | C128: Matrix (2D Array) | D128: Matrix Manipulation | E128: In-place Transformation | F128: 48 | G128: Rotate Image | H128: Medium | I128: ★ Blind 75 | J128: P0 | L128: https://leetcode.com/problems/rotate-image/ | M128: Not Started | O128: 0 | P128: =IF(N128="","",N128+CHOOSE(MIN(O128,3)+1,3,7,21,45))
A129: 128 | B129: W03 | C129: Matrix (2D Array) | D129: Matrix Manipulation | E129: In-place Transformation | F129: 73 | G129: Set Matrix Zeroes | H129: Medium | I129: ★ Blind 75 | J129: P0 | L129: https://leetcode.com/problems/set-matrix-zeroes/ | M129: Not Started | O129: 0 | P129: =IF(N129="","",N129+CHOOSE(MIN(O129,3)+1,3,7,21,45))
A130: 129 | B130: W03 | C130: Matrix (2D Array) | D130: Matrix Manipulation | E130: In-place Transformation | F130: 289 | G130: Game of Life | H130: Medium | I130: Practice | J130: P2 | L130: https://leetcode.com/problems/game-of-life/ | M130: Not Started | O130: 0 | P130: =IF(N130="","",N130+CHOOSE(MIN(O130,3)+1,3,7,21,45))
A131: 130 | B131: W04 | C131: Stack | D131: Classic Stack | E131: Matching / Balanced Brackets | F131: 20 | G131: Valid Parentheses | H131: Easy | I131: ★ Blind 75 | J131: P0 | L131: https://leetcode.com/problems/valid-parentheses/ | M131: Not Started | O131: 0 | P131: =IF(N131="","",N131+CHOOSE(MIN(O131,3)+1,3,7,21,45))
A132: 131 | B132: W04 | C132: Stack | D132: Classic Stack | E132: Matching / Balanced Brackets | F132: 1047 | G132: Remove All Adjacent Duplicates In String | H132: Easy | I132: Practice | J132: P2 | L132: https://leetcode.com/problems/remove-all-adjacent-duplicates-in-string/ | M132: Not Started | O132: 0 | P132: =IF(N132="","",N132+CHOOSE(MIN(O132,3)+1,3,7,21,45))
... A220: 219 | B220: W06 | C220: Intervals | D220: Interval Patterns | E220: Merge / Insert | F220: 57 | G220: Insert Interval | H220: Medium | I220: ★ Blind 75 | J220: P0 | L220: https://leetcode.com/problems/insert-interval/ | M220: Not Started | O220: 0 | P220: =IF(N220="","",N220+CHOOSE(MIN(O220,3)+1,3,7,21,45))
A221: 220 | B221: W06 | C221: Intervals | D221: Interval Patterns | E221: Non-overlap Scheduling (Greedy by End) | F221: 252 | G221: Meeting Rooms | H221: Easy | I221: ★ Blind 75 | J221: P0 | K221: 🔒 Yes | L221: https://leetcode.com/problems/meeting-rooms/ | M221: Not Started | O221: 0 | P221: =IF(N221="","",N221+CHOOSE(MIN(O221,3)+1,3,7,21,45))
A222: 221 | B222: W06 | C222: Intervals | D222: Interval Patterns | E222: Non-overlap Scheduling (Greedy by End) | F222: 435 | G222: Non-overlapping Intervals | H222: Medium | I222: ★ Blind 75 | J222: P0 | L222: https://leetcode.com/problems/non-overlapping-intervals/ | M222: Not Started | O222: 0 | P222: =IF(N222="","",N222+CHOOSE(MIN(O222,3)+1,3,7,21,45))
A223: 222 | B223: W06 | C223: Intervals | D223: Interval Patterns | E223: Non-overlap Scheduling (Greedy by End) | F223: 452 | G223: Minimum Number of Arrows to Burst Balloons | H223: Medium | I223: ● Must-Know Classic | J223: P1 | L223: https://leetcode.com/problems/minimum-number-of-arrows-to-burst-balloons/ | M223: Not Started | O223: 0 | P223: =IF(N223="","",N223+CHOOSE(MIN(O223,3)+1,3,7,21,45))
A224: 223 | B224: W06 | C224: Intervals | D224: Interval Patterns | E224: Sweep Line / Concurrent Count | F224: 253 | G224: Meeting Rooms II | H224: Medium | I224: ★ Blind 75 | J224: P0 | K224: 🔒 Yes | L224: https://leetcode.com/problems/meeting-rooms-ii/ | M224: Not Started | O224: 0 | P224: =IF(N224="","",N224+CHOOSE(MIN(O224,3)+1,3,7,21,45))
A225: 224 | B225: W06 | C225: Intervals | D225: Interval Patterns | E225: Sweep Line / Concurrent Count | F225: 1851 | G225: Minimum Interval to Include Each Query | H225: Hard | I225: ◆ NeetCode 150 | J225: P1 | L225: https://leetcode.com/problems/minimum-interval-to-include-each-query/ | M225: Not Started | O225: 0 | P225: =IF(N225="","",N225+CHOOSE(MIN(O225,3)+1,3,7,21,45))
A226: 225 | B226: W06 | C226: Intervals | D226: Interval Patterns | E226: Sweep Line / Concurrent Count | F226: 2402 | G226: Meeting Rooms III | H226: Hard | I226: Practice | J226: P2 | L226: https://leetcode.com/problems/meeting-rooms-iii/ | M226: Not Started | O226: 0 | P226: =IF(N226="","",N226+CHOOSE(MIN(O226,3)+1,3,7,21,45))
A227: 226 | B227: W06 | C227: Intervals | D227: Interval Patterns | E227: Sweep Line / Concurrent Count | F227: 732 | G227: My Calendar III | H227: Hard | I227: Practice | J227: P2 | L227: https://leetcode.com/problems/my-calendar-iii/ | M227: Not Started | O227: 0 | P227: =IF(N227="","",N227+CHOOSE(MIN(O227,3)+1,3,7,21,45))
A228: 227 | B228: W06 | C228: Intervals | D228: Interval Patterns | E228: Sweep Line / Concurrent Count | F228: 218 | G228: The Skyline Problem | H228: Hard | I228: ● Must-Know Classic | J228: P1 | L228: https://leetcode.com/problems/the-skyline-problem/ | M228: Not Started | O228: 0 | P228: =IF(N228="","",N228+CHOOSE(MIN(O228,3)+1,3,7,21,45))
A229: 228 | B229: W06 | C229: Intervals | D229: Interval Patterns | E229: Intersection / Booking | F229: 986 | G229: Interval List Intersections | H229: Medium | I229: Practice | J229: P2 | L229: https://leetcode.com/problems/interval-list-intersections/ | M229: Not Started | O229: 0 | P229: =IF(N229="","",N229+CHOOSE(MIN(O229,3)+1,3,7,21,45))
A230: 229 | B230: W06 | C230: Intervals | D230: Interval Patterns | E230: Intersection / Booking | F230: 729 | G230: My Calendar I | H230: Medium | I230: Practice | J230: P2 | L230: https://leetcode.com/problems/my-calendar-i/ | M230: Not Started | O230: 0 | P230: =IF(N230="","",N230+CHOOSE(MIN(O230,3)+1,3,7,21,45))
A231: 230 | B231: W06 | C231: Intervals | D231: Interval Patterns | E231: Intersection / Booking | F231: 759 | G231: Employee Free Time | H231: Hard | I231: Practice | J231: P2 | K231: 🔒 Yes | L231: https://leetcode.com/problems/employee-free-time/ | M231: Not Started | O231: 0 | P231: =IF(N231="","",N231+CHOOSE(MIN(O231,3)+1,3,7,21,45))
A232: 231 | B232: W07 | C232: Trees | D232: DFS Traversal | E232: Pre / In / Post-order (Recursive & Iterative) | F232: 144 | G232: Binary Tree Preorder Traversal | H232: Easy | I232: Practice | J232: P2 | L232: https://leetcode.com/problems/binary-tree-preorder-traversal/ | M232: Not Started | O232: 0 | P232: =IF(N232="","",N232+CHOOSE(MIN(O232,3)+1,3,7,21,45))
A233: 232 | B233: W07 | C233: Trees | D233: DFS Traversal | E233: Pre / In / Post-order (Recursive & Iterative) | F233: 94 | G233: Binary Tree Inorder Traversal | H233: Easy | I233: ● Must-Know Classic | J233: P1 | L233: https://leetcode.com/problems/binary-tree-inorder-traversal/ | M233: Not Started | O233: 0 | P233: =IF(N233="","",N233+CHOOSE(MIN(O233,3)+1,3,7,21,45))
A234: 233 | B234: W07 | C234: Trees | D234: DFS Traversal | E234: Pre / In / Post-order (Recursive & Iterative) | F234: 145 | G234: Binary Tree Postorder Traversal | H234: Easy | I234: Practice | J234: P2 | L234: https://leetcode.com/problems/binary-tree-postorder-traversal/ | M234: Not Started | O234: 0 | P234: =IF(N234="","",N234+CHOOSE(MIN(O234,3)+1,3,7,21,45))
A235: 234 | B235: W07 | C235: Trees | D235: DFS Traversal | E235: Structural Comparison | F235: 100 | G235: Same Tree | H235: Easy | I235: ★ Blind 75 | J235: P0 | L235: https://leetcode.com/problems/same-tree/ | M235: Not Started | O235: 0 | P235: =IF(N235="","",N235+CHOOSE(MIN(O235,3)+1,3,7,21,45))
A236: 235 | B236: W07 | C236: Trees | D236: DFS Traversal | E236: Structural Comparison | F236: 226 | G236: Invert Binary Tree | H236: Easy | I236: ★ Blind 75 | J236: P0 | L236: https://leetcode.com/problems/invert-binary-tree/ | M236: Not Started | O236: 0 | P236: =IF(N236="","",N236+CHOOSE(MIN(O236,3)+1,3,7,21,45))
A237: 236 | B237: W07 | C237: Trees | D237: DFS Traversal | E237: Structural Comparison | F237: 101 | G237: Symmetric Tree | H237: Easy | I237: ● Must-Know Classic | J237: P1 | L237: https://leetcode.com/problems/symmetric-tree/ | M237: Not Started | O237: 0 | P237: =IF(N237="","",N237+CHOOSE(MIN(O237,3)+1,3,7,21,45))
A238: 237 | B238: W07 | C238: Trees | D238: DFS Traversal | E238: Structural Comparison | F238: 572 | G238: Subtree of Another Tree | H238: Easy | I238: ★ Blind 75 | J238: P0 | L238: https://leetcode.com/problems/subtree-of-another-tree/ | M238: Not Started | O238: 0 | P238: =IF(N238="","",N238+CHOOSE(MIN(O238,3)+1,3,7,21,45))
A239: 238 | B239: W07 | C239: Trees | D239: DFS Traversal | E239: Structural Comparison | F239: 617 | G239: Merge Two Binary Trees | H239: Easy | I239: Practice | J239: P2 | L239: https://leetcode.com/problems/merge-two-binary-trees/ | M239: Not Started | O239: 0 | P239: =IF(N239="","",N239+CHOOSE(MIN(O239,3)+1,3,7,21,45))
A240: 239 | B240: W07 | C240: Trees | D240: DFS Traversal | E240: Structural Comparison | F240: 872 | G240: Leaf-Similar Trees | H240: Easy | I240: Practice | J240: P2 | L240: https://leetcode.com/problems/leaf-similar-trees/ | M240: Not Started | O240: 0 | P240: =IF(N240="","",N240+CHOOSE(MIN(O240,3)+1,3,7,21,45))
A241: 240 | B241: W07 | C241: Trees | D241: BFS / Level Order | E241: Level-by-Level Processing | F241: 637 | G241: Average of Levels in Binary Tree | H241: Easy | I241: Practice | J241: P2 | L241: https://leetcode.com/problems/average-of-levels-in-binary-tree/ | M241: Not Started | O241: 0 | P241: =IF(N241="","",N241+CHOOSE(MIN(O241,3)+1,3,7,21,45))
A242: 241 | B242: W07 | C242: Trees | D242: BFS / Level Order | E242: Level-by-Level Processing | F242: 102 | G242: Binary Tree Level Order Traversal | H242: Medium | I242: ★ Blind 75 | J242: P0 | L242: https://leetcode.com/problems/binary-tree-level-order-traversal/ | M242: Not Started | O242: 0 | P242: =IF(N242="","",N242+CHOOSE(MIN(O242,3)+1,3,7,21,45))
A243: 242 | B243: W07 | C243: Trees | D243: BFS / Level Order | E243: Level-by-Level Processing | F243: 103 | G243: Binary Tree Zigzag Level Order Traversal | H243: Medium | I243: ● Must-Know Classic | J243: P1 | L243: https://leetcode.com/problems/binary-tree-zigzag-level-order-traversal/ | M243: Not Started | O243: 0 | P243: =IF(N243="","",N243+CHOOSE(MIN(O243,3)+1,3,7,21,45))
... A341: 340 | B341: W11 | C341: Graphs | D341: Grid Graphs (DFS / BFS) | E341: Flood Fill / Connected Islands | F341: 695 | G341: Max Area of Island | H341: Medium | I341: ◆ NeetCode 150 | J341: P1 | L341: https://leetcode.com/problems/max-area-of-island/ | M341: Not Started | O341: 0 | P341: =IF(N341="","",N341+CHOOSE(MIN(O341,3)+1,3,7,21,45))
A342: 341 | B342: W11 | C342: Graphs | D342: Grid Graphs (DFS / BFS) | E342: Flood Fill / Connected Islands | F342: 694 | G342: Number of Distinct Islands | H342: Medium | I342: Practice | J342: P2 | K342: 🔒 Yes | L342: https://leetcode.com/problems/number-of-distinct-islands/ | M342: Not Started | O342: 0 | P342: =IF(N342="","",N342+CHOOSE(MIN(O342,3)+1,3,7,21,45))
A343: 342 | B343: W11 | C343: Graphs | D343: Grid Graphs (DFS / BFS) | E343: Boundary DFS (Reverse Thinking) | F343: 130 | G343: Surrounded Regions | H343: Medium | I343: ◆ NeetCode 150 | J343: P1 | L343: https://leetcode.com/problems/surrounded-regions/ | M343: Not Started | O343: 0 | P343: =IF(N343="","",N343+CHOOSE(MIN(O343,3)+1,3,7,21,45))
A344: 343 | B344: W11 | C344: Graphs | D344: Grid Graphs (DFS / BFS) | E344: Boundary DFS (Reverse Thinking) | F344: 417 | G344: Pacific Atlantic Water Flow | H344: Medium | I344: ★ Blind 75 | J344: P0 | L344: https://leetcode.com/problems/pacific-atlantic-water-flow/ | M344: Not Started | O344: 0 | P344: =IF(N344="","",N344+CHOOSE(MIN(O344,3)+1,3,7,21,45))
A345: 344 | B345: W11 | C345: Graphs | D345: Grid Graphs (DFS / BFS) | E345: Boundary DFS (Reverse Thinking) | F345: 1020 | G345: Number of Enclaves | H345: Medium | I345: Practice | J345: P2 | L345: https://leetcode.com/problems/number-of-enclaves/ | M345: Not Started | O345: 0 | P345: =IF(N345="","",N345+CHOOSE(MIN(O345,3)+1,3,7,21,45))
A346: 345 | B346: W11 | C346: Graphs | D346: Grid Graphs (DFS / BFS) | E346: Boundary DFS (Reverse Thinking) | F346: 1254 | G346: Number of Closed Islands | H346: Medium | I346: Practice | J346: P2 | L346: https://leetcode.com/problems/number-of-closed-islands/ | M346: Not Started | O346: 0 | P346: =IF(N346="","",N346+CHOOSE(MIN(O346,3)+1,3,7,21,45))
A347: 346 | B347: W11 | C347: Graphs | D347: Grid Graphs (DFS / BFS) | E347: Multi-source BFS | F347: 994 | G347: Rotting Oranges | H347: Medium | I347: ◆ NeetCode 150 | J347: P1 | L347: https://leetcode.com/problems/rotting-oranges/ | M347: Not Started | O347: 0 | P347: =IF(N347="","",N347+CHOOSE(MIN(O347,3)+1,3,7,21,45))
A348: 347 | B348: W11 | C348: Graphs | D348: Grid Graphs (DFS / BFS) | E348: Multi-source BFS | F348: 542 | G348: 01 Matrix | H348: Medium | I348: ● Must-Know Classic | J348: P1 | L348: https://leetcode.com/problems/01-matrix/ | M348: Not Started | O348: 0 | P348: =IF(N348="","",N348+CHOOSE(MIN(O348,3)+1,3,7,21,45))
A349: 348 | B349: W11 | C349: Graphs | D349: Grid Graphs (DFS / BFS) | E349: Multi-source BFS | F349: 286 | G349: Walls and Gates | H349: Medium | I349: ◆ NeetCode 150 | J349: P1 | K349: 🔒 Yes | L349: https://leetcode.com/problems/walls-and-gates/ | M349: Not Started | O349: 0 | P349: =IF(N349="","",N349+CHOOSE(MIN(O349,3)+1,3,7,21,45))
A350: 349 | B350: W11 | C350: Graphs | D350: Grid Graphs (DFS / BFS) | E350: Multi-source BFS | F350: 1162 | G350: As Far from Land as Possible | H350: Medium | I350: Practice | J350: P2 | L350: https://leetcode.com/problems/as-far-from-land-as-possible/ | M350: Not Started | O350: 0 | P350: =IF(N350="","",N350+CHOOSE(MIN(O350,3)+1,3,7,21,45))
A351: 350 | B351: W11 | C351: Graphs | D351: Grid Graphs (DFS / BFS) | E351: Multi-source BFS | F351: 1765 | G351: Map of Highest Peak | H351: Medium | I351: Practice | J351: P2 | L351: https://leetcode.com/problems/map-of-highest-peak/ | M351: Not Started | O351: 0 | P351: =IF(N351="","",N351+CHOOSE(MIN(O351,3)+1,3,7,21,45))
A352: 351 | B352: W11 | C352: Graphs | D352: Graph Traversal | E352: Adjacency List DFS / BFS | F352: 1971 | G352: Find if Path Exists in Graph | H352: Easy | I352: Practice | J352: P2 | L352: https://leetcode.com/problems/find-if-path-exists-in-graph/ | M352: Not Started | O352: 0 | P352: =IF(N352="","",N352+CHOOSE(MIN(O352,3)+1,3,7,21,45))
A353: 352 | B353: W11 | C353: Graphs | D353: Graph Traversal | E353: Adjacency List DFS / BFS | F353: 997 | G353: Find the Town Judge | H353: Easy | I353: Practice | J353: P2 | L353: https://leetcode.com/problems/find-the-town-judge/ | M353: Not Started | O353: 0 | P353: =IF(N353="","",N353+CHOOSE(MIN(O353,3)+1,3,7,21,45))
A354: 353 | B354: W11 | C354: Graphs | D354: Graph Traversal | E354: Adjacency List DFS / BFS | F354: 133 | G354: Clone Graph | H354: Medium | I354: ★ Blind 75 | J354: P0 | L354: https://leetcode.com/problems/clone-graph/ | M354: Not Started | O354: 0 | P354: =IF(N354="","",N354+CHOOSE(MIN(O354,3)+1,3,7,21,45))
A355: 354 | B355: W11 | C355: Graphs | D355: Graph Traversal | E355: Adjacency List DFS / BFS | F355: 547 | G355: Number of Provinces | H355: Medium | I355: ● Must-Know Classic | J355: P1 | L355: https://leetcode.com/problems/number-of-provinces/ | M355: Not Started | O355: 0 | P355: =IF(N355="","",N355+CHOOSE(MIN(O355,3)+1,3,7,21,45))
A356: 355 | B356: W11 | C356: Graphs | D356: Graph Traversal | E356: Adjacency List DFS / BFS | F356: 841 | G356: Keys and Rooms | H356: Medium | I356: Practice | J356: P2 | L356: https://leetcode.com/problems/keys-and-rooms/ | M356: Not Started | O356: 0 | P356: =IF(N356="","",N356+CHOOSE(MIN(O356,3)+1,3,7,21,45))
A357: 356 | B357: W11 | C357: Graphs | D357: Graph Traversal | E357: Adjacency List DFS / BFS | F357: 323 | G357: Number of Connected Components in an Undirected Graph | H357: Medium | I357: ★ Blind 75 | J357: P0 | K357: 🔒 Yes | L357: https://leetcode.com/problems/number-of-connected-components-in-an-undirected-graph/ | M357: Not Started | O357: 0 | P357: =IF(N357="","",N357+CHOOSE(MIN(O357,3)+1,3,7,21,45))
A358: 357 | B358: W11 | C358: Graphs | D358: Graph Traversal | E358: Adjacency List DFS / BFS | F358: 1466 | G358: Reorder Routes to Make All Paths Lead to the City Zero | H358: Medium | I358: Practice | J358: P2 | L358: https://leetcode.com/problems/reorder-routes-to-make-all-paths-lead-to-the-city-zero/ | M358: Not Started | O358: 0 | P358: =IF(N358="","",N358+CHOOSE(MIN(O358,3)+1,3,7,21,45))
A359: 358 | B359: W11 | C359: Graphs | D359: Graph Traversal | E359: Adjacency List DFS / BFS | F359: 399 | G359: Evaluate Division | H359: Medium | I359: ● Must-Know Classic | J359: P1 | L359: https://leetcode.com/problems/evaluate-division/ | M359: Not Started | O359: 0 | P359: =IF(N359="","",N359+CHOOSE(MIN(O359,3)+1,3,7,21,45))
A360: 359 | B360: W11 | C360: Graphs | D360: Graph Traversal | E360: BFS Shortest Path (Unweighted) | F360: 1091 | G360: Shortest Path in Binary Matrix | H360: Medium | I360: Practice | J360: P2 | L360: https://leetcode.com/problems/shortest-path-in-binary-matrix/ | M360: Not Started | O360: 0 | P360: =IF(N360="","",N360+CHOOSE(MIN(O360,3)+1,3,7,21,45))
A361: 360 | B361: W11 | C361: Graphs | D361: Graph Traversal | E361: BFS Shortest Path (Unweighted) | F361: 1926 | G361: Nearest Exit from Entrance in Maze | H361: Medium | I361: Practice | J361: P2 | L361: https://leetcode.com/problems/nearest-exit-from-entrance-in-maze/ | M361: Not Started | O361: 0 | P361: =IF(N361="","",N361+CHOOSE(MIN(O361,3)+1,3,7,21,45))
A362: 361 | B362: W11 | C362: Graphs | D362: Graph Traversal | E362: BFS Shortest Path (Unweighted) | F362: 752 | G362: Open the Lock | H362: Medium | I362: Practice | J362: P2 | L362: https://leetcode.com/problems/open-the-lock/ | M362: Not Started | O362: 0 | P362: =IF(N362="","",N362+CHOOSE(MIN(O362,3)+1,3,7,21,45))
A363: 362 | B363: W11 | C363: Graphs | D363: Graph Traversal | E363: BFS Shortest Path (Unweighted) | F363: 433 | G363: Minimum Genetic Mutation | H363: Medium | I363: Practice | J363: P2 | L363: https://leetcode.com/problems/minimum-genetic-mutation/ | M363: Not Started | O363: 0 | P363: =IF(N363="","",N363+CHOOSE(MIN(O363,3)+1,3,7,21,45))
A364: 363 | B364: W11 | C364: Graphs | D364: Graph Traversal | E364: BFS Shortest Path (Unweighted) | F364: 909 | G364: Snakes and Ladders | H364: Medium | I364: Practice | J364: P2 | L364: https://leetcode.com/problems/snakes-and-ladders/ | M364: Not Started | O364: 0 | P364: =IF(N364="","",N364+CHOOSE(MIN(O364,3)+1,3,7,21,45))
A365: 364 | B365: W11 | C365: Graphs | D365: Graph Traversal | E365: BFS Shortest Path (Unweighted) | F365: 127 | G365: Word Ladder | H365: Hard | I365: ◆ NeetCode 150 | J365: P1 | L365: https://leetcode.com/problems/word-ladder/ | M365: Not Started | O365: 0 | P365: =IF(N365="","",N365+CHOOSE(MIN(O365,3)+1,3,7,21,45))
A366: 365 | B366: W11 | C366: Graphs | D366: Graph Traversal | E366: BFS Shortest Path (Unweighted) | F366: 815 | G366: Bus Routes | H366: Hard | I366: Practice | J366: P2 | L366: https://leetcode.com/problems/bus-routes/ | M366: Not Started | O366: 0 | P366: =IF(N366="","",N366+CHOOSE(MIN(O366,3)+1,3,7,21,45))
...

Sheet How to Use
A1: HOW TO USE THIS TRACKER
A3: SHEETS
A4: Dashboard | B4: Overall KPIs, progress by data structure, difficulty, famous list and the 17-week plan. Fully formula-driven.
A5: Pattern Map | B5: Hierarchy: Data Structure → Pattern → Sub-Pattern, with how to recognise it, the core template, complexity and live problem counts.
A6: Problem Tracker | B6: Every problem with its LeetCode link. Click the problem name or the link to open it. Filter by any column.
A7: CELLS YOU EDIT
A8: Status | B8: Dropdown: Not Started → In Progress → Solved → Revise → Mastered. 'Mastered' strikes the title through.
A9: Date Solved | B9: Date you first solved it (or last revised). Drives Next Revision.
A10: Revisions | B10: How many times you've re-solved it. Next Revision = Date + 3 / 7 / 21 / 45 days (spaced repetition).
A11: Confidence (1-5) | B11: 1–2 turns red (redo soon), 4–5 turns green.
A12: Notes | B12: One line on the key insight — this is what you revise before interviews. Row 2 is a filled example; overwrite it.
A13: COLOUR LEGEND
A14: Easy | B14: Difficulty tag
A15: Medium | B15: Difficulty tag
A16: Hard | B16: Difficulty tag
A17: ★ Blind 75 | B17: The original 75 most-repeated interview problems — Priority P0. Do these first.
A18: ◆ NeetCode 150 | B18: Additional problems from the NeetCode 150 list (Blind 75 + these ≈ NeetCode 150) — P1.
A19: ● Must-Know Classic | B19: Frequently asked classics outside those two lists (LFU, Next Permutation, Subarray Sum = K…) — P1.
A20: Practice | B20: Extra depth for the pattern — P2. Do after P0/P1 of the same sub-pattern.
A21: 🔥 Very High | B21: Interview weight of a sub-pattern (Pattern Map) — appears in most loops.
A22: Next Revision (orange) | B22: Revision date has arrived — redo the problem without looking at your old code.
A23: 🔒 Premium | B23: Needs LeetCode Premium. Free mirrors exist on NeetCode.io / LintCode for most.
A24: RECOMMENDED WORKFLOW
A25: 1. Learn the pattern | B25: Read the Pattern Map row: trigger + template. Write the template from memory once.
A26: 2. Solve in order | B26: Within each sub-pattern problems are ordered Easy → Medium → Hard. Do P0/P1 first, P2 if time allows.
A27: 3. Time-box | B27: 25 min Easy, 40 min Medium, 60 min Hard. Stuck → read the approach only, then code it yourself.
A28: 4. Say it out loud | B28: Product-company interviews grade communication: state brute force, complexity, then optimise.
A29: 5. Revise | B29: Filter Next Revision ≤ today every morning. Mark 'Mastered' only after solving cold twice.
